{
  "type": "Feature",
  "properties": {
    "gn:admin1_code":"23",
    "gn:asciiname":"Arabuko",
    "gn:country_code":"KE",
    "gn:dem":64,
    "gn:feature_class":"P",
    "gn:feature_code":"PPL",
    "gn:name":"Arabuko",
    "gn:population":0,
    "gn:timezone":"Africa/Nairobi",
    "iso:country":"KE",
    "wof:name":"Arabuko",
    "wof:placetype":"locality"
},
  "geometry": {"coordinates":[39.97445,-3.256],"type":"Point"}
}