{
  "type": "Feature",
  "properties": {
    "gn:admin1_code":"32.0",
    "gn:asciiname":"Masimbani",
    "gn:country_code":"KE",
    "gn:dem":664,
    "gn:feature_class":"P",
    "gn:feature_code":"PPL",
    "gn:name":"Masimbani",
    "gn:population":0,
    "gn:timezone":"Africa/Nairobi",
    "iso:country":"KE",
    "wof:name":"Masimbani",
    "wof:placetype":"locality"
},
  "geometry": {"coordinates":[38.126,-2.36714],"type":"Point"}
}