{
  "type": "Feature",
  "properties": {
    "gn:admin1_code":"38.0",
    "gn:asciiname":"Kagundu",
    "gn:country_code":"KE",
    "gn:dem":2133,
    "gn:feature_class":"P",
    "gn:feature_code":"PPL",
    "gn:name":"Kagundu",
    "gn:population":0,
    "gn:timezone":"Africa/Nairobi",
    "iso:country":"KE",
    "name:und_x_variant":[
        "Kagondu",
        "Kagundu"
    ],
    "wof:name":"Kagundu",
    "wof:placetype":"locality"
},
  "geometry": {"coordinates":[36.85768,-0.76019],"type":"Point"}
}