{
  "type": "Feature",
  "properties": {
    "gn:gn_country":"KE",
    "gn:gn_fcode":"PPL",
    "gn:gn_pop":13377,
    "gn:population":13377,
    "iso:country":"KE",
    "name:ceb_x_preferred":[
        "Taveta"
    ],
    "name:deu_x_preferred":[
        "Taveta"
    ],
    "name:eng_x_preferred":[
        "Taveta"
    ],
    "name:fra_x_preferred":[
        "Taveta"
    ],
    "name:jpn_x_preferred":[
        "\u30bf\u30f4\u30a7\u30bf"
    ],
    "name:nld_x_preferred":[
        "Taveta"
    ],
    "name:pol_x_preferred":[
        "Taveta"
    ],
    "name:spa_x_preferred":[
        "Taveta"
    ],
    "name:swa_x_preferred":[
        "Taveta"
    ],
    "name:swe_x_preferred":[
        "Taveta"
    ],
    "name:zho_x_preferred":[
        "\u5854\u97cb\u5854"
    ],
    "qs_pg:aaroncc":"KE",
    "qs_pg:gn_country":"KE",
    "qs_pg:gn_fcode":"PPL",
    "qs_pg:gn_pop":13377,
    "qs_pg:name":"Taveta",
    "qs_pg:photos_9r":0,
    "qs_pg:photos_sr":0,
    "qs_pg:pop_sr":6,
    "qs_pg:qs_pg_placetype":"locality",
    "wof:name":"Taveta",
    "wof:placetype":"locality",
    "wof:population":13377
},
  "geometry": {"coordinates":[37.68336,-3.39879],"type":"Point"}
}