{
  "type": "Feature",
  "properties": {
    "gn:admin1_code":"51",
    "gn:asciiname":"Kanamkemer",
    "gn:country_code":"KE",
    "gn:dem":516,
    "gn:feature_class":"P",
    "gn:feature_code":"PPL",
    "gn:name":"Kanamkemer",
    "gn:population":0,
    "gn:timezone":"Africa/Nairobi",
    "iso:country":"KE",
    "wof:name":"Kanamkemer",
    "wof:placetype":"locality"
},
  "geometry": {"coordinates":[35.6015,3.10125],"type":"Point"}
}