{
  "type": "Feature",
  "properties": {
    "iso:country":"KE",
    "name:ceb_x_preferred":[
        "Kikuyu"
    ],
    "name:deu_x_preferred":[
        "Kikuyu"
    ],
    "name:eng_x_preferred":[
        "Kikuyu"
    ],
    "name:jpn_x_preferred":[
        "\u30ad\u30af\u30e6"
    ],
    "name:kik_x_preferred":[
        "Kikuyu"
    ],
    "name:nld_x_preferred":[
        "Kikuyu"
    ],
    "name:nob_x_preferred":[
        "Kikuyu"
    ],
    "name:nor_x_preferred":[
        "Kikuyu"
    ],
    "name:pol_x_preferred":[
        "Kikuyu"
    ],
    "name:spa_x_preferred":[
        "Kikuyu"
    ],
    "name:swa_x_preferred":[
        "Kikuyu"
    ],
    "name:swe_x_preferred":[
        "Kikuyu"
    ],
    "name:unk_x_variant":[
        "Gikuyu"
    ],
    "name:urd_x_preferred":[
        "\u06a9\u06cc\u06a9\u0648\u06cc\u0648\u060c \u06a9\u06cc\u0646\u06cc\u0627"
    ],
    "name:urd_x_variant":[
        "\u06a9\u06cc\u06a9\u0648\u06cc\u0648"
    ],
    "qs:gn_country":"KE",
    "qs:gn_fcode":"PPL",
    "qs:gn_pop":3953,
    "qs:name":"Kikuyu",
    "qs:name_adm0":"Kenya",
    "qs:name_adm1":"Central",
    "qs:photos":0,
    "qs:photos_1k":0,
    "qs:photos_9k":1,
    "qs:photos_9r":1,
    "qs:photos_all":13,
    "qs:photos_sr":0,
    "qs:placetype":"Town",
    "qs:pop_sr":"4",
    "qs:woe_adm0":23424863,
    "wd:wordcount":775,
    "wof:name":"Kikuyu",
    "wof:placetype":"locality",
    "wof:population":3953
},
  "geometry": {"coordinates":[36.66328,-1.24576],"type":"Point"}
}