{
  "type": "Feature",
  "properties": {
    "gn:admin1_code":"26",
    "gn:asciiname":"Kombewa",
    "gn:country_code":"KE",
    "gn:dem":1207,
    "gn:feature_class":"P",
    "gn:feature_code":"PPL",
    "gn:name":"Kombewa",
    "gn:population":0,
    "gn:timezone":"Africa/Nairobi",
    "iso:country":"KE",
    "wof:name":"Kombewa",
    "wof:placetype":"locality"
},
  "geometry": {"coordinates":[34.5205,-0.10643],"type":"Point"}
}