{
  "type": "Feature",
  "properties": {
    "gn:admin1_code":"15.0",
    "gn:asciiname":"Mashamba",
    "gn:country_code":"KE",
    "gn:dem":1090,
    "gn:feature_class":"P",
    "gn:feature_code":"PPL",
    "gn:name":"Mashamba",
    "gn:population":0,
    "gn:timezone":"Africa/Nairobi",
    "iso:country":"KE",
    "wof:name":"Mashamba",
    "wof:placetype":"locality"
},
  "geometry": {"coordinates":[37.51261,-0.75631],"type":"Point"}
}