{
  "type": "Feature",
  "properties": {
    "gn:admin1_code":"36.0",
    "gn:asciiname":"Suna",
    "gn:country_code":"KE",
    "gn:dem":1351,
    "gn:feature_class":"P",
    "gn:feature_code":"PPL",
    "gn:name":"Suna",
    "gn:population":0,
    "gn:timezone":"Africa/Nairobi",
    "iso:country":"KE",
    "name:bel_x_preferred":[
        "\u0421\u0443\u043d\u0430"
    ],
    "name:cat_x_preferred":[
        "Suna"
    ],
    "name:ceb_x_preferred":[
        "Suna"
    ],
    "name:deu_x_preferred":[
        "Suna"
    ],
    "name:ita_x_preferred":[
        "Suna"
    ],
    "name:lit_x_preferred":[
        "Suna"
    ],
    "name:rus_x_preferred":[
        "\u0421\u0443\u043d\u0430"
    ],
    "name:swe_x_preferred":[
        "Suna"
    ],
    "name:tur_x_preferred":[
        "Suna"
    ],
    "wof:name":"Suna",
    "wof:placetype":"locality"
},
  "geometry": {"coordinates":[34.45421,-1.09639],"type":"Point"}
}