{
  "type": "Feature",
  "properties": {
    "gn:admin1_code":"48.0",
    "gn:asciiname":"Kulelet",
    "gn:country_code":"KE",
    "gn:dem":230,
    "gn:feature_class":"P",
    "gn:feature_code":"PPL",
    "gn:name":"Kulelet",
    "gn:population":0,
    "gn:timezone":"Africa/Nairobi",
    "iso:country":"KE",
    "wof:name":"Kulelet",
    "wof:placetype":"locality"
},
  "geometry": {"coordinates":[39.15,-2.03333],"type":"Point"}
}