{
  "type": "Feature",
  "properties": {
    "gn:admin1_code":"26.0",
    "gn:asciiname":"Rabour",
    "gn:country_code":"KE",
    "gn:dem":1148,
    "gn:feature_class":"P",
    "gn:feature_code":"PPL",
    "gn:name":"Rabour",
    "gn:population":0,
    "gn:timezone":"Africa/Nairobi",
    "iso:country":"KE",
    "name:und_x_variant":[
        "Rabwor",
        "Rabur",
        "Rabour"
    ],
    "wof:name":"Rabour",
    "wof:placetype":"locality"
},
  "geometry": {"coordinates":[34.8249,-0.14958],"type":"Point"}
}