{
  "type": "Feature",
  "properties": {
    "gn:admin1_code":"38.0",
    "gn:asciiname":"Thaara",
    "gn:country_code":"KE",
    "gn:dem":1197,
    "gn:feature_class":"P",
    "gn:feature_code":"PPL",
    "gn:name":"Thaara",
    "gn:population":0,
    "gn:timezone":"Africa/Nairobi",
    "iso:country":"KE",
    "name:und_x_variant":[
        "Thara",
        "Thaara"
    ],
    "wof:name":"Thaara",
    "wof:placetype":"locality"
},
  "geometry": {"coordinates":[37.2158,-0.79922],"type":"Point"}
}