{
  "type": "Feature",
  "properties": {
    "gn:admin1_code":"28",
    "gn:asciiname":"Kizibe",
    "gn:country_code":"KE",
    "gn:dem":219,
    "gn:feature_class":"P",
    "gn:feature_code":"PPL",
    "gn:name":"Kizibe",
    "gn:population":0,
    "gn:timezone":"Africa/Nairobi",
    "iso:country":"KE",
    "wof:name":"Kizibe",
    "wof:placetype":"locality"
},
  "geometry": {"coordinates":[39.30177,-4.25653],"type":"Point"}
}