{
  "type": "Feature",
  "properties": {
    "gn:admin1_code":"22.0",
    "gn:asciiname":"Gichiengo",
    "gn:country_code":"KE",
    "gn:dem":2485,
    "gn:feature_class":"P",
    "gn:feature_code":"PPL",
    "gn:name":"Gichiengo",
    "gn:population":0,
    "gn:timezone":"Africa/Nairobi",
    "iso:country":"KE",
    "wof:name":"Gichiengo",
    "wof:placetype":"locality"
},
  "geometry": {"coordinates":[36.61762,-0.94263],"type":"Point"}
}