{
  "type": "Feature",
  "properties": {
    "gn:admin1_code":"08",
    "gn:asciiname":"Mau Summit",
    "gn:country_code":"KE",
    "gn:dem":2536,
    "gn:feature_class":"P",
    "gn:feature_code":"PPL",
    "gn:name":"Mau Summit",
    "gn:population":0,
    "gn:timezone":"Africa/Nairobi",
    "iso:country":"KE",
    "wof:name":"Mau Summit",
    "wof:placetype":"locality"
},
  "geometry": {"coordinates":[35.69316,-0.16074],"type":"Point"}
}