{
  "type": "Feature",
  "properties": {
    "gn:admin1_code":"39",
    "gn:asciiname":"Kuresoi",
    "gn:country_code":"KE",
    "gn:dem":2551,
    "gn:feature_class":"P",
    "gn:feature_code":"PPL",
    "gn:name":"Kuresoi",
    "gn:population":0,
    "gn:timezone":"Africa/Nairobi",
    "iso:country":"KE",
    "wof:name":"Kuresoi",
    "wof:placetype":"locality"
},
  "geometry": {"coordinates":[35.52174,-0.30088],"type":"Point"}
}