{
  "type": "Feature",
  "properties": {
    "gn:admin1_code":"48",
    "gn:asciiname":"Mikameni",
    "gn:country_code":"KE",
    "gn:dem":26,
    "gn:feature_class":"P",
    "gn:feature_code":"PPL",
    "gn:name":"Mikameni",
    "gn:population":0,
    "gn:timezone":"Africa/Nairobi",
    "iso:country":"KE",
    "wof:name":"Mikameni",
    "wof:placetype":"locality"
},
  "geometry": {"coordinates":[40.16176,-2.0651],"type":"Point"}
}