{
  "type": "Feature",
  "properties": {
    "gn:admin1_code":"48.0",
    "gn:asciiname":"Furaha",
    "gn:country_code":"KE",
    "gn:dem":10,
    "gn:feature_class":"P",
    "gn:feature_code":"PPL",
    "gn:name":"Furaha",
    "gn:population":0,
    "gn:timezone":"Africa/Nairobi",
    "iso:country":"KE",
    "name:und_x_variant":[
        "Furaka",
        "Furaha"
    ],
    "wof:name":"Furaha",
    "wof:placetype":"locality"
},
  "geometry": {"coordinates":[40.21023,-2.48175],"type":"Point"}
}