{
  "type": "Feature",
  "properties": {
    "gn:admin1_code":"13",
    "gn:asciiname":"Bumudondo",
    "gn:country_code":"KE",
    "gn:dem":1142,
    "gn:feature_class":"P",
    "gn:feature_code":"PPL",
    "gn:name":"Bumudondo",
    "gn:population":0,
    "gn:timezone":"Africa/Nairobi",
    "iso:country":"KE",
    "wof:name":"Bumudondo",
    "wof:placetype":"locality"
},
  "geometry": {"coordinates":[34.03333,0.06667],"type":"Point"}
}