{
  "type": "Feature",
  "properties": {
    "gn:admin1_code":"24.0",
    "gn:asciiname":"Kibingo",
    "gn:country_code":"KE",
    "gn:dem":1656,
    "gn:feature_class":"P",
    "gn:feature_code":"PPL",
    "gn:name":"Kibingo",
    "gn:population":0,
    "gn:timezone":"Africa/Nairobi",
    "iso:country":"KE",
    "wof:name":"Kibingo",
    "wof:placetype":"locality"
},
  "geometry": {"coordinates":[37.25,-0.48333],"type":"Point"}
}