{
  "type": "Feature",
  "properties": {
    "iso:country":"KE",
    "name:ceb_x_preferred":[
        "Rongai"
    ],
    "name:deu_x_preferred":[
        "Rongai"
    ],
    "name:eng_x_preferred":[
        "Rongai"
    ],
    "name:fas_x_preferred":[
        "\u0631\u0648\u0646\u06af\u0627\u06cc\u060c \u06a9\u0646\u06cc\u0627"
    ],
    "name:fas_x_variant":[
        "\u0631\u0648\u0646\u06af\u0627\u06cc"
    ],
    "name:nld_x_preferred":[
        "Rongai"
    ],
    "name:nob_x_preferred":[
        "Rongai"
    ],
    "name:nor_x_preferred":[
        "Rongai"
    ],
    "name:pol_x_preferred":[
        "Rongai"
    ],
    "name:swa_x_preferred":[
        "Rongai"
    ],
    "name:swe_x_preferred":[
        "Rongai"
    ],
    "qs:gn_country":"KE",
    "qs:gn_fcode":"PPL",
    "qs:gn_pop":30471,
    "qs:name":"Rongai",
    "qs:name_adm0":"Kenya",
    "qs:name_adm1":"Rift Valley",
    "qs:photos":0,
    "qs:photos_1k":0,
    "qs:photos_9k":0,
    "qs:photos_9r":0,
    "qs:photos_all":0,
    "qs:photos_sr":0,
    "qs:placetype":"Town",
    "qs:pop_sr":"7",
    "qs:woe_adm0":23424863,
    "wd:wordcount":149,
    "wof:name":"Rongai",
    "wof:placetype":"locality",
    "wof:population":30471
},
  "geometry": {"coordinates":[35.86382,-0.17333],"type":"Point"}
}