{
  "type": "Feature",
  "properties": {
    "gn:admin1_code":"23.0",
    "gn:asciiname":"Mbungoni",
    "gn:country_code":"KE",
    "gn:dem":214,
    "gn:feature_class":"P",
    "gn:feature_code":"PPL",
    "gn:name":"Mbungoni",
    "gn:population":0,
    "gn:timezone":"Africa/Nairobi",
    "iso:country":"KE",
    "name:und_x_variant":[
        "Mbunboni",
        "Mbungoni",
        "Mubungoni"
    ],
    "wof:name":"Mbungoni",
    "wof:placetype":"locality"
},
  "geometry": {"coordinates":[39.63333,-3.85],"type":"Point"}
}