{
  "type": "Feature",
  "properties": {
    "gn:admin1_code":"32.0",
    "gn:asciiname":"Sultan Hamud",
    "gn:country_code":"KE",
    "gn:dem":1319,
    "gn:feature_class":"P",
    "gn:feature_code":"PPL",
    "gn:name":"Sultan Hamud",
    "gn:population":0,
    "gn:timezone":"Africa/Nairobi",
    "iso:country":"KE",
    "wof:name":"Sultan Hamud",
    "wof:placetype":"locality"
},
  "geometry": {"coordinates":[37.37212,-2.02042],"type":"Point"}
}