{
  "type": "Feature",
  "properties": {
    "gn:admin1_code":"48",
    "gn:asciiname":"Laini",
    "gn:country_code":"KE",
    "gn:dem":74,
    "gn:feature_class":"P",
    "gn:feature_code":"PPL",
    "gn:name":"Laini",
    "gn:population":0,
    "gn:timezone":"Africa/Nairobi",
    "iso:country":"KE",
    "wof:name":"Laini",
    "wof:placetype":"locality"
},
  "geometry": {"coordinates":[40.00185,-1.36347],"type":"Point"}
}