{
  "type": "Feature",
  "properties": {
    "gn:admin1_code":"26.0",
    "gn:asciiname":"Koru",
    "gn:country_code":"KE",
    "gn:dem":1417,
    "gn:feature_class":"P",
    "gn:feature_code":"PPL",
    "gn:name":"Koru",
    "gn:population":0,
    "gn:timezone":"Africa/Nairobi",
    "iso:country":"KE",
    "wof:name":"Koru",
    "wof:placetype":"locality"
},
  "geometry": {"coordinates":[35.26636,-0.18089],"type":"Point"}
}