{
  "type": "Feature",
  "properties": {
    "gn:admin1_code":"27.0",
    "gn:asciiname":"Kakunio",
    "gn:country_code":"KE",
    "gn:dem":779,
    "gn:feature_class":"P",
    "gn:feature_code":"PPL",
    "gn:name":"Kakunio",
    "gn:population":0,
    "gn:timezone":"Africa/Nairobi",
    "iso:country":"KE",
    "wof:name":"Kakunio",
    "wof:placetype":"locality"
},
  "geometry": {"coordinates":[38.18445,-1.91791],"type":"Point"}
}