{
  "type": "Feature",
  "properties": {
    "gn:admin1_code":"28.0",
    "gn:asciiname":"Nguruweni",
    "gn:country_code":"KE",
    "gn:dem":69,
    "gn:feature_class":"P",
    "gn:feature_code":"PPL",
    "gn:name":"Nguruweni",
    "gn:population":0,
    "gn:timezone":"Africa/Nairobi",
    "iso:country":"KE",
    "wof:name":"Nguruweni",
    "wof:placetype":"locality"
},
  "geometry": {"coordinates":[39.40334,-4.46855],"type":"Point"}
}