{
  "type": "Feature",
  "properties": {
    "gn:admin1_code":"43.0",
    "gn:asciiname":"Miharati",
    "gn:country_code":"KE",
    "gn:dem":2574,
    "gn:feature_class":"P",
    "gn:feature_code":"PPL",
    "gn:name":"Miharati",
    "gn:population":0,
    "gn:timezone":"Africa/Nairobi",
    "iso:country":"KE",
    "wof:name":"Miharati",
    "wof:placetype":"locality"
},
  "geometry": {"coordinates":[36.49273,-0.39958],"type":"Point"}
}