{
  "type": "Feature",
  "properties": {
    "iso:country":"KE",
    "name:bul_x_preferred":[
        "\u0420\u0443\u043c\u0443\u0440\u0443\u0442\u0438"
    ],
    "name:ceb_x_preferred":[
        "Rumuruti"
    ],
    "name:eng_x_preferred":[
        "Rumuruti"
    ],
    "name:jpn_x_preferred":[
        "\u30eb\u30e0\u30eb\u30c1"
    ],
    "name:nld_x_preferred":[
        "Rumuruti"
    ],
    "name:pol_x_preferred":[
        "Rumuruti"
    ],
    "name:spa_x_preferred":[
        "Rumuruti"
    ],
    "name:swa_x_preferred":[
        "Rumuruti"
    ],
    "name:swe_x_preferred":[
        "Rumuruti"
    ],
    "name:urd_x_preferred":[
        "\u0631\u0648\u0645\u0648\u0631\u0648\u062a\u06cc"
    ],
    "qs:gn_country":"KE",
    "qs:gn_fcode":"PPL",
    "qs:gn_pop":4501,
    "qs:name":"Rumuruti",
    "qs:name_adm0":"Kenya",
    "qs:name_adm1":"Rift Valley",
    "qs:photos":0,
    "qs:photos_1k":0,
    "qs:photos_9k":1,
    "qs:photos_9r":4,
    "qs:photos_all":184,
    "qs:photos_sr":0,
    "qs:placetype":"Town",
    "qs:pop_sr":"4",
    "qs:woe_adm0":23424863,
    "wd:wordcount":182,
    "wof:name":"Rumuruti",
    "wof:placetype":"locality",
    "wof:population":4501
},
  "geometry": {"coordinates":[36.53886,0.26699],"type":"Point"}
}