{
  "type": "Feature",
  "properties": {
    "gn:admin1_code":"10",
    "gn:asciiname":"Chemoigut",
    "gn:country_code":"KE",
    "gn:dem":1127,
    "gn:feature_class":"P",
    "gn:feature_code":"PPL",
    "gn:name":"Chemoigut",
    "gn:population":0,
    "gn:timezone":"Africa/Nairobi",
    "iso:country":"KE",
    "wof:name":"Chemoigut",
    "wof:placetype":"locality"
},
  "geometry": {"coordinates":[36.2163,0.67995],"type":"Point"}
}