{
  "type": "Feature",
  "properties": {
    "gn:admin1_code":"48",
    "gn:asciiname":"Kiarukungu",
    "gn:country_code":"KE",
    "gn:dem":72,
    "gn:feature_class":"P",
    "gn:feature_code":"PPL",
    "gn:name":"Kiarukungu",
    "gn:population":0,
    "gn:timezone":"Africa/Nairobi",
    "iso:country":"KE",
    "wof:name":"Kiarukungu",
    "wof:placetype":"locality"
},
  "geometry": {"coordinates":[39.98862,-1.48047],"type":"Point"}
}