{
  "type": "Feature",
  "properties": {
    "gn:admin1_code":"23.0",
    "gn:asciiname":"Kadzinuni",
    "gn:country_code":"KE",
    "gn:dem":104,
    "gn:feature_class":"P",
    "gn:feature_code":"PPL",
    "gn:name":"Kadzinuni",
    "gn:population":0,
    "gn:timezone":"Africa/Nairobi",
    "iso:country":"KE",
    "wof:name":"Kadzinuni",
    "wof:placetype":"locality"
},
  "geometry": {"coordinates":[39.81062,-3.7452],"type":"Point"}
}