{
  "type": "Feature",
  "properties": {
    "gn:admin1_code":"23.0",
    "gn:asciiname":"Waresa",
    "gn:country_code":"KE",
    "gn:dem":194,
    "gn:feature_class":"P",
    "gn:feature_code":"PPL",
    "gn:name":"Waresa",
    "gn:population":0,
    "gn:timezone":"Africa/Nairobi",
    "iso:country":"KE",
    "name:und_x_variant":[
        "Waressa",
        "Waresa"
    ],
    "wof:name":"Waresa",
    "wof:placetype":"locality"
},
  "geometry": {"coordinates":[39.99463,-2.76977],"type":"Point"}
}