{
  "type": "Feature",
  "properties": {
    "gn:admin1_code":"46.0",
    "gn:asciiname":"Nyangoma",
    "gn:country_code":"KE",
    "gn:dem":1234,
    "gn:feature_class":"P",
    "gn:feature_code":"PPL",
    "gn:name":"Nyangoma",
    "gn:population":0,
    "gn:timezone":"Africa/Nairobi",
    "iso:country":"KE",
    "wof:name":"Nyangoma",
    "wof:placetype":"locality"
},
  "geometry": {"coordinates":[34.34562,-0.01092],"type":"Point"}
}