{
  "type": "Feature",
  "properties": {
    "gn:admin1_code":"44.0",
    "gn:asciiname":"Kericho",
    "gn:country_code":"KE",
    "gn:dem":1743,
    "gn:feature_class":"P",
    "gn:feature_code":"PPL",
    "gn:name":"Kericho",
    "gn:population":0,
    "gn:timezone":"Africa/Nairobi",
    "iso:country":"KE",
    "name:cat_x_preferred":[
        "Kericho"
    ],
    "name:deu_x_preferred":[
        "Kericho"
    ],
    "name:epo_x_preferred":[
        "Kericho"
    ],
    "name:fas_x_preferred":[
        "\u06a9\u0631\u06cc\u0686\u0648"
    ],
    "name:fra_x_preferred":[
        "Kericho"
    ],
    "name:hrv_x_preferred":[
        "Kericho"
    ],
    "name:ita_x_preferred":[
        "Kericho"
    ],
    "name:kat_x_preferred":[
        "\u10d9\u10d4\u10e0\u10d8\u10e9\u10dd"
    ],
    "name:lit_x_preferred":[
        "Keri\u010das"
    ],
    "name:nld_x_preferred":[
        "Kericho"
    ],
    "name:nor_x_preferred":[
        "Kericho"
    ],
    "name:pol_x_preferred":[
        "Kericho"
    ],
    "name:ron_x_preferred":[
        "Kericho"
    ],
    "name:rus_x_preferred":[
        "\u041a\u0435\u0440\u0438\u0447\u043e"
    ],
    "name:spa_x_preferred":[
        "Kericho"
    ],
    "name:swa_x_preferred":[
        "Kericho"
    ],
    "name:swe_x_preferred":[
        "Kericho"
    ],
    "name:zho_x_preferred":[
        "\u51f1\u91cc\u55ac"
    ],
    "wof:name":"Kericho",
    "wof:placetype":"locality"
},
  "geometry": {"coordinates":[37.02313,-0.41074],"type":"Point"}
}