{
  "type": "Feature",
  "properties": {
    "gn:admin1_code":"28.0",
    "gn:asciiname":"Mkambini",
    "gn:country_code":"KE",
    "gn:dem":93,
    "gn:feature_class":"P",
    "gn:feature_code":"PPL",
    "gn:name":"Mkambini",
    "gn:population":0,
    "gn:timezone":"Africa/Nairobi",
    "iso:country":"KE",
    "wof:name":"Mkambini",
    "wof:placetype":"locality"
},
  "geometry": {"coordinates":[39.10347,-4.54508],"type":"Point"}
}