{
  "type": "Feature",
  "properties": {
    "gn:admin1_code":"29.0",
    "gn:asciiname":"Lamuria",
    "gn:country_code":"KE",
    "gn:dem":1858,
    "gn:feature_class":"P",
    "gn:feature_code":"PPL",
    "gn:name":"Lamuria",
    "gn:population":0,
    "gn:timezone":"Africa/Nairobi",
    "iso:country":"KE",
    "name:und_x_variant":[
        "Lamuria Farm",
        "Lamuria"
    ],
    "name:urd_x_preferred":[
        "\u0644\u0627\u0645\u0648\u0631\u06cc\u0627"
    ],
    "wof:name":"Lamuria",
    "wof:placetype":"locality"
},
  "geometry": {"coordinates":[36.86426,-0.13466],"type":"Point"}
}