{
  "type": "Feature",
  "properties": {
    "gn:admin1_code":"38.0",
    "gn:asciiname":"Wangai",
    "gn:country_code":"KE",
    "gn:dem":1507,
    "gn:feature_class":"P",
    "gn:feature_code":"PPL",
    "gn:name":"Wangai",
    "gn:population":0,
    "gn:timezone":"Africa/Nairobi",
    "iso:country":"KE",
    "wof:name":"Wangai",
    "wof:placetype":"locality"
},
  "geometry": {"coordinates":[37.07121,-0.89687],"type":"Point"}
}