{
  "type": "Feature",
  "properties": {
    "gn:admin1_code":"39.0",
    "gn:asciiname":"Kedong",
    "gn:country_code":"KE",
    "gn:dem":1704,
    "gn:feature_class":"P",
    "gn:feature_code":"PPL",
    "gn:name":"Kedong",
    "gn:population":0,
    "gn:timezone":"Africa/Nairobi",
    "iso:country":"KE",
    "name:und_x_variant":[
        "Nkidongi",
        "Kedong"
    ],
    "wof:name":"Kedong",
    "wof:placetype":"locality"
},
  "geometry": {"coordinates":[36.56667,-1.05],"type":"Point"}
}