{
  "type": "Feature",
  "properties": {
    "gn:admin1_code":"38.0",
    "gn:asciiname":"Gathaithi",
    "gn:country_code":"KE",
    "gn:dem":1959,
    "gn:feature_class":"P",
    "gn:feature_code":"PPL",
    "gn:name":"Gathaithi",
    "gn:population":0,
    "gn:timezone":"Africa/Nairobi",
    "iso:country":"KE",
    "wof:name":"Gathaithi",
    "wof:placetype":"locality"
},
  "geometry": {"coordinates":[36.91667,-0.75],"type":"Point"}
}