{
  "type": "Feature",
  "properties": {
    "gn:admin1_code":"38.0",
    "gn:asciiname":"Karaba",
    "gn:country_code":"KE",
    "gn:dem":1480,
    "gn:feature_class":"P",
    "gn:feature_code":"PPL",
    "gn:name":"Karaba",
    "gn:population":0,
    "gn:timezone":"Africa/Nairobi",
    "iso:country":"KE",
    "wof:name":"Karaba",
    "wof:placetype":"locality"
},
  "geometry": {"coordinates":[37.10616,-0.62702],"type":"Point"}
}