{
  "type": "Feature",
  "properties": {
    "gn:admin1_code":"22.0",
    "gn:asciiname":"Kinunga",
    "gn:country_code":"KE",
    "gn:dem":1729,
    "gn:feature_class":"P",
    "gn:feature_code":"PPL",
    "gn:name":"Kinunga",
    "gn:population":0,
    "gn:timezone":"Africa/Nairobi",
    "iso:country":"KE",
    "wof:name":"Kinunga",
    "wof:placetype":"locality"
},
  "geometry": {"coordinates":[36.83333,-1.08333],"type":"Point"}
}