{
  "type": "Feature",
  "properties": {
    "gn:admin1_code":"38.0",
    "gn:asciiname":"Manyatta",
    "gn:country_code":"KE",
    "gn:dem":1321,
    "gn:feature_class":"P",
    "gn:feature_code":"PPL",
    "gn:name":"Manyatta",
    "gn:population":0,
    "gn:timezone":"Africa/Nairobi",
    "iso:country":"KE",
    "name:und_x_variant":[
        "Manyata"
    ],
    "wof:name":"Manyatta",
    "wof:placetype":"locality"
},
  "geometry": {"coordinates":[37.1736,-0.86879],"type":"Point"}
}