{
  "type": "Feature",
  "properties": {
    "gn:admin1_code":"47.0",
    "gn:asciiname":"Mwaketutu",
    "gn:country_code":"KE",
    "gn:dem":1063,
    "gn:feature_class":"P",
    "gn:feature_code":"PPL",
    "gn:name":"Mwaketutu",
    "gn:population":0,
    "gn:timezone":"Africa/Nairobi",
    "iso:country":"KE",
    "wof:name":"Mwaketutu",
    "wof:placetype":"locality"
},
  "geometry": {"coordinates":[38.35311,-3.49352],"type":"Point"}
}