{
  "type": "Feature",
  "properties": {
    "gn:admin1_code":"48",
    "gn:asciiname":"Garabugoya",
    "gn:country_code":"KE",
    "gn:dem":169,
    "gn:feature_class":"P",
    "gn:feature_code":"PPL",
    "gn:name":"Garabugoya",
    "gn:population":0,
    "gn:timezone":"Africa/Nairobi",
    "iso:country":"KE",
    "wof:name":"Garabugoya",
    "wof:placetype":"locality"
},
  "geometry": {"coordinates":[39.41893,-2.03515],"type":"Point"}
}