{
  "type": "Feature",
  "properties": {
    "gn:admin1_code":"30.0",
    "gn:asciiname":"Kijinitini",
    "gn:country_code":"KE",
    "gn:dem":8,
    "gn:feature_class":"P",
    "gn:feature_code":"PPL",
    "gn:name":"Kijinitini",
    "gn:population":0,
    "gn:timezone":"Africa/Nairobi",
    "iso:country":"KE",
    "name:und_x_variant":[
        "Kisingatini",
        "Kisingatani",
        "Kijinitini",
        "Kisingitini"
    ],
    "wof:name":"Kijinitini",
    "wof:placetype":"locality"
},
  "geometry": {"coordinates":[41.14247,-2.0719],"type":"Point"}
}