{
  "type": "Feature",
  "properties": {
    "gn:admin1_code":"48",
    "gn:asciiname":"Wayu",
    "gn:country_code":"KE",
    "gn:dem":162,
    "gn:feature_class":"P",
    "gn:feature_code":"PPLL",
    "gn:name":"Wayu",
    "gn:population":0,
    "gn:timezone":"Africa/Nairobi",
    "iso:country":"KE",
    "wof:name":"Wayu",
    "wof:placetype":"locality"
},
  "geometry": {"coordinates":[39.55169,-1.55229],"type":"Point"}
}