{
  "type": "Feature",
  "properties": {
    "gn:admin1_code":"48",
    "gn:asciiname":"Onshora",
    "gn:country_code":"KE",
    "gn:dem":168,
    "gn:feature_class":"P",
    "gn:feature_code":"PPL",
    "gn:name":"Onshora",
    "gn:population":0,
    "gn:timezone":"Africa/Nairobi",
    "iso:country":"KE",
    "wof:name":"Onshora",
    "wof:placetype":"locality"
},
  "geometry": {"coordinates":[39.42498,-2.05046],"type":"Point"}
}