{
  "type": "Feature",
  "properties": {
    "gn:admin1_code":"38.0",
    "gn:asciiname":"Mathareini",
    "gn:country_code":"KE",
    "gn:dem":1782,
    "gn:feature_class":"P",
    "gn:feature_code":"PPL",
    "gn:name":"Mathareini",
    "gn:population":0,
    "gn:timezone":"Africa/Nairobi",
    "iso:country":"KE",
    "wof:name":"Mathareini",
    "wof:placetype":"locality"
},
  "geometry": {"coordinates":[36.96667,-0.81667],"type":"Point"}
}