{
  "type": "Feature",
  "properties": {
    "gn:admin1_code":"11.0",
    "gn:asciiname":"Ndanai",
    "gn:country_code":"KE",
    "gn:dem":1863,
    "gn:feature_class":"P",
    "gn:feature_code":"PPL",
    "gn:name":"Ndanai",
    "gn:population":0,
    "gn:timezone":"Africa/Nairobi",
    "iso:country":"KE",
    "wof:name":"Ndanai",
    "wof:placetype":"locality"
},
  "geometry": {"coordinates":[35.09535,-0.83921],"type":"Point"}
}