{
  "type": "Feature",
  "properties": {
    "gn:admin1_code":"48",
    "gn:asciiname":"Emausi",
    "gn:country_code":"KE",
    "gn:dem":60,
    "gn:feature_class":"P",
    "gn:feature_code":"PPL",
    "gn:name":"Emausi",
    "gn:population":0,
    "gn:timezone":"Africa/Nairobi",
    "iso:country":"KE",
    "wof:name":"Emausi",
    "wof:placetype":"locality"
},
  "geometry": {"coordinates":[40.04543,-1.54168],"type":"Point"}
}