{
  "type": "Feature",
  "properties": {
    "gn:admin1_code":"37.0",
    "gn:asciiname":"Jumba la Mtwana",
    "gn:country_code":"KE",
    "gn:dem":14,
    "gn:feature_class":"P",
    "gn:feature_code":"PPL",
    "gn:name":"Jumba la Mtwana",
    "gn:population":0,
    "gn:timezone":"Africa/Nairobi",
    "iso:country":"KE",
    "wof:name":"Jumba la Mtwana",
    "wof:placetype":"locality"
},
  "geometry": {"coordinates":[39.76667,-3.95],"type":"Point"}
}