{
  "type": "Feature",
  "properties": {
    "gn:admin1_code":"10.0",
    "gn:asciiname":"Pemwai",
    "gn:country_code":"KE",
    "gn:dem":2044,
    "gn:feature_class":"P",
    "gn:feature_code":"PPL",
    "gn:name":"Pemwai",
    "gn:population":0,
    "gn:timezone":"Africa/Nairobi",
    "iso:country":"KE",
    "wof:name":"Pemwai",
    "wof:placetype":"locality"
},
  "geometry": {"coordinates":[35.7704,0.57112],"type":"Point"}
}