{
  "type": "Feature",
  "properties": {
    "gn:admin1_code":"54",
    "gn:asciiname":"Hara",
    "gn:country_code":"KE",
    "gn:dem":178,
    "gn:feature_class":"P",
    "gn:feature_code":"PPL",
    "gn:name":"Hara",
    "gn:population":0,
    "gn:timezone":"Africa/Nairobi",
    "iso:country":"KE",
    "name:ceb_x_preferred":[
        "Hara"
    ],
    "name:deu_x_preferred":[
        "Hara"
    ],
    "name:est_x_preferred":[
        "Hara"
    ],
    "name:fin_x_preferred":[
        "Hara"
    ],
    "name:fra_x_preferred":[
        "Hara"
    ],
    "name:nld_x_preferred":[
        "Hara"
    ],
    "name:pol_x_preferred":[
        "Hara"
    ],
    "name:por_x_preferred":[
        "Hara"
    ],
    "name:spa_x_preferred":[
        "Hara"
    ],
    "name:swe_x_preferred":[
        "Hara"
    ],
    "name:vol_x_preferred":[
        "Hara"
    ],
    "wof:name":"Hara",
    "wof:placetype":"locality"
},
  "geometry": {"coordinates":[39.89153,0.9283],"type":"Point"}
}