{
  "type": "Feature",
  "properties": {
    "gn:admin1_code":"55.0",
    "gn:asciiname":"Kalodeke",
    "gn:country_code":"KE",
    "gn:dem":1448,
    "gn:feature_class":"P",
    "gn:feature_code":"PPL",
    "gn:name":"Kalodeke",
    "gn:population":0,
    "gn:timezone":"Africa/Nairobi",
    "iso:country":"KE",
    "wof:name":"Kalodeke",
    "wof:placetype":"locality"
},
  "geometry": {"coordinates":[34.96163,2.14753],"type":"Point"}
}