{
  "type": "Feature",
  "properties": {
    "gn:admin1_code":"27.0",
    "gn:asciiname":"Voo",
    "gn:country_code":"KE",
    "gn:dem":608,
    "gn:feature_class":"P",
    "gn:feature_code":"PPL",
    "gn:name":"Voo",
    "gn:population":0,
    "gn:timezone":"Africa/Nairobi",
    "iso:country":"KE",
    "name:und_x_variant":[
        "Mzembe",
        "Voo"
    ],
    "wof:name":"Voo",
    "wof:placetype":"locality"
},
  "geometry": {"coordinates":[38.32429000000001,-1.66736],"type":"Point"}
}