{
  "type": "Feature",
  "properties": {
    "gn:admin1_code":"52.0",
    "gn:asciiname":"Tumeiyo",
    "gn:country_code":"KE",
    "gn:dem":2525,
    "gn:feature_class":"P",
    "gn:feature_code":"PPL",
    "gn:name":"Tumeiyo",
    "gn:population":0,
    "gn:timezone":"Africa/Nairobi",
    "iso:country":"KE",
    "name:und_x_variant":[
        "Tumeya",
        "Tumeiyo"
    ],
    "wof:name":"Tumeiyo",
    "wof:placetype":"locality"
},
  "geometry": {"coordinates":[35.53100999999999,0.22814],"type":"Point"}
}