{
  "type": "Feature",
  "properties": {
    "gn:admin1_code":"22.0",
    "gn:asciiname":"Giachumi",
    "gn:country_code":"KE",
    "gn:dem":1914,
    "gn:feature_class":"P",
    "gn:feature_code":"PPL",
    "gn:name":"Giachumi",
    "gn:population":0,
    "gn:timezone":"Africa/Nairobi",
    "iso:country":"KE",
    "wof:name":"Giachumi",
    "wof:placetype":"locality"
},
  "geometry": {"coordinates":[36.78333,-1.06667],"type":"Point"}
}