{
  "type": "Feature",
  "properties": {
    "gn:admin1_code":"23.0",
    "gn:asciiname":"Mwarakaya",
    "gn:country_code":"KE",
    "gn:dem":148,
    "gn:feature_class":"P",
    "gn:feature_code":"PPL",
    "gn:name":"Mwarakaya",
    "gn:population":0,
    "gn:timezone":"Africa/Nairobi",
    "iso:country":"KE",
    "wof:name":"Mwarakaya",
    "wof:placetype":"locality"
},
  "geometry": {"coordinates":[39.69447,-3.79706],"type":"Point"}
}