{
  "type": "Feature",
  "properties": {
    "gn:admin1_code":"43",
    "gn:asciiname":"Ndunyu Njeru",
    "gn:country_code":"KE",
    "gn:dem":2497,
    "gn:feature_class":"P",
    "gn:feature_code":"PPL",
    "gn:name":"Ndunyu Njeru",
    "gn:population":0,
    "gn:timezone":"Africa/Nairobi",
    "iso:country":"KE",
    "name:und_x_variant":[
        "Ndunyu Nderu"
    ],
    "wof:name":"Ndunyu Njeru",
    "wof:placetype":"locality"
},
  "geometry": {"coordinates":[36.56182,-0.54592],"type":"Point"}
}