{
  "type": "Feature",
  "properties": {
    "gn:admin1_code":"15.0",
    "gn:asciiname":"Kathungure",
    "gn:country_code":"KE",
    "gn:dem":1429,
    "gn:feature_class":"P",
    "gn:feature_code":"PPL",
    "gn:name":"Kathungure",
    "gn:population":0,
    "gn:timezone":"Africa/Nairobi",
    "iso:country":"KE",
    "name:und_x_variant":[
        "Kathanjure",
        "Kathungure"
    ],
    "wof:name":"Kathungure",
    "wof:placetype":"locality"
},
  "geometry": {"coordinates":[37.60928,-0.42573],"type":"Point"}
}