{
  "type": "Feature",
  "properties": {
    "gn:admin1_code":"32.0",
    "gn:asciiname":"Manoni",
    "gn:country_code":"KE",
    "gn:dem":740,
    "gn:feature_class":"P",
    "gn:feature_code":"PPL",
    "gn:name":"Manoni",
    "gn:population":0,
    "gn:timezone":"Africa/Nairobi",
    "iso:country":"KE",
    "name:und_x_variant":[
        "Munani",
        "Manooni",
        "Manoni"
    ],
    "wof:name":"Manoni",
    "wof:placetype":"locality"
},
  "geometry": {"coordinates":[38.08167,-2.37883],"type":"Point"}
}