{
  "type": "Feature",
  "properties": {
    "gn:admin1_code":"36.0",
    "gn:asciiname":"Nyamuga",
    "gn:country_code":"KE",
    "gn:dem":1341,
    "gn:feature_class":"P",
    "gn:feature_code":"PPL",
    "gn:name":"Nyamuga",
    "gn:population":0,
    "gn:timezone":"Africa/Nairobi",
    "iso:country":"KE",
    "wof:name":"Nyamuga",
    "wof:placetype":"locality"
},
  "geometry": {"coordinates":[34.55,-0.73333],"type":"Point"}
}