{
  "type": "Feature",
  "properties": {
    "gn:admin1_code":"22.0",
    "gn:asciiname":"Gicheru",
    "gn:country_code":"KE",
    "gn:dem":1805,
    "gn:feature_class":"P",
    "gn:feature_code":"PPL",
    "gn:name":"Gicheru",
    "gn:population":0,
    "gn:timezone":"Africa/Nairobi",
    "iso:country":"KE",
    "wof:name":"Gicheru",
    "wof:placetype":"locality"
},
  "geometry": {"coordinates":[36.55299,-1.1804],"type":"Point"}
}