{
  "type": "Feature",
  "properties": {
    "iso:country":"KE",
    "name:azb_x_preferred":[
        "\u0645\u0627\u062c\u06cc\u200c\u0645\u0627\u062a\u0627"
    ],
    "name:eng_x_preferred":[
        "Maji Mata"
    ],
    "name:fas_x_preferred":[
        "\u0645\u0627\u062c\u06cc\u200c\u0645\u0627\u062a\u0627"
    ],
    "name:nld_x_preferred":[
        "Maji Mata"
    ],
    "name:und_x_variant":[
        "Maji Moto"
    ],
    "qs:gn_country":"KE",
    "qs:gn_fcode":"PPL",
    "qs:gn_pop":0,
    "qs:name":"Maji Ya Moto",
    "qs:name_adm0":"Kenya",
    "qs:name_adm1":"Rift Valley",
    "qs:photos":68,
    "qs:photos_1k":14,
    "qs:photos_9k":1,
    "qs:photos_9r":2,
    "qs:photos_all":68,
    "qs:photos_sr":2,
    "qs:placetype":"Town",
    "qs:pop_sr":"0",
    "qs:woe_adm0":23424863,
    "wof:name":"Maji Ya Moto",
    "wof:placetype":"locality"
},
  "geometry": {"coordinates":[36.04842,0.26846],"type":"Point"}
}