{
  "type": "Feature",
  "properties": {
    "gn:admin1_code":"48",
    "gn:asciiname":"Bisadi",
    "gn:country_code":"KE",
    "gn:dem":56,
    "gn:feature_class":"P",
    "gn:feature_code":"PPLL",
    "gn:name":"Bisadi",
    "gn:population":0,
    "gn:timezone":"Africa/Nairobi",
    "iso:country":"KE",
    "wof:name":"Bisadi",
    "wof:placetype":"locality"
},
  "geometry": {"coordinates":[39.96496,-1.7698],"type":"Point"}
}