{
  "type": "Feature",
  "properties": {
    "iso:country":"KE",
    "name:ces_x_preferred":[
        "Gilgil"
    ],
    "name:eng_x_preferred":[
        "Gilgil"
    ],
    "name:jpn_x_preferred":[
        "\u30ae\u30eb\u30ae\u30eb"
    ],
    "name:nld_x_preferred":[
        "Gilgil"
    ],
    "name:nob_x_preferred":[
        "Gilgil"
    ],
    "name:nor_x_preferred":[
        "Gilgil"
    ],
    "name:pol_x_preferred":[
        "Gilgil"
    ],
    "name:rus_x_preferred":[
        "\u0413\u0438\u043b\u0433\u0438\u043b"
    ],
    "name:swa_x_preferred":[
        "Gilgil"
    ],
    "name:swe_x_preferred":[
        "Gilgil"
    ],
    "qs:gn_country":"KE",
    "qs:gn_fcode":"PPL",
    "qs:gn_pop":0,
    "qs:name":"Gilgil",
    "qs:name_adm0":"Kenya",
    "qs:name_adm1":"Rift Valley",
    "qs:photos":137,
    "qs:photos_1k":28,
    "qs:photos_9k":1,
    "qs:photos_9r":3,
    "qs:photos_all":137,
    "qs:photos_sr":3,
    "qs:placetype":"Town",
    "qs:pop_sr":"4",
    "qs:woe_adm0":23424863,
    "wd:wordcount":869,
    "wof:name":"Gilgil",
    "wof:placetype":"locality"
},
  "geometry": {"coordinates":[36.31201,-0.48972],"type":"Point"}
}