{
  "type": "Feature",
  "properties": {
    "gn:admin1_code":"22.0",
    "gn:asciiname":"Githamba",
    "gn:country_code":"KE",
    "gn:dem":1752,
    "gn:feature_class":"P",
    "gn:feature_code":"PPL",
    "gn:name":"Githamba",
    "gn:population":0,
    "gn:timezone":"Africa/Nairobi",
    "iso:country":"KE",
    "wof:name":"Githamba",
    "wof:placetype":"locality"
},
  "geometry": {"coordinates":[36.81667,-1.06667],"type":"Point"}
}