{
  "type": "Feature",
  "properties": {
    "gn:admin1_code":"14",
    "gn:asciiname":"Chepkorio",
    "gn:country_code":"KE",
    "gn:dem":2559,
    "gn:feature_class":"P",
    "gn:feature_code":"PPL",
    "gn:name":"Chepkorio",
    "gn:population":0,
    "gn:timezone":"Africa/Nairobi",
    "iso:country":"KE",
    "name:azb_x_preferred":[
        "\u0686\u067e\u06a9\u0648\u0631\u06cc\u0648"
    ],
    "name:fas_x_preferred":[
        "\u0686\u067e\u06a9\u0648\u0631\u06cc\u0648"
    ],
    "wof:name":"Chepkorio",
    "wof:placetype":"locality"
},
  "geometry": {"coordinates":[35.54074,0.37894],"type":"Point"}
}