{
  "type": "Feature",
  "properties": {
    "gn:admin1_code":"28",
    "gn:asciiname":"Mtata",
    "gn:country_code":"KE",
    "gn:dem":287,
    "gn:feature_class":"P",
    "gn:feature_code":"PPL",
    "gn:name":"Mtata",
    "gn:population":0,
    "gn:timezone":"Africa/Nairobi",
    "iso:country":"KE",
    "wof:name":"Mtata",
    "wof:placetype":"locality"
},
  "geometry": {"coordinates":[39.10845,-4.04284],"type":"Point"}
}