{
  "type": "Feature",
  "properties": {
    "gn:admin1_code":"38.0",
    "gn:asciiname":"Thuita",
    "gn:country_code":"KE",
    "gn:dem":1574,
    "gn:feature_class":"P",
    "gn:feature_code":"PPL",
    "gn:name":"Thuita",
    "gn:population":0,
    "gn:timezone":"Africa/Nairobi",
    "iso:country":"KE",
    "wof:name":"Thuita",
    "wof:placetype":"locality"
},
  "geometry": {"coordinates":[37.03333,-0.83333],"type":"Point"}
}