{
  "type": "Feature",
  "properties": {
    "gn:admin1_code":"23.0",
    "gn:asciiname":"Gongoni",
    "gn:country_code":"KE",
    "gn:dem":127,
    "gn:feature_class":"P",
    "gn:feature_code":"PPL",
    "gn:name":"Gongoni",
    "gn:population":0,
    "gn:timezone":"Africa/Nairobi",
    "iso:country":"KE",
    "wof:name":"Gongoni",
    "wof:placetype":"locality"
},
  "geometry": {"coordinates":[39.76301,-3.82718],"type":"Point"}
}