{
  "type": "Feature",
  "properties": {
    "gn:admin1_code":"47",
    "gn:asciiname":"Chukia",
    "gn:country_code":"KE",
    "gn:dem":1010,
    "gn:feature_class":"P",
    "gn:feature_code":"PPL",
    "gn:name":"Chukia",
    "gn:population":0,
    "gn:timezone":"Africa/Nairobi",
    "iso:country":"KE",
    "wof:name":"Chukia",
    "wof:placetype":"locality"
},
  "geometry": {"coordinates":[38.60137,-3.49194],"type":"Point"}
}