{
  "type": "Feature",
  "properties": {
    "gn:admin1_code":"38.0",
    "gn:asciiname":"Maganjo",
    "gn:country_code":"KE",
    "gn:dem":1338,
    "gn:feature_class":"P",
    "gn:feature_code":"PPL",
    "gn:name":"Maganjo",
    "gn:population":0,
    "gn:timezone":"Africa/Nairobi",
    "iso:country":"KE",
    "wof:name":"Maganjo",
    "wof:placetype":"locality"
},
  "geometry": {"coordinates":[37.15037,-0.86395],"type":"Point"}
}