{
  "type": "Feature",
  "properties": {
    "gn:admin1_code":"44.0",
    "gn:asciiname":"Kangaita",
    "gn:country_code":"KE",
    "gn:dem":1785,
    "gn:feature_class":"P",
    "gn:feature_code":"PPL",
    "gn:name":"Kangaita",
    "gn:population":0,
    "gn:timezone":"Africa/Nairobi",
    "iso:country":"KE",
    "wof:name":"Kangaita",
    "wof:placetype":"locality"
},
  "geometry": {"coordinates":[36.99491,-0.49724],"type":"Point"}
}