{
  "type": "Feature",
  "properties": {
    "gn:admin1_code":"33",
    "gn:asciiname":"Lafey",
    "gn:country_code":"KE",
    "gn:dem":418,
    "gn:feature_class":"P",
    "gn:feature_code":"PPL",
    "gn:name":"Lafey",
    "gn:population":0,
    "gn:timezone":"Africa/Nairobi",
    "iso:country":"KE",
    "wof:name":"Lafey",
    "wof:placetype":"locality"
},
  "geometry": {"coordinates":[41.18577,3.15106],"type":"Point"}
}