{
  "type": "Feature",
  "properties": {
    "gn:admin1_code":"15.0",
    "gn:asciiname":"Muchumo",
    "gn:country_code":"KE",
    "gn:dem":1299,
    "gn:feature_class":"P",
    "gn:feature_code":"PPL",
    "gn:name":"Muchumo",
    "gn:population":0,
    "gn:timezone":"Africa/Nairobi",
    "iso:country":"KE",
    "wof:name":"Muchumo",
    "wof:placetype":"locality"
},
  "geometry": {"coordinates":[37.59575,-0.48088],"type":"Point"}
}