{
  "type": "Feature",
  "properties": {
    "gn:admin1_code":"32.0",
    "gn:asciiname":"Kilala",
    "gn:country_code":"KE",
    "gn:dem":1162,
    "gn:feature_class":"P",
    "gn:feature_code":"PPL",
    "gn:name":"Kilala",
    "gn:population":0,
    "gn:timezone":"Africa/Nairobi",
    "iso:country":"KE",
    "name:und_x_variant":[
        "Kaumoni",
        "Kilala"
    ],
    "wof:name":"Kilala",
    "wof:placetype":"locality"
},
  "geometry": {"coordinates":[37.5543,-1.77065],"type":"Point"}
}