{
  "type": "Feature",
  "properties": {
    "gn:admin1_code":"08",
    "gn:asciiname":"Burnt Forest",
    "gn:country_code":"KE",
    "gn:dem":2419,
    "gn:feature_class":"P",
    "gn:feature_code":"PPL",
    "gn:name":"Burnt Forest",
    "gn:population":0,
    "gn:timezone":"Africa/Nairobi",
    "iso:country":"KE",
    "wof:name":"Burnt Forest",
    "wof:placetype":"locality"
},
  "geometry": {"coordinates":[35.43163,0.21539],"type":"Point"}
}