{
  "type": "Feature",
  "properties": {
    "gn:admin1_code":"15.0",
    "gn:asciiname":"Gichiche",
    "gn:country_code":"KE",
    "gn:dem":1472,
    "gn:feature_class":"P",
    "gn:feature_code":"PPL",
    "gn:name":"Gichiche",
    "gn:population":0,
    "gn:timezone":"Africa/Nairobi",
    "iso:country":"KE",
    "wof:name":"Gichiche",
    "wof:placetype":"locality"
},
  "geometry": {"coordinates":[37.58694000000001,-0.43346],"type":"Point"}
}