{
  "type": "Feature",
  "properties": {
    "iso:country":"KE",
    "qs:gn_pop":0,
    "qs:name":"Junda",
    "qs:name_adm0":"Kenya",
    "qs:name_adm1":"Coast",
    "qs:photos":415,
    "qs:photos_1k":84,
    "qs:photos_9k":2,
    "qs:photos_9r":5,
    "qs:photos_all":415,
    "qs:photos_sr":6,
    "qs:placetype":"Town",
    "qs:pop_sr":"0",
    "qs:woe_adm0":23424863,
    "wof:name":"Junda",
    "wof:placetype":"locality"
},
  "geometry": {"coordinates":[39.707164,-4.016415],"type":"Point"}
}