{
  "type": "Feature",
  "properties": {
    "gn:admin1_code":"37.0",
    "gn:asciiname":"Mwakirunge ya Pwani",
    "gn:country_code":"KE",
    "gn:dem":11,
    "gn:feature_class":"P",
    "gn:feature_code":"PPL",
    "gn:name":"Mwakirunge ya Pwani",
    "gn:population":0,
    "gn:timezone":"Africa/Nairobi",
    "iso:country":"KE",
    "name:und_x_variant":[
        "Mwachirunje ya Pwani",
        "Mwakirunge ya Pwani"
    ],
    "name:urd_x_preferred":[
        "\u0645\u0648\u0627\u0686\u06cc\u0631\u0648\u0646\u062c\u06d2 \u06cc\u0627 \u067e\u0648\u0627\u0646\u06cc"
    ],
    "wof:name":"Mwakirunge ya Pwani",
    "wof:placetype":"locality"
},
  "geometry": {"coordinates":[39.65,-3.95],"type":"Point"}
}