{
  "type": "Feature",
  "properties": {
    "gn:admin1_code":"52",
    "gn:asciiname":"Leinguse",
    "gn:country_code":"KE",
    "gn:dem":2608,
    "gn:feature_class":"P",
    "gn:feature_code":"PPL",
    "gn:name":"Leinguse",
    "gn:population":0,
    "gn:timezone":"Africa/Nairobi",
    "iso:country":"KE",
    "wof:name":"Leinguse",
    "wof:placetype":"locality"
},
  "geometry": {"coordinates":[35.40252,0.10546],"type":"Point"}
}