{
  "type": "Feature",
  "properties": {
    "gn:admin1_code":"44.0",
    "gn:asciiname":"Gititu",
    "gn:country_code":"KE",
    "gn:dem":1695,
    "gn:feature_class":"P",
    "gn:feature_code":"PPL",
    "gn:name":"Gititu",
    "gn:population":0,
    "gn:timezone":"Africa/Nairobi",
    "iso:country":"KE",
    "wof:name":"Gititu",
    "wof:placetype":"locality"
},
  "geometry": {"coordinates":[37.01299,-0.50268],"type":"Point"}
}