{
  "type": "Feature",
  "properties": {
    "gn:admin1_code":"55.0",
    "gn:asciiname":"Kamunono",
    "gn:country_code":"KE",
    "gn:dem":813,
    "gn:feature_class":"P",
    "gn:feature_code":"PPL",
    "gn:name":"Kamunono",
    "gn:population":0,
    "gn:timezone":"Africa/Nairobi",
    "iso:country":"KE",
    "wof:name":"Kamunono",
    "wof:placetype":"locality"
},
  "geometry": {"coordinates":[35.31615,2.14623],"type":"Point"}
}