{
  "type": "Feature",
  "properties": {
    "gn:admin1_code":"44.0",
    "gn:asciiname":"Kagundu",
    "gn:country_code":"KE",
    "gn:dem":1972,
    "gn:feature_class":"P",
    "gn:feature_code":"PPL",
    "gn:name":"Kagundu",
    "gn:population":0,
    "gn:timezone":"Africa/Nairobi",
    "iso:country":"KE",
    "name:und_x_variant":[
        "Kagundu-ini",
        "Kagundo",
        "Kagundu"
    ],
    "wof:name":"Kagundu",
    "wof:placetype":"locality"
},
  "geometry": {"coordinates":[36.89204,-0.44448],"type":"Point"}
}