{
  "type": "Feature",
  "properties": {
    "gn:admin1_code":"15.0",
    "gn:asciiname":"Kathangari",
    "gn:country_code":"KE",
    "gn:dem":1518,
    "gn:feature_class":"P",
    "gn:feature_code":"PPL",
    "gn:name":"Kathangari",
    "gn:population":0,
    "gn:timezone":"Africa/Nairobi",
    "iso:country":"KE",
    "name:und_x_variant":[
        "Kathangare",
        "Kathangari"
    ],
    "wof:name":"Kathangari",
    "wof:placetype":"locality"
},
  "geometry": {"coordinates":[37.4406,-0.47307],"type":"Point"}
}