{
  "type": "Feature",
  "properties": {
    "gn:admin1_code":"51",
    "gn:asciiname":"Angorangora",
    "gn:country_code":"KE",
    "gn:dem":625,
    "gn:feature_class":"P",
    "gn:feature_code":"PPL",
    "gn:name":"Angorangora",
    "gn:population":0,
    "gn:timezone":"Africa/Nairobi",
    "iso:country":"KE",
    "name:und_x_variant":[
        "Kankwangangora"
    ],
    "wof:name":"Angorangora",
    "wof:placetype":"locality"
},
  "geometry": {"coordinates":[35.40045999999999,2.63469],"type":"Point"}
}