{
  "type": "Feature",
  "properties": {
    "gn:admin1_code":"38.0",
    "gn:asciiname":"Karunge",
    "gn:country_code":"KE",
    "gn:dem":1696,
    "gn:feature_class":"P",
    "gn:feature_code":"PPL",
    "gn:name":"Karunge",
    "gn:population":0,
    "gn:timezone":"Africa/Nairobi",
    "iso:country":"KE",
    "wof:name":"Karunge",
    "wof:placetype":"locality"
},
  "geometry": {"coordinates":[36.98396,-0.65754],"type":"Point"}
}