{
  "type": "Feature",
  "properties": {
    "iso:country":"KE",
    "name:eng_x_preferred":[
        "Matondoni"
    ],
    "name:fra_x_preferred":[
        "Matondoni"
    ],
    "name:nld_x_preferred":[
        "Matondoni"
    ],
    "name:und_x_variant":[
        "Matadoni"
    ],
    "qs:gn_country":"KE",
    "qs:gn_fcode":"PPL",
    "qs:gn_pop":0,
    "qs:name":"Matondoni",
    "qs:name_adm0":"Kenya",
    "qs:name_adm1":"Coast",
    "qs:photos":1198,
    "qs:photos_1k":243,
    "qs:photos_9k":5,
    "qs:photos_9r":7,
    "qs:photos_all":1198,
    "qs:photos_sr":11,
    "qs:placetype":"Town",
    "qs:pop_sr":"4",
    "qs:woe_adm0":23424863,
    "wd:wordcount":21,
    "wof:name":"Matondoni",
    "wof:placetype":"locality"
},
  "geometry": {"coordinates":[40.83815,-2.26492],"type":"Point"}
}