{
  "type": "Feature",
  "properties": {
    "gn:admin1_code":"22.0",
    "gn:asciiname":"Gathiruini",
    "gn:country_code":"KE",
    "gn:dem":1888,
    "gn:feature_class":"P",
    "gn:feature_code":"PPL",
    "gn:name":"Gathiruini",
    "gn:population":0,
    "gn:timezone":"Africa/Nairobi",
    "iso:country":"KE",
    "wof:name":"Gathiruini",
    "wof:placetype":"locality"
},
  "geometry": {"coordinates":[36.80552,-1.02493],"type":"Point"}
}