{
  "type": "Feature",
  "properties": {
    "gn:admin1_code":"29.0",
    "gn:asciiname":"Gituandaga",
    "gn:country_code":"KE",
    "gn:dem":2383,
    "gn:feature_class":"P",
    "gn:feature_code":"PPL",
    "gn:name":"Gituandaga",
    "gn:population":0,
    "gn:timezone":"Africa/Nairobi",
    "iso:country":"KE",
    "name:und_x_variant":[
        "Gitundaga"
    ],
    "wof:name":"Gituandaga",
    "wof:placetype":"locality"
},
  "geometry": {"coordinates":[36.31082,0.15887],"type":"Point"}
}