{
  "type": "Feature",
  "properties": {
    "gn:admin1_code":"37.0",
    "gn:asciiname":"Pendeza",
    "gn:country_code":"KE",
    "gn:dem":43,
    "gn:feature_class":"P",
    "gn:feature_code":"PPL",
    "gn:name":"Pendeza",
    "gn:population":0,
    "gn:timezone":"Africa/Nairobi",
    "iso:country":"KE",
    "wof:name":"Pendeza",
    "wof:placetype":"locality"
},
  "geometry": {"coordinates":[39.63479,-3.95687],"type":"Point"}
}