{
  "type": "Feature",
  "properties": {
    "gn:admin1_code":"15.0",
    "gn:asciiname":"Gategi",
    "gn:country_code":"KE",
    "gn:dem":1115,
    "gn:feature_class":"P",
    "gn:feature_code":"PPL",
    "gn:name":"Gategi",
    "gn:population":0,
    "gn:timezone":"Africa/Nairobi",
    "iso:country":"KE",
    "wof:name":"Gategi",
    "wof:placetype":"locality"
},
  "geometry": {"coordinates":[37.42554000000001,-0.75097],"type":"Point"}
}