{
  "type": "Feature",
  "properties": {
    "gn:admin1_code":"10",
    "gn:asciiname":"Barwesa",
    "gn:country_code":"KE",
    "gn:dem":1444,
    "gn:feature_class":"P",
    "gn:feature_code":"PPL",
    "gn:name":"Barwesa",
    "gn:population":0,
    "gn:timezone":"Africa/Nairobi",
    "iso:country":"KE",
    "name:azb_x_preferred":[
        "\u0628\u0627\u0631\u0648\u0633\u0627"
    ],
    "name:fas_x_preferred":[
        "\u0628\u0627\u0631\u0648\u0633\u0627"
    ],
    "name:und_x_variant":[
        "Barwessa",
        "Barwesa"
    ],
    "wof:name":"Barwesa",
    "wof:placetype":"locality"
},
  "geometry": {"coordinates":[35.73333,0.71667],"type":"Point"}
}