{
  "type": "Feature",
  "properties": {
    "gn:admin1_code":"38.0",
    "gn:asciiname":"Kiarutara",
    "gn:country_code":"KE",
    "gn:dem":2008,
    "gn:feature_class":"P",
    "gn:feature_code":"PPL",
    "gn:name":"Kiarutara",
    "gn:population":0,
    "gn:timezone":"Africa/Nairobi",
    "iso:country":"KE",
    "wof:name":"Kiarutara",
    "wof:placetype":"locality"
},
  "geometry": {"coordinates":[36.82489,-0.85684],"type":"Point"}
}