{
  "type": "Feature",
  "properties": {
    "iso:country":"KE",
    "name:ceb_x_preferred":[
        "Ahero"
    ],
    "name:eng_x_preferred":[
        "Ahero"
    ],
    "name:nld_x_preferred":[
        "Ahero"
    ],
    "name:pol_x_preferred":[
        "Ahero"
    ],
    "name:rus_x_preferred":[
        "\u0410\u0445\u0435\u0440\u043e"
    ],
    "name:spa_x_preferred":[
        "Ahero"
    ],
    "name:swa_x_preferred":[
        "Ahero"
    ],
    "name:swe_x_preferred":[
        "Ahero"
    ],
    "name:ukr_x_preferred":[
        "\u0410\u0433\u0435\u0440\u043e"
    ],
    "name:zul_x_preferred":[
        "Ahero"
    ],
    "qs:gn_country":"KE",
    "qs:gn_fcode":"PPL",
    "qs:gn_pop":8788,
    "qs:name":"Ahero",
    "qs:name_adm0":"Kenya",
    "qs:name_adm1":"Nyanza",
    "qs:photos":11,
    "qs:photos_1k":2,
    "qs:photos_9k":1,
    "qs:photos_9r":1,
    "qs:photos_all":11,
    "qs:photos_sr":1,
    "qs:placetype":"Town",
    "qs:pop_sr":"5",
    "qs:woe_adm0":23424863,
    "wd:wordcount":131,
    "wof:name":"Ahero",
    "wof:placetype":"locality",
    "wof:population":8788
},
  "geometry": {"coordinates":[34.9163,-0.17462],"type":"Point"}
}