{
  "type": "Feature",
  "properties": {
    "iso:country":"KE",
    "name:dut_x_preferred":[
        "Kikambala"
    ],
    "name:eng_x_preferred":[
        "Kikambala"
    ],
    "name:jpn_x_preferred":[
        "\u30ad\u30ab\u30f3\u30d0\u30e9"
    ],
    "qs:gn_country":"KE",
    "qs:gn_fcode":"PPL",
    "qs:gn_pop":0,
    "qs:name":"Kikambala",
    "qs:name_adm0":"Kenya",
    "qs:name_adm1":"Coast",
    "qs:photos":209,
    "qs:photos_1k":42,
    "qs:photos_9k":1,
    "qs:photos_9r":4,
    "qs:photos_all":209,
    "qs:photos_sr":4,
    "qs:placetype":"Town",
    "qs:pop_sr":"0",
    "qs:woe_adm0":23424863,
    "wd:wordcount":22,
    "wof:name":"Kikambala",
    "wof:placetype":"locality"
},
  "geometry": {"coordinates":[39.79341,-3.89732],"type":"Point"}
}