{
  "type": "Feature",
  "properties": {
    "gn:admin1_code":"03",
    "gn:asciiname":"Mataka",
    "gn:country_code":"KE",
    "gn:dem":738,
    "gn:feature_class":"P",
    "gn:feature_code":"PPLL",
    "gn:name":"Mataka",
    "gn:population":0,
    "gn:timezone":"Africa/Nairobi",
    "iso:country":"KE",
    "name:eng_x_preferred":[
        "Kavoko"
    ],
    "wof:name":"Mataka",
    "wof:placetype":"locality"
},
  "geometry": {"coordinates":[38.18504,-0.4549],"type":"Point"}
}