{
  "type": "Feature",
  "properties": {
    "gn:admin1_code":"22.0",
    "gn:asciiname":"Gathiga",
    "gn:country_code":"KE",
    "gn:dem":1852,
    "gn:feature_class":"P",
    "gn:feature_code":"PPL",
    "gn:name":"Gathiga",
    "gn:population":0,
    "gn:timezone":"Africa/Nairobi",
    "iso:country":"KE",
    "wof:name":"Gathiga",
    "wof:placetype":"locality"
},
  "geometry": {"coordinates":[36.73739000000001,-1.21806],"type":"Point"}
}