{
  "type": "Feature",
  "properties": {
    "gn:admin1_code":"22.0",
    "gn:asciiname":"Gichoto",
    "gn:country_code":"KE",
    "gn:dem":1989,
    "gn:feature_class":"P",
    "gn:feature_code":"PPL",
    "gn:name":"Gichoto",
    "gn:population":0,
    "gn:timezone":"Africa/Nairobi",
    "iso:country":"KE",
    "wof:name":"Gichoto",
    "wof:placetype":"locality"
},
  "geometry": {"coordinates":[36.65145,-1.27853],"type":"Point"}
}