{
  "type": "Feature",
  "properties": {
    "gn:admin1_code":"42.0",
    "gn:asciiname":"Ikonge",
    "gn:country_code":"KE",
    "gn:dem":1790,
    "gn:feature_class":"P",
    "gn:feature_code":"PPL",
    "gn:name":"Ikonge",
    "gn:population":0,
    "gn:timezone":"Africa/Nairobi",
    "iso:country":"KE",
    "wof:name":"Ikonge",
    "wof:placetype":"locality"
},
  "geometry": {"coordinates":[35.02677,-0.53174],"type":"Point"}
}