{
  "type": "Feature",
  "properties": {
    "gn:admin1_code":"38.0",
    "gn:asciiname":"Gatheru",
    "gn:country_code":"KE",
    "gn:dem":1566,
    "gn:feature_class":"P",
    "gn:feature_code":"PPL",
    "gn:name":"Gatheru",
    "gn:population":0,
    "gn:timezone":"Africa/Nairobi",
    "iso:country":"KE",
    "wof:name":"Gatheru",
    "wof:placetype":"locality"
},
  "geometry": {"coordinates":[37.06828,-0.7326],"type":"Point"}
}