{
  "type": "Feature",
  "properties": {
    "iso:country":"KE",
    "qs:gn_pop":0,
    "qs:name":"Uplands",
    "qs:name_adm0":"Kenya",
    "qs:name_adm1":"Central",
    "qs:photos":178,
    "qs:photos_1k":36,
    "qs:photos_9k":1,
    "qs:photos_9r":4,
    "qs:photos_all":178,
    "qs:photos_sr":4,
    "qs:placetype":"Town",
    "qs:pop_sr":"0",
    "qs:woe_adm0":23424863,
    "wd:wordcount":376,
    "wof:name":"Uplands",
    "wof:placetype":"locality"
},
  "geometry": {"coordinates":[36.60256,-1.024841],"type":"Point"}
}