{
  "type": "Feature",
  "properties": {
    "gn:admin1_code":"28.0",
    "gn:asciiname":"Tiribe",
    "gn:country_code":"KE",
    "gn:dem":209,
    "gn:feature_class":"P",
    "gn:feature_code":"PPL",
    "gn:name":"Tiribe",
    "gn:population":0,
    "gn:timezone":"Africa/Nairobi",
    "iso:country":"KE",
    "wof:name":"Tiribe",
    "wof:placetype":"locality"
},
  "geometry": {"coordinates":[39.25494000000001,-4.31949],"type":"Point"}
}