{
  "type": "Feature",
  "properties": {
    "gn:admin1_code":"13.0",
    "gn:asciiname":"Mbweka",
    "gn:country_code":"KE",
    "gn:dem":1197,
    "gn:feature_class":"P",
    "gn:feature_code":"PPL",
    "gn:name":"Mbweka",
    "gn:population":0,
    "gn:timezone":"Africa/Nairobi",
    "iso:country":"KE",
    "name:und_x_variant":[
        "Mbwekas",
        "Mbweka"
    ],
    "wof:name":"Mbweka",
    "wof:placetype":"locality"
},
  "geometry": {"coordinates":[34.15,0.45],"type":"Point"}
}