{
  "type": "Feature",
  "properties": {
    "gn:admin1_code":"10.0",
    "gn:asciiname":"Kapedo",
    "gn:country_code":"KE",
    "gn:dem":864,
    "gn:feature_class":"P",
    "gn:feature_code":"PPL",
    "gn:name":"Kapedo",
    "gn:population":0,
    "gn:timezone":"Africa/Nairobi",
    "iso:country":"KE",
    "name:azb_x_preferred":[
        "\u06a9\u0627\u067e\u062f\u0648"
    ],
    "name:fas_x_preferred":[
        "\u06a9\u0627\u067e\u062f\u0648"
    ],
    "name:und_x_variant":[
        "Karpedo",
        "Karpeddo",
        "Kapedo"
    ],
    "wof:name":"Kapedo",
    "wof:placetype":"locality"
},
  "geometry": {"coordinates":[36.03901,1.17453],"type":"Point"}
}