{
  "type": "Feature",
  "properties": {
    "gn:admin1_code":"46.0",
    "gn:asciiname":"Kalandini",
    "gn:country_code":"KE",
    "gn:dem":1175,
    "gn:feature_class":"P",
    "gn:feature_code":"PPL",
    "gn:name":"Kalandini",
    "gn:population":0,
    "gn:timezone":"Africa/Nairobi",
    "iso:country":"KE",
    "wof:name":"Kalandini",
    "wof:placetype":"locality"
},
  "geometry": {"coordinates":[34.36621,-0.17387],"type":"Point"}
}