{
  "type": "Feature",
  "properties": {
    "gn:admin1_code":"48",
    "gn:asciiname":"Gomesa",
    "gn:country_code":"KE",
    "gn:dem":10,
    "gn:feature_class":"P",
    "gn:feature_code":"PPL",
    "gn:name":"Gomesa",
    "gn:population":0,
    "gn:timezone":"Africa/Nairobi",
    "iso:country":"KE",
    "name:ara_x_preferred":[
        "\u063a\u0648\u0645\u064a\u0632\u0629"
    ],
    "name:ceb_x_preferred":[
        "Gomesa"
    ],
    "name:fra_x_preferred":[
        "Gomesa"
    ],
    "name:mrj_x_preferred":[
        "\u0413\u043e\u043c\u0435\u0437\u0430"
    ],
    "name:por_x_preferred":[
        "Gomesa"
    ],
    "name:spa_x_preferred":[
        "Gomesa"
    ],
    "name:srp_x_preferred":[
        "Gomesa"
    ],
    "name:swe_x_preferred":[
        "Gomesa"
    ],
    "name:vie_x_preferred":[
        "Gomesa"
    ],
    "name:war_x_preferred":[
        "Gomesa"
    ],
    "wof:name":"Gomesa",
    "wof:placetype":"locality"
},
  "geometry": {"coordinates":[40.21607,-2.34635],"type":"Point"}
}