{
  "type": "Feature",
  "properties": {
    "gn:admin1_code":"48",
    "gn:asciiname":"Gomesa",
    "gn:country_code":"KE",
    "gn:dem":10,
    "gn:feature_class":"P",
    "gn:feature_code":"PPL",
    "gn:name":"Gomesa",
    "gn:population":0,
    "gn:timezone":"Africa/Nairobi",
    "iso:country":"KE",
    "wof:name":"Gomesa",
    "wof:placetype":"locality"
},
  "geometry": {"coordinates":[40.21607,-2.34635],"type":"Point"}
}