{
  "type": "Feature",
  "properties": {
    "gn:admin1_code":"28.0",
    "gn:asciiname":"Mkomba",
    "gn:country_code":"KE",
    "gn:dem":220,
    "gn:feature_class":"P",
    "gn:feature_code":"PPL",
    "gn:name":"Mkomba",
    "gn:population":0,
    "gn:timezone":"Africa/Nairobi",
    "iso:country":"KE",
    "wof:name":"Mkomba",
    "wof:placetype":"locality"
},
  "geometry": {"coordinates":[39.2589,-4.30109],"type":"Point"}
}