{
  "type": "Feature",
  "properties": {
    "gn:admin1_code":"31.0",
    "gn:asciiname":"Kiteta",
    "gn:country_code":"KE",
    "gn:dem":1241,
    "gn:feature_class":"P",
    "gn:feature_code":"PPL",
    "gn:name":"Kiteta",
    "gn:population":0,
    "gn:timezone":"Africa/Nairobi",
    "iso:country":"KE",
    "wof:name":"Kiteta",
    "wof:placetype":"locality"
},
  "geometry": {"coordinates":[37.52332,-1.49961],"type":"Point"}
}