{
  "type": "Feature",
  "properties": {
    "gn:admin1_code":"47.0",
    "gn:asciiname":"Shelemba",
    "gn:country_code":"KE",
    "gn:dem":805,
    "gn:feature_class":"P",
    "gn:feature_code":"PPL",
    "gn:name":"Shelemba",
    "gn:population":0,
    "gn:timezone":"Africa/Nairobi",
    "iso:country":"KE",
    "wof:name":"Shelemba",
    "wof:placetype":"locality"
},
  "geometry": {"coordinates":[38.4611,-3.43734],"type":"Point"}
}