{
  "type": "Feature",
  "properties": {
    "gn:admin1_code":"54.0",
    "gn:asciiname":"Habaswein",
    "gn:country_code":"KE",
    "gn:dem":204,
    "gn:feature_class":"P",
    "gn:feature_code":"PPL",
    "gn:name":"Habaswein",
    "gn:population":0,
    "gn:timezone":"Africa/Nairobi",
    "iso:country":"KE",
    "name:urd_x_preferred":[
        "\u062d\u0628\u0633 \u0648\u0627\u0626\u0646"
    ],
    "wof:name":"Habaswein",
    "wof:placetype":"locality"
},
  "geometry": {"coordinates":[39.49122,1.01659],"type":"Point"}
}