{
  "type": "Feature",
  "properties": {
    "gn:admin1_code":"49.0",
    "gn:asciiname":"Kamaende",
    "gn:country_code":"KE",
    "gn:dem":732,
    "gn:feature_class":"P",
    "gn:feature_code":"PPL",
    "gn:name":"Kamaende",
    "gn:population":0,
    "gn:timezone":"Africa/Nairobi",
    "iso:country":"KE",
    "wof:name":"Kamaende",
    "wof:placetype":"locality"
},
  "geometry": {"coordinates":[37.85685,-0.36401],"type":"Point"}
}