{
  "type": "Feature",
  "properties": {
    "gn:admin1_code":"37.0",
    "gn:asciiname":"Shimo la Tewa",
    "gn:country_code":"KE",
    "gn:dem":22,
    "gn:feature_class":"P",
    "gn:feature_code":"PPL",
    "gn:name":"Shimo la Tewa",
    "gn:population":0,
    "gn:timezone":"Africa/Nairobi",
    "iso:country":"KE",
    "wof:name":"Shimo la Tewa",
    "wof:placetype":"locality"
},
  "geometry": {"coordinates":[39.73799,-3.95545],"type":"Point"}
}