{
  "type": "Feature",
  "properties": {
    "gn:admin1_code":"38.0",
    "gn:asciiname":"Gathukeini",
    "gn:country_code":"KE",
    "gn:dem":1524,
    "gn:feature_class":"P",
    "gn:feature_code":"PPL",
    "gn:name":"Gathukeini",
    "gn:population":0,
    "gn:timezone":"Africa/Nairobi",
    "iso:country":"KE",
    "name:und_x_variant":[
        "Kathukeini",
        "Kathukeni",
        "Gathukiini",
        "Gathukeini"
    ],
    "wof:name":"Gathukeini",
    "wof:placetype":"locality"
},
  "geometry": {"coordinates":[37.06695,-0.63477],"type":"Point"}
}