{
  "type": "Feature",
  "properties": {
    "gn:admin1_code":"55.0",
    "gn:asciiname":"Morkwijit",
    "gn:country_code":"KE",
    "gn:dem":1997,
    "gn:feature_class":"P",
    "gn:feature_code":"PPL",
    "gn:name":"Morkwijit",
    "gn:population":0,
    "gn:timezone":"Africa/Nairobi",
    "iso:country":"KE",
    "name:und_x_variant":[
        "Nakwajit",
        "Morkwijit"
    ],
    "wof:name":"Morkwijit",
    "wof:placetype":"locality"
},
  "geometry": {"coordinates":[35.0842,1.19795],"type":"Point"}
}