{
  "type": "Feature",
  "properties": {
    "iso:country":"KE",
    "name:eng_x_preferred":[
        "Elmenteita"
    ],
    "name:nld_x_preferred":[
        "Elmenteita"
    ],
    "qs:gn_country":"KE",
    "qs:gn_fcode":"PPL",
    "qs:gn_pop":0,
    "qs:name":"Elmenteita",
    "qs:name_adm0":"Kenya",
    "qs:name_adm1":"Rift Valley",
    "qs:photos":24,
    "qs:photos_1k":5,
    "qs:photos_9k":1,
    "qs:photos_9r":1,
    "qs:photos_all":24,
    "qs:photos_sr":1,
    "qs:placetype":"Town",
    "qs:pop_sr":"0",
    "qs:woe_adm0":23424863,
    "wd:wordcount":9,
    "wof:name":"Elmenteita",
    "wof:placetype":"locality"
},
  "geometry": {"coordinates":[36.1575,-0.48697],"type":"Point"}
}