{
  "type": "Feature",
  "properties": {
    "gn:admin1_code":"24.0",
    "gn:asciiname":"Kianyaga",
    "gn:country_code":"KE",
    "gn:dem":1474,
    "gn:feature_class":"P",
    "gn:feature_code":"PPL",
    "gn:name":"Kianyaga",
    "gn:population":0,
    "gn:timezone":"Africa/Nairobi",
    "iso:country":"KE",
    "name:und_x_variant":[
        "Kienyagga",
        "Kianyagga",
        "Kianyaga"
    ],
    "wof:name":"Kianyaga",
    "wof:placetype":"locality"
},
  "geometry": {"coordinates":[37.35027,-0.49546],"type":"Point"}
}