{
  "type": "Feature",
  "properties": {
    "gn:admin1_code":"08",
    "gn:asciiname":"Enkokidongoi",
    "gn:country_code":"KE",
    "gn:dem":1293,
    "gn:feature_class":"P",
    "gn:feature_code":"PPL",
    "gn:name":"Enkokidongoi",
    "gn:population":0,
    "gn:timezone":"Africa/Nairobi",
    "iso:country":"KE",
    "wof:name":"Enkokidongoi",
    "wof:placetype":"locality"
},
  "geometry": {"coordinates":[36.81667,-2.53333],"type":"Point"}
}