{
  "type": "Feature",
  "properties": {
    "gn:admin1_code":"24.0",
    "gn:asciiname":"Ndindiruku",
    "gn:country_code":"KE",
    "gn:dem":1144,
    "gn:feature_class":"P",
    "gn:feature_code":"PPL",
    "gn:name":"Ndindiruku",
    "gn:population":0,
    "gn:timezone":"Africa/Nairobi",
    "iso:country":"KE",
    "wof:name":"Ndindiruku",
    "wof:placetype":"locality"
},
  "geometry": {"coordinates":[37.40993,-0.7189],"type":"Point"}
}