{
  "type": "Feature",
  "properties": {
    "iso:country":"KE",
    "name:bul_x_preferred":[
        "\u041b\u043e\u0438\u0435\u043d\u0433\u0430\u043b\u0430\u043d\u0438"
    ],
    "name:cat_x_preferred":[
        "Loyangalani"
    ],
    "name:eng_x_preferred":[
        "Loiyangalani"
    ],
    "name:ita_x_preferred":[
        "Loyangalani"
    ],
    "name:jpn_x_preferred":[
        "\u30ed\u30a4\u30e4\u30f3\u30ac\u30e9\u30cb\u30fc"
    ],
    "name:kat_x_preferred":[
        "\u10da\u10dd\u10d8\u10d8\u10d0\u10dc\u10d2\u10d0\u10da\u10d0\u10dc\u10d8"
    ],
    "name:nld_x_preferred":[
        "Loiyangalani"
    ],
    "name:ron_x_preferred":[
        "Loyangalani"
    ],
    "name:swa_x_preferred":[
        "Loiyangalani"
    ],
    "name:swe_x_preferred":[
        "Loiyangalani"
    ],
    "name:urd_x_preferred":[
        "\u0644\u0648\u0626\u06cc\u0627\u0646\u06af\u0627\u0644\u0627\u0646\u06cc"
    ],
    "name:zho_x_preferred":[
        "\u7f85\u63da\u52a0\u62c9\u5c3c"
    ],
    "qs:gn_pop":0,
    "qs:name":"Loiyangalani",
    "qs:name_adm0":"Kenya",
    "qs:name_adm1":"Eastern",
    "qs:photos":53,
    "qs:photos_1k":11,
    "qs:photos_9k":1,
    "qs:photos_9r":2,
    "qs:photos_all":53,
    "qs:photos_sr":2,
    "qs:placetype":"Town",
    "qs:pop_sr":"0",
    "qs:woe_adm0":23424863,
    "wd:wordcount":250,
    "wof:name":"Loiyangalani",
    "wof:placetype":"locality"
},
  "geometry": {"coordinates":[36.707725,2.728041],"type":"Point"}
}