{
  "type": "Feature",
  "properties": {
    "gn:admin1_code":"23.0",
    "gn:asciiname":"Ribe",
    "gn:country_code":"KE",
    "gn:dem":169,
    "gn:feature_class":"P",
    "gn:feature_code":"PPL",
    "gn:name":"Ribe",
    "gn:population":0,
    "gn:timezone":"Africa/Nairobi",
    "iso:country":"KE",
    "name:cat_x_preferred":[
        "Ribe"
    ],
    "name:ceb_x_preferred":[
        "Ribe"
    ],
    "name:ces_x_preferred":[
        "Ribe"
    ],
    "name:dan_x_preferred":[
        "Ribe"
    ],
    "name:deu_x_preferred":[
        "Ribe"
    ],
    "name:epo_x_preferred":[
        "Ribe"
    ],
    "name:est_x_preferred":[
        "Ribe"
    ],
    "name:eus_x_preferred":[
        "Ribe"
    ],
    "name:fao_x_preferred":[
        "Ribe"
    ],
    "name:fas_x_preferred":[
        "\u0631\u06cc\u0628\u0647"
    ],
    "name:fin_x_preferred":[
        "Ribe"
    ],
    "name:fra_x_preferred":[
        "Ribe"
    ],
    "name:glg_x_preferred":[
        "Ribe"
    ],
    "name:hrv_x_preferred":[
        "Ribe"
    ],
    "name:hun_x_preferred":[
        "Ribe"
    ],
    "name:ind_x_preferred":[
        "Ribe"
    ],
    "name:isl_x_preferred":[
        "R\u00edpar"
    ],
    "name:jpn_x_preferred":[
        "\u30ea\u30fc\u30d9"
    ],
    "name:kor_x_preferred":[
        "\ub9ac\ubca0"
    ],
    "name:nld_x_preferred":[
        "Ribe"
    ],
    "name:nno_x_preferred":[
        "Ribe"
    ],
    "name:nor_x_preferred":[
        "Ribe"
    ],
    "name:pol_x_preferred":[
        "Ribe"
    ],
    "name:por_x_preferred":[
        "Ribe"
    ],
    "name:ron_x_preferred":[
        "Ribe"
    ],
    "name:rus_x_preferred":[
        "\u0420\u0438\u0431\u0435"
    ],
    "name:sco_x_preferred":[
        "Ribe"
    ],
    "name:slk_x_preferred":[
        "Ribe"
    ],
    "name:spa_x_preferred":[
        "Ribe"
    ],
    "name:srp_x_preferred":[
        "\u0420\u0438\u0431\u0435"
    ],
    "name:swe_x_preferred":[
        "Ribe"
    ],
    "name:ukr_x_preferred":[
        "\u0420\u0456\u0431\u0435"
    ],
    "name:und_x_variant":[
        "Ribe Mission",
        "Ribe"
    ],
    "wof:name":"Ribe",
    "wof:placetype":"locality"
},
  "geometry": {"coordinates":[39.63298,-3.88536],"type":"Point"}
}