{
  "type": "Feature",
  "properties": {
    "gn:admin1_code":"38.0",
    "gn:asciiname":"Gacharageini",
    "gn:country_code":"KE",
    "gn:dem":2075,
    "gn:feature_class":"P",
    "gn:feature_code":"PPL",
    "gn:name":"Gacharageini",
    "gn:population":0,
    "gn:timezone":"Africa/Nairobi",
    "iso:country":"KE",
    "wof:name":"Gacharageini",
    "wof:placetype":"locality"
},
  "geometry": {"coordinates":[36.86183,-0.62522],"type":"Point"}
}