{
  "type": "Feature",
  "properties": {
    "gn:admin1_code":"52.0",
    "gn:asciiname":"Moi`s Bridge",
    "gn:country_code":"KE",
    "gn:dem":1842,
    "gn:feature_class":"P",
    "gn:feature_code":"PPL",
    "gn:name":"Moi\u2018s Bridge",
    "gn:population":0,
    "gn:timezone":"Africa/Nairobi",
    "iso:country":"KE",
    "name:und_x_variant":[
        "Moi\u2019s Bridge",
        "Hoeys Bridge",
        "Moi\u2018s Bridge"
    ],
    "wof:name":"Moi`s Bridge",
    "wof:placetype":"locality"
},
  "geometry": {"coordinates":[35.12213,0.87178],"type":"Point"}
}