{
  "type": "Feature",
  "properties": {
    "gn:admin1_code":"23.0",
    "gn:asciiname":"Junju",
    "gn:country_code":"KE",
    "gn:dem":100,
    "gn:feature_class":"P",
    "gn:feature_code":"PPL",
    "gn:name":"Junju",
    "gn:population":0,
    "gn:timezone":"Africa/Nairobi",
    "iso:country":"KE",
    "wof:name":"Junju",
    "wof:placetype":"locality"
},
  "geometry": {"coordinates":[39.75116,-3.84929],"type":"Point"}
}