{
  "type": "Feature",
  "properties": {
    "gn:admin1_code":"22.0",
    "gn:asciiname":"Gathanji",
    "gn:country_code":"KE",
    "gn:dem":1887,
    "gn:feature_class":"P",
    "gn:feature_code":"PPL",
    "gn:name":"Gathanji",
    "gn:population":0,
    "gn:timezone":"Africa/Nairobi",
    "iso:country":"KE",
    "name:kik_x_preferred":[
        "Gathanji"
    ],
    "wof:name":"Gathanji",
    "wof:placetype":"locality"
},
  "geometry": {"coordinates":[36.76795,-1.08259],"type":"Point"}
}