{
  "type": "Feature",
  "properties": {
    "gn:admin1_code":"51.0",
    "gn:asciiname":"Lorukumu",
    "gn:country_code":"KE",
    "gn:dem":614,
    "gn:feature_class":"P",
    "gn:feature_code":"PPL",
    "gn:name":"Lorukumu",
    "gn:population":0,
    "gn:timezone":"Africa/Nairobi",
    "iso:country":"KE",
    "name:und_x_variant":[
        "Lorugumu"
    ],
    "wof:name":"Lorukumu",
    "wof:placetype":"locality"
},
  "geometry": {"coordinates":[35.26492000000001,2.89199],"type":"Point"}
}