{
  "type": "Feature",
  "properties": {
    "gn:admin1_code":"49.0",
    "gn:asciiname":"Kiakanyinga",
    "gn:country_code":"KE",
    "gn:dem":1275,
    "gn:feature_class":"P",
    "gn:feature_code":"PPL",
    "gn:name":"Kiakanyinga",
    "gn:population":0,
    "gn:timezone":"Africa/Nairobi",
    "iso:country":"KE",
    "wof:name":"Kiakanyinga",
    "wof:placetype":"locality"
},
  "geometry": {"coordinates":[37.69845,-0.25829],"type":"Point"}
}