{
  "type": "Feature",
  "properties": {
    "gn:admin1_code":"35.0",
    "gn:asciiname":"Mikinduri",
    "gn:country_code":"KE",
    "gn:dem":1299,
    "gn:feature_class":"P",
    "gn:feature_code":"PPL",
    "gn:name":"Mikinduri",
    "gn:population":0,
    "gn:timezone":"Africa/Nairobi",
    "iso:country":"KE",
    "wof:name":"Mikinduri",
    "wof:placetype":"locality"
},
  "geometry": {"coordinates":[37.83594,0.12335],"type":"Point"}
}