{
  "type": "Feature",
  "properties": {
    "gn:admin1_code":"32.0",
    "gn:asciiname":"Kalamba",
    "gn:country_code":"KE",
    "gn:dem":1137,
    "gn:feature_class":"P",
    "gn:feature_code":"PPL",
    "gn:name":"Kalamba",
    "gn:population":0,
    "gn:timezone":"Africa/Nairobi",
    "iso:country":"KE",
    "name:ita_x_preferred":[
        "Kalamba"
    ],
    "name:swa_x_preferred":[
        "Kalamba"
    ],
    "wof:name":"Kalamba",
    "wof:placetype":"locality"
},
  "geometry": {"coordinates":[37.5122,-1.86826],"type":"Point"}
}