{
  "type": "Feature",
  "properties": {
    "gn:admin1_code":"45",
    "gn:asciiname":"Sukuta Lol Marmar",
    "gn:country_code":"KE",
    "gn:dem":1793,
    "gn:feature_class":"P",
    "gn:feature_code":"PPL",
    "gn:name":"Sukuta Lol Marmar",
    "gn:population":0,
    "gn:timezone":"Africa/Nairobi",
    "iso:country":"KE",
    "wof:name":"Sukuta Lol Marmar",
    "wof:placetype":"locality"
},
  "geometry": {"coordinates":[36.68979,0.82772],"type":"Point"}
}