{
  "type": "Feature",
  "properties": {
    "gn:admin1_code":"46.0",
    "gn:asciiname":"Nyangweso",
    "gn:country_code":"KE",
    "gn:dem":1442,
    "gn:feature_class":"P",
    "gn:feature_code":"PPL",
    "gn:name":"Nyangweso",
    "gn:population":0,
    "gn:timezone":"Africa/Nairobi",
    "iso:country":"KE",
    "wof:name":"Nyangweso",
    "wof:placetype":"locality"
},
  "geometry": {"coordinates":[34.45694,0.07667],"type":"Point"}
}