{
  "type": "Feature",
  "properties": {
    "gn:admin1_code":"38.0",
    "gn:asciiname":"Mununga",
    "gn:country_code":"KE",
    "gn:dem":1513,
    "gn:feature_class":"P",
    "gn:feature_code":"PPL",
    "gn:name":"Mununga",
    "gn:population":0,
    "gn:timezone":"Africa/Nairobi",
    "iso:country":"KE",
    "wof:name":"Mununga",
    "wof:placetype":"locality"
},
  "geometry": {"coordinates":[37.04304000000001,-0.69689],"type":"Point"}
}