{
  "type": "Feature",
  "properties": {
    "gn:admin1_code":"32",
    "gn:asciiname":"Emali",
    "gn:country_code":"KE",
    "gn:dem":1149,
    "gn:feature_class":"P",
    "gn:feature_code":"PPL",
    "gn:name":"Emali",
    "gn:population":0,
    "gn:timezone":"Africa/Nairobi",
    "iso:country":"KE",
    "wof:name":"Emali",
    "wof:placetype":"locality"
},
  "geometry": {"coordinates":[37.47202,-2.08033],"type":"Point"}
}