{
  "type": "Feature",
  "properties": {
    "gn:admin1_code":"44.0",
    "gn:asciiname":"Rukira",
    "gn:country_code":"KE",
    "gn:dem":1858,
    "gn:feature_class":"P",
    "gn:feature_code":"PPL",
    "gn:name":"Rukira",
    "gn:population":0,
    "gn:timezone":"Africa/Nairobi",
    "iso:country":"KE",
    "wof:name":"Rukira",
    "wof:placetype":"locality"
},
  "geometry": {"coordinates":[36.93664,-0.53722],"type":"Point"}
}