{
  "type": "Feature",
  "properties": {
    "gn:admin1_code":"34",
    "gn:asciiname":"Choba",
    "gn:country_code":"KE",
    "gn:dem":1063,
    "gn:feature_class":"P",
    "gn:feature_code":"PPL",
    "gn:name":"Choba",
    "gn:population":0,
    "gn:timezone":"Africa/Nairobi",
    "iso:country":"KE",
    "wof:name":"Choba",
    "wof:placetype":"locality"
},
  "geometry": {"coordinates":[38.04091,2.42609],"type":"Point"}
}