{
  "type": "Feature",
  "properties": {
    "gn:admin1_code":"22.0",
    "gn:asciiname":"Karia",
    "gn:country_code":"KE",
    "gn:dem":1684,
    "gn:feature_class":"P",
    "gn:feature_code":"PPL",
    "gn:name":"Karia",
    "gn:population":0,
    "gn:timezone":"Africa/Nairobi",
    "iso:country":"KE",
    "wof:name":"Karia",
    "wof:placetype":"locality"
},
  "geometry": {"coordinates":[36.91667,-0.98333],"type":"Point"}
}