{
  "type": "Feature",
  "properties": {
    "gn:admin1_code":"28",
    "gn:asciiname":"Ngozini",
    "gn:country_code":"KE",
    "gn:dem":147,
    "gn:feature_class":"P",
    "gn:feature_code":"PPL",
    "gn:name":"Ngozini",
    "gn:population":0,
    "gn:timezone":"Africa/Nairobi",
    "iso:country":"KE",
    "wof:name":"Ngozini",
    "wof:placetype":"locality"
},
  "geometry": {"coordinates":[39.42367,-4.1297],"type":"Point"}
}