{
  "type": "Feature",
  "properties": {
    "gn:admin1_code":"24.0",
    "gn:asciiname":"Karaba",
    "gn:country_code":"KE",
    "gn:dem":1115,
    "gn:feature_class":"P",
    "gn:feature_code":"PPL",
    "gn:name":"Karaba",
    "gn:population":0,
    "gn:timezone":"Africa/Nairobi",
    "iso:country":"KE",
    "name:ceb_x_preferred":[
        "Karaba"
    ],
    "name:fra_x_preferred":[
        "Karaba"
    ],
    "name:swe_x_preferred":[
        "Karaba"
    ],
    "wof:name":"Karaba",
    "wof:placetype":"locality"
},
  "geometry": {"coordinates":[37.41667,-0.75],"type":"Point"}
}