{
  "type": "Feature",
  "properties": {
    "gn:admin1_code":"44.0",
    "gn:asciiname":"Ihwa",
    "gn:country_code":"KE",
    "gn:dem":2067,
    "gn:feature_class":"P",
    "gn:feature_code":"PPL",
    "gn:name":"Ihwa",
    "gn:population":0,
    "gn:timezone":"Africa/Nairobi",
    "iso:country":"KE",
    "name:und_x_variant":[
        "Ihua",
        "Ihwa"
    ],
    "wof:name":"Ihwa",
    "wof:placetype":"locality"
},
  "geometry": {"coordinates":[36.86794,-0.42584],"type":"Point"}
}