{
  "type": "Feature",
  "properties": {
    "gn:admin1_code":"28",
    "gn:asciiname":"Bomani",
    "gn:country_code":"KE",
    "gn:dem":174,
    "gn:feature_class":"P",
    "gn:feature_code":"PPL",
    "gn:name":"Bomani",
    "gn:population":0,
    "gn:timezone":"Africa/Nairobi",
    "iso:country":"KE",
    "wof:name":"Bomani",
    "wof:placetype":"locality"
},
  "geometry": {"coordinates":[39.14781,-4.24798],"type":"Point"}
}