{
  "type": "Feature",
  "properties": {
    "gn:admin1_code":"38.0",
    "gn:asciiname":"Gitui",
    "gn:country_code":"KE",
    "gn:dem":1552,
    "gn:feature_class":"P",
    "gn:feature_code":"PPL",
    "gn:name":"Gitui",
    "gn:population":0,
    "gn:timezone":"Africa/Nairobi",
    "iso:country":"KE",
    "wof:name":"Gitui",
    "wof:placetype":"locality"
},
  "geometry": {"coordinates":[37.0536,-0.74544],"type":"Point"}
}