{
  "type": "Feature",
  "properties": {
    "gn:admin1_code":"33",
    "gn:asciiname":"Arda Dadaja",
    "gn:country_code":"KE",
    "gn:dem":408,
    "gn:feature_class":"P",
    "gn:feature_code":"PPL",
    "gn:name":"Arda Dadaja",
    "gn:population":0,
    "gn:timezone":"Africa/Nairobi",
    "iso:country":"KE",
    "wof:name":"Arda Dadaja",
    "wof:placetype":"locality"
},
  "geometry": {"coordinates":[41.05517,2.90873],"type":"Point"}
}