{
  "type": "Feature",
  "properties": {
    "gn:admin1_code":"28.0",
    "gn:asciiname":"Mwabila",
    "gn:country_code":"KE",
    "gn:dem":155,
    "gn:feature_class":"P",
    "gn:feature_code":"PPL",
    "gn:name":"Mwabila",
    "gn:population":0,
    "gn:timezone":"Africa/Nairobi",
    "iso:country":"KE",
    "name:urd_x_preferred":[
        "\u0645\u0648\u0627\u0628\u0644\u0627"
    ],
    "wof:name":"Mwabila",
    "wof:placetype":"locality"
},
  "geometry": {"coordinates":[39.48975,-4.28754],"type":"Point"}
}