{
  "type": "Feature",
  "properties": {
    "gn:admin1_code":"22.0",
    "gn:asciiname":"Karinga",
    "gn:country_code":"KE",
    "gn:dem":1847,
    "gn:feature_class":"P",
    "gn:feature_code":"PPL",
    "gn:name":"Karinga",
    "gn:population":0,
    "gn:timezone":"Africa/Nairobi",
    "iso:country":"KE",
    "wof:name":"Karinga",
    "wof:placetype":"locality"
},
  "geometry": {"coordinates":[36.83333,-0.95],"type":"Point"}
}