{
  "type": "Feature",
  "properties": {
    "gn:admin1_code":"06",
    "gn:asciiname":"Lagdera",
    "gn:country_code":"KE",
    "gn:dem":320,
    "gn:feature_class":"P",
    "gn:feature_code":"PPL",
    "gn:name":"Lagdera",
    "gn:population":0,
    "gn:timezone":"Africa/Nairobi",
    "iso:country":"KE",
    "wof:name":"Lagdera",
    "wof:placetype":"locality"
},
  "geometry": {"coordinates":[39.25964000000001,0.11261],"type":"Point"}
}