{
  "type": "Feature",
  "properties": {
    "gn:admin1_code":"32.0",
    "gn:asciiname":"Kalulini",
    "gn:country_code":"KE",
    "gn:dem":841,
    "gn:feature_class":"P",
    "gn:feature_code":"PPL",
    "gn:name":"Kalulini",
    "gn:population":0,
    "gn:timezone":"Africa/Nairobi",
    "iso:country":"KE",
    "wof:name":"Kalulini",
    "wof:placetype":"locality"
},
  "geometry": {"coordinates":[38.00069000000001,-2.34295],"type":"Point"}
}