{
  "type": "Feature",
  "properties": {
    "gn:admin1_code":"27.0",
    "gn:asciiname":"Katothya",
    "gn:country_code":"KE",
    "gn:dem":1195,
    "gn:feature_class":"P",
    "gn:feature_code":"PPL",
    "gn:name":"Katothya",
    "gn:population":0,
    "gn:timezone":"Africa/Nairobi",
    "iso:country":"KE",
    "name:und_x_variant":[
        "Katothia",
        "Katothya"
    ],
    "wof:name":"Katothya",
    "wof:placetype":"locality"
},
  "geometry": {"coordinates":[37.72517,-1.23514],"type":"Point"}
}