{
  "type": "Feature",
  "properties": {
    "gn:admin1_code":"22.0",
    "gn:asciiname":"Mutomo",
    "gn:country_code":"KE",
    "gn:dem":1664,
    "gn:feature_class":"P",
    "gn:feature_code":"PPL",
    "gn:name":"Mutomo",
    "gn:population":0,
    "gn:timezone":"Africa/Nairobi",
    "iso:country":"KE",
    "name:swa_x_preferred":[
        "Mutomo"
    ],
    "name:urd_x_preferred":[
        "\u0645\u0648\u062a\u0648\u0645\u0648"
    ],
    "wof:name":"Mutomo",
    "wof:placetype":"locality"
},
  "geometry": {"coordinates":[36.93615,-1.02441],"type":"Point"}
}