{
  "type": "Feature",
  "properties": {
    "gn:admin1_code":"23.0",
    "gn:asciiname":"Galanema",
    "gn:country_code":"KE",
    "gn:dem":209,
    "gn:feature_class":"P",
    "gn:feature_code":"PPL",
    "gn:name":"Galanema",
    "gn:population":0,
    "gn:timezone":"Africa/Nairobi",
    "iso:country":"KE",
    "wof:name":"Galanema",
    "wof:placetype":"locality"
},
  "geometry": {"coordinates":[39.7009,-3.7248],"type":"Point"}
}