{
  "type": "Feature",
  "properties": {
    "gn:admin1_code":"48.0",
    "gn:asciiname":"Marembo",
    "gn:country_code":"KE",
    "gn:dem":17,
    "gn:feature_class":"P",
    "gn:feature_code":"PPL",
    "gn:name":"Marembo",
    "gn:population":0,
    "gn:timezone":"Africa/Nairobi",
    "iso:country":"KE",
    "wof:name":"Marembo",
    "wof:placetype":"locality"
},
  "geometry": {"coordinates":[40.17482,-2.13734],"type":"Point"}
}