{
  "type": "Feature",
  "properties": {
    "gn:admin1_code":"44.0",
    "gn:asciiname":"Kiaguthu",
    "gn:country_code":"KE",
    "gn:dem":1829,
    "gn:feature_class":"P",
    "gn:feature_code":"PPL",
    "gn:name":"Kiaguthu",
    "gn:population":0,
    "gn:timezone":"Africa/Nairobi",
    "iso:country":"KE",
    "wof:name":"Kiaguthu",
    "wof:placetype":"locality"
},
  "geometry": {"coordinates":[36.94892,-0.59387],"type":"Point"}
}