{
  "type": "Feature",
  "properties": {
    "gn:admin1_code":"23",
    "gn:asciiname":"Majengo",
    "gn:country_code":"KE",
    "gn:dem":44,
    "gn:feature_class":"P",
    "gn:feature_code":"PPL",
    "gn:name":"Majengo",
    "gn:population":0,
    "gn:timezone":"Africa/Nairobi",
    "iso:country":"KE",
    "name:ita_x_preferred":[
        "Majengo"
    ],
    "name:swa_x_preferred":[
        "Majengo"
    ],
    "wof:name":"Majengo",
    "wof:placetype":"locality"
},
  "geometry": {"coordinates":[40.08959,-2.94784],"type":"Point"}
}