{
  "type": "Feature",
  "properties": {
    "gn:admin1_code":"22.0",
    "gn:asciiname":"Gitiha",
    "gn:country_code":"KE",
    "gn:dem":2217,
    "gn:feature_class":"P",
    "gn:feature_code":"PPL",
    "gn:name":"Gitiha",
    "gn:population":0,
    "gn:timezone":"Africa/Nairobi",
    "iso:country":"KE",
    "wof:name":"Gitiha",
    "wof:placetype":"locality"
},
  "geometry": {"coordinates":[36.69469,-1.06295],"type":"Point"}
}