{
  "type": "Feature",
  "properties": {
    "gn:admin1_code":"38.0",
    "gn:asciiname":"Gatare",
    "gn:country_code":"KE",
    "gn:dem":2538,
    "gn:feature_class":"P",
    "gn:feature_code":"PPL",
    "gn:name":"Gatare",
    "gn:population":0,
    "gn:timezone":"Africa/Nairobi",
    "iso:country":"KE",
    "wof:name":"Gatare",
    "wof:placetype":"locality"
},
  "geometry": {"coordinates":[36.76775,-0.73234],"type":"Point"}
}