{
  "type": "Feature",
  "properties": {
    "gn:admin1_code":"16",
    "gn:asciiname":"Roka",
    "gn:country_code":"KE",
    "gn:dem":66,
    "gn:feature_class":"P",
    "gn:feature_code":"PPL",
    "gn:name":"Roka",
    "gn:population":0,
    "gn:timezone":"Africa/Nairobi",
    "iso:country":"KE",
    "name:khm_x_preferred":[
        "\u1783\u17bb\u17c6\u179a\u1780\u17b6"
    ],
    "name:spa_x_preferred":[
        "Roka"
    ],
    "wof:name":"Roka",
    "wof:placetype":"locality"
},
  "geometry": {"coordinates":[40.44557,-1.54899],"type":"Point"}
}