{
  "type": "Feature",
  "properties": {
    "gn:admin1_code":"22",
    "gn:asciiname":"Barigito",
    "gn:country_code":"KE",
    "gn:dem":1836,
    "gn:feature_class":"P",
    "gn:feature_code":"PPL",
    "gn:name":"Barigito",
    "gn:population":0,
    "gn:timezone":"Africa/Nairobi",
    "iso:country":"KE",
    "wof:name":"Barigito",
    "wof:placetype":"locality"
},
  "geometry": {"coordinates":[36.86667,-0.93333],"type":"Point"}
}