{
  "type": "Feature",
  "properties": {
    "gn:admin1_code":"22.0",
    "gn:asciiname":"Nderi",
    "gn:country_code":"KE",
    "gn:dem":2042,
    "gn:feature_class":"P",
    "gn:feature_code":"PPL",
    "gn:name":"Nderi",
    "gn:population":0,
    "gn:timezone":"Africa/Nairobi",
    "iso:country":"KE",
    "wof:name":"Nderi",
    "wof:placetype":"locality"
},
  "geometry": {"coordinates":[36.65144,-1.22291],"type":"Point"}
}