{
  "type": "Feature",
  "properties": {
    "gn:admin1_code":"28",
    "gn:asciiname":"Perani",
    "gn:country_code":"KE",
    "gn:dem":49,
    "gn:feature_class":"P",
    "gn:feature_code":"PPL",
    "gn:name":"Perani",
    "gn:population":0,
    "gn:timezone":"Africa/Nairobi",
    "iso:country":"KE",
    "wof:name":"Perani",
    "wof:placetype":"locality"
},
  "geometry": {"coordinates":[39.17932,-4.52471],"type":"Point"}
}