{
  "type": "Feature",
  "properties": {
    "gn:admin1_code":"19.0",
    "gn:asciiname":"Rombo",
    "gn:country_code":"KE",
    "gn:dem":1166,
    "gn:feature_class":"P",
    "gn:feature_code":"PPL",
    "gn:name":"Rombo",
    "gn:population":0,
    "gn:timezone":"Africa/Nairobi",
    "iso:country":"KE",
    "wof:name":"Rombo",
    "wof:placetype":"locality"
},
  "geometry": {"coordinates":[37.69539,-3.04631],"type":"Point"}
}