{
  "type": "Feature",
  "properties": {
    "gn:admin1_code":"31.0",
    "gn:asciiname":"Kavumbu",
    "gn:country_code":"KE",
    "gn:dem":1259,
    "gn:feature_class":"P",
    "gn:feature_code":"PPL",
    "gn:name":"Kavumbu",
    "gn:population":0,
    "gn:timezone":"Africa/Nairobi",
    "iso:country":"KE",
    "name:und_x_variant":[
        "Kivumbu"
    ],
    "wof:name":"Kavumbu",
    "wof:placetype":"locality"
},
  "geometry": {"coordinates":[37.4276,-1.52325],"type":"Point"}
}