{
  "type": "Feature",
  "properties": {
    "gn:admin1_code":"54",
    "gn:asciiname":"Hungai",
    "gn:country_code":"KE",
    "gn:dem":445,
    "gn:feature_class":"P",
    "gn:feature_code":"PPL",
    "gn:name":"Hungai",
    "gn:population":0,
    "gn:timezone":"Africa/Nairobi",
    "iso:country":"KE",
    "wof:name":"Hungai",
    "wof:placetype":"locality"
},
  "geometry": {"coordinates":[40.19462,2.2383],"type":"Point"}
}