{
  "type": "Feature",
  "properties": {
    "iso:country":"KE",
    "name:ceb_x_preferred":[
        "Pumwani"
    ],
    "name:eng_x_preferred":[
        "Pumwani"
    ],
    "name:swe_x_preferred":[
        "Pumwani"
    ],
    "name:und_x_variant":[
        "Pumuani"
    ],
    "qs:gn_country":"KE",
    "qs:gn_fcode":"PPLX",
    "qs:gn_pop":0,
    "qs:name":"Pumwani",
    "qs:name_adm0":"Kenya",
    "qs:name_adm1":"Nairobi Area",
    "qs:photos":142,
    "qs:photos_1k":29,
    "qs:photos_9k":1,
    "qs:photos_9r":3,
    "qs:photos_all":142,
    "qs:photos_sr":3,
    "qs:placetype":"Suburb",
    "qs:pop_sr":"0",
    "qs:woe_adm0":23424863,
    "wd:wordcount":139,
    "wof:name":"Pumwani",
    "wof:placetype":"neighbourhood"
},
  "geometry": {"coordinates":[36.85,-1.28333],"type":"Point"}
}