{
  "type": "Feature",
  "properties": {
    "iso:country":"KE",
    "name:eng_x_preferred":[
        "Magina"
    ],
    "name:nld_x_preferred":[
        "Magina"
    ],
    "qs:gn_country":"KE",
    "qs:gn_fcode":"PPL",
    "qs:gn_pop":0,
    "qs:name":"Magina",
    "qs:name_adm0":"Kenya",
    "qs:name_adm1":"Central",
    "qs:photos":89,
    "qs:photos_1k":18,
    "qs:photos_9k":1,
    "qs:photos_9r":3,
    "qs:photos_all":89,
    "qs:photos_sr":3,
    "qs:placetype":"Town",
    "qs:pop_sr":"4",
    "qs:woe_adm0":23424863,
    "wd:wordcount":23,
    "wof:name":"Magina",
    "wof:placetype":"locality"
},
  "geometry": {"coordinates":[36.61386,-0.94838],"type":"Point"}
}