{
  "type": "Feature",
  "properties": {
    "gn:admin1_code":"48.0",
    "gn:asciiname":"Masalani",
    "gn:country_code":"KE",
    "gn:dem":45,
    "gn:feature_class":"P",
    "gn:feature_code":"PPL",
    "gn:name":"Masalani",
    "gn:population":0,
    "gn:timezone":"Africa/Nairobi",
    "iso:country":"KE",
    "name:und_x_variant":[
        "Massalani",
        "Masalani"
    ],
    "wof:name":"Masalani",
    "wof:placetype":"locality"
},
  "geometry": {"coordinates":[40.12186,-1.69746],"type":"Point"}
}