{
  "type": "Feature",
  "properties": {
    "gn:admin1_code":"55",
    "gn:asciiname":"Chepropro",
    "gn:country_code":"KE",
    "gn:dem":821,
    "gn:feature_class":"P",
    "gn:feature_code":"PPL",
    "gn:name":"Chepropro",
    "gn:population":0,
    "gn:timezone":"Africa/Nairobi",
    "iso:country":"KE",
    "name:und_x_variant":[
        "Chepropoi"
    ],
    "wof:name":"Chepropro",
    "wof:placetype":"locality"
},
  "geometry": {"coordinates":[35.34418,2.04733],"type":"Point"}
}