{
  "type": "Feature",
  "properties": {
    "gn:admin1_code":"38.0",
    "gn:asciiname":"Gachocho",
    "gn:country_code":"KE",
    "gn:dem":1667,
    "gn:feature_class":"P",
    "gn:feature_code":"PPL",
    "gn:name":"Gachocho",
    "gn:population":0,
    "gn:timezone":"Africa/Nairobi",
    "iso:country":"KE",
    "wof:name":"Gachocho",
    "wof:placetype":"locality"
},
  "geometry": {"coordinates":[36.99124000000001,-0.78105],"type":"Point"}
}