{
  "type": "Feature",
  "properties": {
    "gn:admin1_code":"22.0",
    "gn:asciiname":"Ngababa",
    "gn:country_code":"KE",
    "gn:dem":1854,
    "gn:feature_class":"P",
    "gn:feature_code":"PPL",
    "gn:name":"Ngababa",
    "gn:population":0,
    "gn:timezone":"Africa/Nairobi",
    "iso:country":"KE",
    "wof:name":"Ngababa",
    "wof:placetype":"locality"
},
  "geometry": {"coordinates":[36.71667,-1.21667],"type":"Point"}
}