{
  "type": "Feature",
  "properties": {
    "gn:admin1_code":"24.0",
    "gn:asciiname":"Kiamuthambi",
    "gn:country_code":"KE",
    "gn:dem":1329,
    "gn:feature_class":"P",
    "gn:feature_code":"PPL",
    "gn:name":"Kiamuthambi",
    "gn:population":0,
    "gn:timezone":"Africa/Nairobi",
    "iso:country":"KE",
    "wof:name":"Kiamuthambi",
    "wof:placetype":"locality"
},
  "geometry": {"coordinates":[37.28333,-0.56667],"type":"Point"}
}