{
  "type": "Feature",
  "properties": {
    "gn:admin1_code":"26.0",
    "gn:asciiname":"Awach",
    "gn:country_code":"KE",
    "gn:dem":1225,
    "gn:feature_class":"P",
    "gn:feature_code":"PPL",
    "gn:name":"Awach",
    "gn:population":0,
    "gn:timezone":"Africa/Nairobi",
    "iso:country":"KE",
    "name:und_x_variant":[
        "Seme Awach"
    ],
    "wof:name":"Awach",
    "wof:placetype":"locality"
},
  "geometry": {"coordinates":[34.47948,-0.09348],"type":"Point"}
}