{
  "type": "Feature",
  "properties": {
    "gn:admin1_code":"48",
    "gn:asciiname":"Gerarsa",
    "gn:country_code":"KE",
    "gn:dem":156,
    "gn:feature_class":"P",
    "gn:feature_code":"PPL",
    "gn:name":"Gerarsa",
    "gn:population":0,
    "gn:timezone":"Africa/Nairobi",
    "iso:country":"KE",
    "wof:name":"Gerarsa",
    "wof:placetype":"locality"
},
  "geometry": {"coordinates":[39.47681,-2.04547],"type":"Point"}
}