{
  "type": "Feature",
  "properties": {
    "gn:admin1_code":"48.0",
    "gn:asciiname":"Wayu",
    "gn:country_code":"KE",
    "gn:dem":156,
    "gn:feature_class":"P",
    "gn:feature_code":"PPL",
    "gn:name":"Wayu",
    "gn:population":0,
    "gn:timezone":"Africa/Nairobi",
    "iso:country":"KE",
    "name:und_x_variant":[
        "Wagu",
        "Wayu"
    ],
    "wof:name":"Wayu",
    "wof:placetype":"locality"
},
  "geometry": {"coordinates":[39.58529,-1.52995],"type":"Point"}
}