{
  "type": "Feature",
  "properties": {
    "gn:admin1_code":"47.0",
    "gn:asciiname":"Kifumbu",
    "gn:country_code":"KE",
    "gn:dem":924,
    "gn:feature_class":"P",
    "gn:feature_code":"PPL",
    "gn:name":"Kifumbu",
    "gn:population":0,
    "gn:timezone":"Africa/Nairobi",
    "iso:country":"KE",
    "wof:name":"Kifumbu",
    "wof:placetype":"locality"
},
  "geometry": {"coordinates":[38.65,-3.81667],"type":"Point"}
}