{
  "type": "Feature",
  "properties": {
    "gn:admin1_code":"15.0",
    "gn:asciiname":"Kiamuringa",
    "gn:country_code":"KE",
    "gn:dem":1247,
    "gn:feature_class":"P",
    "gn:feature_code":"PPL",
    "gn:name":"Kiamuringa",
    "gn:population":0,
    "gn:timezone":"Africa/Nairobi",
    "iso:country":"KE",
    "wof:name":"Kiamuringa",
    "wof:placetype":"locality"
},
  "geometry": {"coordinates":[37.53179,-0.56976],"type":"Point"}
}