{
  "type": "Feature",
  "properties": {
    "gn:admin1_code":"48.0",
    "gn:asciiname":"Nyangwani",
    "gn:country_code":"KE",
    "gn:dem":73,
    "gn:feature_class":"P",
    "gn:feature_code":"PPL",
    "gn:name":"Nyangwani",
    "gn:population":0,
    "gn:timezone":"Africa/Nairobi",
    "iso:country":"KE",
    "wof:name":"Nyangwani",
    "wof:placetype":"locality"
},
  "geometry": {"coordinates":[40.02508,-1.26171],"type":"Point"}
}