{
  "type": "Feature",
  "properties": {
    "gn:admin1_code":"10.0",
    "gn:asciiname":"Kolowa",
    "gn:country_code":"KE",
    "gn:dem":954,
    "gn:feature_class":"P",
    "gn:feature_code":"PPL",
    "gn:name":"Kolowa",
    "gn:population":0,
    "gn:timezone":"Africa/Nairobi",
    "iso:country":"KE",
    "name:und_x_variant":[
        "Kolloa",
        "Kolowa"
    ],
    "wof:name":"Kolowa",
    "wof:placetype":"locality"
},
  "geometry": {"coordinates":[35.75490999999999,1.21686],"type":"Point"}
}