{
  "type": "Feature",
  "properties": {
    "gn:admin1_code":"48.0",
    "gn:asciiname":"Handampia",
    "gn:country_code":"KE",
    "gn:dem":56,
    "gn:feature_class":"P",
    "gn:feature_code":"PPL",
    "gn:name":"Handampia",
    "gn:population":0,
    "gn:timezone":"Africa/Nairobi",
    "iso:country":"KE",
    "wof:name":"Handampia",
    "wof:placetype":"locality"
},
  "geometry": {"coordinates":[40.06086,-1.5974],"type":"Point"}
}