{
  "type": "Feature",
  "properties": {
    "gn:admin1_code":"17.0",
    "gn:asciiname":"Marinde",
    "gn:country_code":"KE",
    "gn:dem":1379,
    "gn:feature_class":"P",
    "gn:feature_code":"PPL",
    "gn:name":"Marinde",
    "gn:population":0,
    "gn:timezone":"Africa/Nairobi",
    "iso:country":"KE",
    "wof:name":"Marinde",
    "wof:placetype":"locality"
},
  "geometry": {"coordinates":[34.52088,-0.64968],"type":"Point"}
}