{
  "type": "Feature",
  "properties": {
    "gn:admin1_code":"24.0",
    "gn:asciiname":"Kamuiru",
    "gn:country_code":"KE",
    "gn:dem":1642,
    "gn:feature_class":"P",
    "gn:feature_code":"PPL",
    "gn:name":"Kamuiru",
    "gn:population":0,
    "gn:timezone":"Africa/Nairobi",
    "iso:country":"KE",
    "wof:name":"Kamuiru",
    "wof:placetype":"locality"
},
  "geometry": {"coordinates":[37.2236,-0.49048],"type":"Point"}
}