{
  "type": "Feature",
  "properties": {
    "gn:admin1_code":"38.0",
    "gn:asciiname":"Kagira",
    "gn:country_code":"KE",
    "gn:dem":1658,
    "gn:feature_class":"P",
    "gn:feature_code":"PPL",
    "gn:name":"Kagira",
    "gn:population":0,
    "gn:timezone":"Africa/Nairobi",
    "iso:country":"KE",
    "wof:name":"Kagira",
    "wof:placetype":"locality"
},
  "geometry": {"coordinates":[37.00145,-0.85167],"type":"Point"}
}