{
  "type": "Feature",
  "properties": {
    "gn:admin1_code":"44.0",
    "gn:asciiname":"Wetima One",
    "gn:country_code":"KE",
    "gn:dem":1779,
    "gn:feature_class":"P",
    "gn:feature_code":"PPL",
    "gn:name":"Wetima One",
    "gn:population":0,
    "gn:timezone":"Africa/Nairobi",
    "iso:country":"KE",
    "wof:name":"Wetima One",
    "wof:placetype":"locality"
},
  "geometry": {"coordinates":[36.98333,-0.55],"type":"Point"}
}