{
  "type": "Feature",
  "properties": {
    "gn:admin1_code":"22.0",
    "gn:asciiname":"Githoito",
    "gn:country_code":"KE",
    "gn:dem":2386,
    "gn:feature_class":"P",
    "gn:feature_code":"PPL",
    "gn:name":"Githoito",
    "gn:population":0,
    "gn:timezone":"Africa/Nairobi",
    "iso:country":"KE",
    "wof:name":"Githoito",
    "wof:placetype":"locality"
},
  "geometry": {"coordinates":[36.65509,-0.97341],"type":"Point"}
}