{
  "type": "Feature",
  "properties": {
    "gn:admin1_code":"23.0",
    "gn:asciiname":"Marafa",
    "gn:country_code":"KE",
    "gn:dem":97,
    "gn:feature_class":"P",
    "gn:feature_code":"PPL",
    "gn:name":"Marafa",
    "gn:population":0,
    "gn:timezone":"Africa/Nairobi",
    "iso:country":"KE",
    "wof:name":"Marafa",
    "wof:placetype":"locality"
},
  "geometry": {"coordinates":[39.96155,-3.03297],"type":"Point"}
}