{
  "type": "Feature",
  "properties": {
    "gn:admin1_code":"5.0",
    "gn:asciiname":"Kanyongo",
    "gn:country_code":"KE",
    "gn:dem":1828,
    "gn:feature_class":"P",
    "gn:feature_code":"PPL",
    "gn:name":"Kanyongo",
    "gn:population":0,
    "gn:timezone":"Africa/Nairobi",
    "iso:country":"KE",
    "name:und_x_variant":[
        "Kanyongon",
        "Kanyongo"
    ],
    "wof:name":"Kanyongo",
    "wof:placetype":"locality"
},
  "geometry": {"coordinates":[36.72596,-1.24223],"type":"Point"}
}