{
  "type": "Feature",
  "properties": {
    "gn:admin1_code":"19.0",
    "gn:asciiname":"Ilpartimaro",
    "gn:country_code":"KE",
    "gn:dem":1470,
    "gn:feature_class":"P",
    "gn:feature_code":"PPL",
    "gn:name":"Ilpartimaro",
    "gn:population":0,
    "gn:timezone":"Africa/Nairobi",
    "iso:country":"KE",
    "wof:name":"Ilpartimaro",
    "wof:placetype":"locality"
},
  "geometry": {"coordinates":[36.71173,-2.27059],"type":"Point"}
}