{
  "type": "Feature",
  "properties": {
    "gn:admin1_code":"38.0",
    "gn:asciiname":"Kiria",
    "gn:country_code":"KE",
    "gn:dem":1468,
    "gn:feature_class":"P",
    "gn:feature_code":"PPL",
    "gn:name":"Kiria",
    "gn:population":0,
    "gn:timezone":"Africa/Nairobi",
    "iso:country":"KE",
    "wof:name":"Kiria",
    "wof:placetype":"locality"
},
  "geometry": {"coordinates":[37.06667,-0.75],"type":"Point"}
}