{
  "type": "Feature",
  "properties": {
    "gn:admin1_code":"18.0",
    "gn:asciiname":"Kampi Ya Juu",
    "gn:country_code":"KE",
    "gn:dem":1161,
    "gn:feature_class":"P",
    "gn:feature_code":"PPL",
    "gn:name":"Kampi Ya Juu",
    "gn:population":0,
    "gn:timezone":"Africa/Nairobi",
    "iso:country":"KE",
    "wof:name":"Kampi Ya Juu",
    "wof:placetype":"locality"
},
  "geometry": {"coordinates":[37.56667,0.33333],"type":"Point"}
}