{
  "type": "Feature",
  "properties": {
    "gn:admin1_code":"22.0",
    "gn:asciiname":"Kirenga",
    "gn:country_code":"KE",
    "gn:dem":2303,
    "gn:feature_class":"P",
    "gn:feature_code":"PPL",
    "gn:name":"Kirenga",
    "gn:population":0,
    "gn:timezone":"Africa/Nairobi",
    "iso:country":"KE",
    "wof:name":"Kirenga",
    "wof:placetype":"locality"
},
  "geometry": {"coordinates":[36.63333,-1.00865],"type":"Point"}
}