{
  "type": "Feature",
  "properties": {
    "gn:admin1_code":"41.0",
    "gn:asciiname":"Morijo",
    "gn:country_code":"KE",
    "gn:dem":2163,
    "gn:feature_class":"P",
    "gn:feature_code":"PPL",
    "gn:name":"Morijo",
    "gn:population":0,
    "gn:timezone":"Africa/Nairobi",
    "iso:country":"KE",
    "wof:name":"Morijo",
    "wof:placetype":"locality"
},
  "geometry": {"coordinates":[35.81341,-1.71064],"type":"Point"}
}