{
  "type": "Feature",
  "properties": {
    "gn:admin1_code":"16.0",
    "gn:asciiname":"Lughena",
    "gn:country_code":"KE",
    "gn:dem":109,
    "gn:feature_class":"P",
    "gn:feature_code":"PPL",
    "gn:name":"Lughena",
    "gn:population":0,
    "gn:timezone":"Africa/Nairobi",
    "iso:country":"KE",
    "wof:name":"Lughena",
    "wof:placetype":"locality"
},
  "geometry": {"coordinates":[40.88333,-0.08333],"type":"Point"}
}