{
  "type": "Feature",
  "properties": {
    "gn:admin1_code":"10.0",
    "gn:asciiname":"Lorwok",
    "gn:country_code":"KE",
    "gn:dem":1063,
    "gn:feature_class":"P",
    "gn:feature_code":"PPL",
    "gn:name":"Lorwok",
    "gn:population":0,
    "gn:timezone":"Africa/Nairobi",
    "iso:country":"KE",
    "wof:name":"Lorwok",
    "wof:placetype":"locality"
},
  "geometry": {"coordinates":[36.05,0.35],"type":"Point"}
}