{
  "type": "Feature",
  "properties": {
    "gn:admin1_code":"24.0",
    "gn:asciiname":"Njega",
    "gn:country_code":"KE",
    "gn:dem":1329,
    "gn:feature_class":"P",
    "gn:feature_code":"PPL",
    "gn:name":"Njega",
    "gn:population":0,
    "gn:timezone":"Africa/Nairobi",
    "iso:country":"KE",
    "name:und_x_variant":[
        "Boma",
        "Njegas",
        "Njega"
    ],
    "wof:name":"Njega",
    "wof:placetype":"locality"
},
  "geometry": {"coordinates":[37.28333,-0.56667],"type":"Point"}
}