{
  "type": "Feature",
  "properties": {
    "gn:admin1_code":"38.0",
    "gn:asciiname":"Geitwa",
    "gn:country_code":"KE",
    "gn:dem":1487,
    "gn:feature_class":"P",
    "gn:feature_code":"PPL",
    "gn:name":"Geitwa",
    "gn:population":0,
    "gn:timezone":"Africa/Nairobi",
    "iso:country":"KE",
    "wof:name":"Geitwa",
    "wof:placetype":"locality"
},
  "geometry": {"coordinates":[37.08047,-0.62711],"type":"Point"}
}