{
  "type": "Feature",
  "properties": {
    "gn:admin1_code":"28",
    "gn:asciiname":"Kilimangodo",
    "gn:country_code":"KE",
    "gn:dem":178,
    "gn:feature_class":"P",
    "gn:feature_code":"PPL",
    "gn:name":"Kilimangodo",
    "gn:population":0,
    "gn:timezone":"Africa/Nairobi",
    "iso:country":"KE",
    "wof:name":"Kilimangodo",
    "wof:placetype":"locality"
},
  "geometry": {"coordinates":[39.07575,-4.36299],"type":"Point"}
}