{
  "type": "Feature",
  "properties": {
    "gn:admin1_code":"41.0",
    "gn:asciiname":"Iminuet",
    "gn:country_code":"KE",
    "gn:dem":1902,
    "gn:feature_class":"P",
    "gn:feature_code":"PPL",
    "gn:name":"Iminuet",
    "gn:population":0,
    "gn:timezone":"Africa/Nairobi",
    "iso:country":"KE",
    "wof:name":"Iminuet",
    "wof:placetype":"locality"
},
  "geometry": {"coordinates":[35.48333,-0.85],"type":"Point"}
}