{
  "type": "Feature",
  "properties": {
    "gn:admin1_code":"41",
    "gn:asciiname":"Aitong",
    "gn:country_code":"KE",
    "gn:dem":1853,
    "gn:feature_class":"P",
    "gn:feature_code":"PPL",
    "gn:name":"Aitong",
    "gn:population":0,
    "gn:timezone":"Africa/Nairobi",
    "iso:country":"KE",
    "wof:name":"Aitong",
    "wof:placetype":"locality"
},
  "geometry": {"coordinates":[35.25,-1.18333],"type":"Point"}
}