{
  "type": "Feature",
  "properties": {
    "gn:admin1_code":"46.0",
    "gn:asciiname":"Rangala",
    "gn:country_code":"KE",
    "gn:dem":1252,
    "gn:feature_class":"P",
    "gn:feature_code":"PPL",
    "gn:name":"Rangala",
    "gn:population":0,
    "gn:timezone":"Africa/Nairobi",
    "iso:country":"KE",
    "name:und_x_variant":[
        "Toweri",
        "Tower",
        "Rangala"
    ],
    "wof:name":"Rangala",
    "wof:placetype":"locality"
},
  "geometry": {"coordinates":[34.33187,0.15036],"type":"Point"}
}