{
  "type": "Feature",
  "properties": {
    "gn:admin1_code":"40.0",
    "gn:asciiname":"Kaiboi",
    "gn:country_code":"KE",
    "gn:dem":1989,
    "gn:feature_class":"P",
    "gn:feature_code":"PPL",
    "gn:name":"Kaiboi",
    "gn:population":0,
    "gn:timezone":"Africa/Nairobi",
    "iso:country":"KE",
    "wof:name":"Kaiboi",
    "wof:placetype":"locality"
},
  "geometry": {"coordinates":[35.01981,0.41344],"type":"Point"}
}