{
  "type": "Feature",
  "properties": {
    "gn:admin1_code":"28",
    "gn:asciiname":"Jorore",
    "gn:country_code":"KE",
    "gn:dem":120,
    "gn:feature_class":"P",
    "gn:feature_code":"PPL",
    "gn:name":"Jorore",
    "gn:population":0,
    "gn:timezone":"Africa/Nairobi",
    "iso:country":"KE",
    "wof:name":"Jorore",
    "wof:placetype":"locality"
},
  "geometry": {"coordinates":[39.46121,-4.31077],"type":"Point"}
}