{
  "type": "Feature",
  "properties": {
    "gn:admin1_code":"32.0",
    "gn:asciiname":"Uvete",
    "gn:country_code":"KE",
    "gn:dem":1492,
    "gn:feature_class":"P",
    "gn:feature_code":"PPL",
    "gn:name":"Uvete",
    "gn:population":0,
    "gn:timezone":"Africa/Nairobi",
    "iso:country":"KE",
    "name:und_x_variant":[
        "Upete"
    ],
    "wof:name":"Uvete",
    "wof:placetype":"locality"
},
  "geometry": {"coordinates":[37.35095,-1.85422],"type":"Point"}
}