{
  "type": "Feature",
  "properties": {
    "gn:admin1_code":"13",
    "gn:asciiname":"Butula",
    "gn:country_code":"KE",
    "gn:dem":1323,
    "gn:feature_class":"P",
    "gn:feature_code":"PPL",
    "gn:name":"Butula",
    "gn:population":0,
    "gn:timezone":"Africa/Nairobi",
    "iso:country":"KE",
    "wof:name":"Butula",
    "wof:placetype":"locality"
},
  "geometry": {"coordinates":[34.33597,0.34195],"type":"Point"}
}