{
  "type": "Feature",
  "properties": {
    "gn:admin1_code":"40",
    "gn:asciiname":"Arwos",
    "gn:country_code":"KE",
    "gn:dem":1985,
    "gn:feature_class":"P",
    "gn:feature_code":"PPL",
    "gn:name":"Arwos",
    "gn:population":0,
    "gn:timezone":"Africa/Nairobi",
    "iso:country":"KE",
    "wof:name":"Arwos",
    "wof:placetype":"locality"
},
  "geometry": {"coordinates":[35.22778,0.20522],"type":"Point"}
}