{
  "type": "Feature",
  "properties": {
    "gn:admin1_code":"40.0",
    "gn:asciiname":"Kabiyet",
    "gn:country_code":"KE",
    "gn:dem":1984,
    "gn:feature_class":"P",
    "gn:feature_code":"PPL",
    "gn:name":"Kabiyet",
    "gn:population":0,
    "gn:timezone":"Africa/Nairobi",
    "iso:country":"KE",
    "name:und_x_variant":[
        "Kapivet",
        "Kapiyet",
        "Kabiyet"
    ],
    "wof:name":"Kabiyet",
    "wof:placetype":"locality"
},
  "geometry": {"coordinates":[35.08605,0.40453],"type":"Point"}
}