{
  "type": "Feature",
  "properties": {
    "iso:country":"KE",
    "name:eng_x_preferred":[
        "Mwatate"
    ],
    "name:jpn_x_preferred":[
        "\u30e0\u30ef\u30bf\u30c6"
    ],
    "name:nld_x_preferred":[
        "Mwatate"
    ],
    "name:swa_x_preferred":[
        "Mwatate"
    ],
    "name:zho_x_preferred":[
        "\u59c6\u74e6\u5854\u6cf0"
    ],
    "qs:gn_country":"KE",
    "qs:gn_fcode":"PPL",
    "qs:gn_pop":0,
    "qs:name":"Mwatate",
    "qs:name_adm0":"Kenya",
    "qs:name_adm1":"Coast",
    "qs:photos":0,
    "qs:photos_1k":0,
    "qs:photos_9k":1,
    "qs:photos_9r":1,
    "qs:photos_all":1,
    "qs:photos_sr":0,
    "qs:placetype":"Town",
    "qs:pop_sr":"4",
    "qs:woe_adm0":23424863,
    "wd:wordcount":250,
    "wof:name":"Mwatate",
    "wof:placetype":"locality"
},
  "geometry": {"coordinates":[38.37624,-3.49947],"type":"Point"}
}