{
  "type": "Feature",
  "properties": {
    "gn:admin1_code":"24.0",
    "gn:asciiname":"Kimbimbi",
    "gn:country_code":"KE",
    "gn:dem":1221,
    "gn:feature_class":"P",
    "gn:feature_code":"PPL",
    "gn:name":"Kimbimbi",
    "gn:population":0,
    "gn:timezone":"Africa/Nairobi",
    "iso:country":"KE",
    "wof:name":"Kimbimbi",
    "wof:placetype":"locality"
},
  "geometry": {"coordinates":[37.36482,-0.62233],"type":"Point"}
}