{
  "type": "Feature",
  "properties": {
    "gn:admin1_code":"28.0",
    "gn:asciiname":"Kidomaya",
    "gn:country_code":"KE",
    "gn:dem":37,
    "gn:feature_class":"P",
    "gn:feature_code":"PPL",
    "gn:name":"Kidomaya",
    "gn:population":0,
    "gn:timezone":"Africa/Nairobi",
    "iso:country":"KE",
    "wof:name":"Kidomaya",
    "wof:placetype":"locality"
},
  "geometry": {"coordinates":[39.1719,-4.56888],"type":"Point"}
}