{
  "type": "Feature",
  "properties": {
    "gn:admin1_code":"38.0",
    "gn:asciiname":"Mukungai",
    "gn:country_code":"KE",
    "gn:dem":1372,
    "gn:feature_class":"P",
    "gn:feature_code":"PPL",
    "gn:name":"Mukungai",
    "gn:population":0,
    "gn:timezone":"Africa/Nairobi",
    "iso:country":"KE",
    "wof:name":"Mukungai",
    "wof:placetype":"locality"
},
  "geometry": {"coordinates":[37.11667,-0.71667],"type":"Point"}
}