{
  "type": "Feature",
  "properties": {
    "gn:admin1_code":"30.0",
    "gn:asciiname":"Pangani",
    "gn:country_code":"KE",
    "gn:dem":13,
    "gn:feature_class":"P",
    "gn:feature_code":"PPL",
    "gn:name":"Pangani",
    "gn:population":0,
    "gn:timezone":"Africa/Nairobi",
    "iso:country":"KE",
    "name:ceb_x_preferred":[
        "Pangani"
    ],
    "name:dan_x_preferred":[
        "Pangani"
    ],
    "name:deu_x_preferred":[
        "Pangani"
    ],
    "name:fin_x_preferred":[
        "Pangani"
    ],
    "name:fra_x_preferred":[
        "Pangani"
    ],
    "name:nld_x_preferred":[
        "Pangani"
    ],
    "name:ron_x_preferred":[
        "Pangani"
    ],
    "name:rus_x_preferred":[
        "\u041f\u0430\u043d\u0433\u0430\u043d\u0438"
    ],
    "name:swa_x_preferred":[
        "Pangani"
    ],
    "name:swe_x_preferred":[
        "Pangani"
    ],
    "name:tur_x_preferred":[
        "Pangani"
    ],
    "name:urd_x_preferred":[
        "\u067e\u0627\u0646\u06af\u0627\u0646\u06cc"
    ],
    "name:zho_x_preferred":[
        "\u6f58\u52a0\u5c3c"
    ],
    "wof:name":"Pangani",
    "wof:placetype":"locality"
},
  "geometry": {"coordinates":[40.55931,-2.36044],"type":"Point"}
}