{
  "type": "Feature",
  "properties": {
    "gn:admin1_code":"30.0",
    "gn:asciiname":"Pangani",
    "gn:country_code":"KE",
    "gn:dem":13,
    "gn:feature_class":"P",
    "gn:feature_code":"PPL",
    "gn:name":"Pangani",
    "gn:population":0,
    "gn:timezone":"Africa/Nairobi",
    "iso:country":"KE",
    "wof:name":"Pangani",
    "wof:placetype":"locality"
},
  "geometry": {"coordinates":[40.55931,-2.36044],"type":"Point"}
}