{
  "type": "Feature",
  "properties": {
    "gn:admin1_code":"23.0",
    "gn:asciiname":"Kidutani",
    "gn:country_code":"KE",
    "gn:dem":149,
    "gn:feature_class":"P",
    "gn:feature_code":"PPL",
    "gn:name":"Kidutani",
    "gn:population":0,
    "gn:timezone":"Africa/Nairobi",
    "iso:country":"KE",
    "name:und_x_variant":[
        "Chidutani",
        "Kiduluni",
        "Kidutani"
    ],
    "wof:name":"Kidutani",
    "wof:placetype":"locality"
},
  "geometry": {"coordinates":[39.71667,-3.76667],"type":"Point"}
}