{
  "type": "Feature",
  "properties": {
    "gn:admin1_code":"44.0",
    "gn:asciiname":"Kairuthi",
    "gn:country_code":"KE",
    "gn:dem":2042,
    "gn:feature_class":"P",
    "gn:feature_code":"PPL",
    "gn:name":"Kairuthi",
    "gn:population":0,
    "gn:timezone":"Africa/Nairobi",
    "iso:country":"KE",
    "wof:name":"Kairuthi",
    "wof:placetype":"locality"
},
  "geometry": {"coordinates":[36.88768,-0.53323],"type":"Point"}
}