{
  "type": "Feature",
  "properties": {
    "gn:admin1_code":"34",
    "gn:asciiname":"Gatab",
    "gn:country_code":"KE",
    "gn:dem":1687,
    "gn:feature_class":"P",
    "gn:feature_code":"PPL",
    "gn:name":"Gatab",
    "gn:population":0,
    "gn:timezone":"Africa/Nairobi",
    "iso:country":"KE",
    "name:eng_x_preferred":[
        "Gatab"
    ],
    "wof:name":"Gatab",
    "wof:placetype":"locality"
},
  "geometry": {"coordinates":[36.92992,2.6426],"type":"Point"}
}