{
  "type": "Feature",
  "properties": {
    "gn:admin1_code":"17",
    "gn:asciiname":"Omboga",
    "gn:country_code":"KE",
    "gn:dem":1222,
    "gn:feature_class":"P",
    "gn:feature_code":"PPL",
    "gn:name":"Omboga",
    "gn:population":0,
    "gn:timezone":"Africa/Nairobi",
    "iso:country":"KE",
    "wof:name":"Omboga",
    "wof:placetype":"locality"
},
  "geometry": {"coordinates":[34.62236,-0.43436],"type":"Point"}
}