{
  "type": "Feature",
  "properties": {
    "gn:admin1_code":"16",
    "gn:asciiname":"Alinjur",
    "gn:country_code":"KE",
    "gn:dem":122,
    "gn:feature_class":"P",
    "gn:feature_code":"PPL",
    "gn:name":"Alinjur",
    "gn:population":0,
    "gn:timezone":"Africa/Nairobi",
    "iso:country":"KE",
    "wof:name":"Alinjur",
    "wof:placetype":"locality"
},
  "geometry": {"coordinates":[40.4563,-0.03113],"type":"Point"}
}