{
  "type": "Feature",
  "properties": {
    "iso:country":"KE",
    "name:eng_x_preferred":[
        "Karungu"
    ],
    "name:nld_x_preferred":[
        "Karungu"
    ],
    "ne:ADM0CAP":0.0,
    "ne:ADM0NAME":"Kenya",
    "ne:ADM0_A3":"KEN",
    "ne:ADM1NAME":"Nyanza",
    "ne:ADMIN1_COD":0,
    "ne:CAPALT":0,
    "ne:CHANGED":0,
    "ne:CHECKME":0,
    "ne:COMPARE":0,
    "ne:DIFFASCII":0,
    "ne:ELEVATION":0.0,
    "ne:FEATURECLA":"Populated place",
    "ne:GEONAMEID":-1,
    "ne:GEONAMESNO":"No GeoNames match due to small population, not in GeoNames, or poor NEV placement.",
    "ne:GN_POP":0,
    "ne:GTOPO30":0.0,
    "ne:ISO_A2":"KE",
    "ne:LABELRANK":5,
    "ne:LATITUDE":-0.849626,
    "ne:LONGITUDE":34.149998,
    "ne:LS_MATCH":1,
    "ne:LS_NAME":"Karungu",
    "ne:MAX_AREAKM":1.0,
    "ne:MAX_AREAMI":0.0,
    "ne:MAX_BBXMAX":34.158333,
    "ne:MAX_BBXMIN":34.15,
    "ne:MAX_BBYMAX":-0.841667,
    "ne:MAX_BBYMIN":-0.85,
    "ne:MAX_NATSCA":20.0,
    "ne:MAX_PERKM":4.0,
    "ne:MAX_PERMI":2.0,
    "ne:MAX_POP10":2376,
    "ne:MAX_POP20":2376,
    "ne:MAX_POP300":0,
    "ne:MAX_POP310":0,
    "ne:MAX_POP50":0,
    "ne:MEAN_BBXC":34.154167,
    "ne:MEAN_BBYC":-0.845833,
    "ne:MEGACITY":0,
    "ne:MIN_AREAKM":1.0,
    "ne:MIN_AREAMI":0.0,
    "ne:MIN_BBXMAX":34.158333,
    "ne:MIN_BBXMIN":34.15,
    "ne:MIN_BBYMAX":-0.841667,
    "ne:MIN_BBYMIN":-0.85,
    "ne:MIN_PERKM":4.0,
    "ne:MIN_PERMI":2.0,
    "ne:NAME":"Karungu",
    "ne:NAMEASCII":"Karungu",
    "ne:NAMEDIFF":0,
    "ne:NATSCALE":20,
    "ne:POP1950":0,
    "ne:POP1955":0,
    "ne:POP1960":0,
    "ne:POP1965":0,
    "ne:POP1970":0,
    "ne:POP1975":0,
    "ne:POP1980":0,
    "ne:POP1985":0,
    "ne:POP1990":0,
    "ne:POP1995":0,
    "ne:POP2000":0,
    "ne:POP2005":0,
    "ne:POP2010":0,
    "ne:POP2015":0,
    "ne:POP2020":0,
    "ne:POP2025":0,
    "ne:POP2050":0,
    "ne:POP_MAX":2376,
    "ne:POP_MIN":2376,
    "ne:POP_OTHER":0,
    "ne:RANK_MAX":4,
    "ne:RANK_MIN":4,
    "ne:SCALERANK":7,
    "ne:SOV0NAME":"Kenya",
    "ne:SOV_A3":"KEN",
    "ne:UN_FID":0,
    "ne:UN_LAT":0.0,
    "ne:UN_LONG":0.0,
    "ne:WORLDCITY":0,
    "ne:min_zoom":6.7,
    "wof:name":"Karungu",
    "wof:placetype":"locality"
},
  "geometry": {"coordinates":[34.14999792352671,-0.84962644562495],"type":"Point"}
}