{
  "type": "Feature",
  "properties": {
    "iso:country":"KE",
    "name:ara_x_preferred":[
        "\u062e\u0644\u064a\u062c \u0643\u0646\u062f\u0648"
    ],
    "name:ceb_x_preferred":[
        "Kendu Bay"
    ],
    "name:eng_x_preferred":[
        "Kendu Bay"
    ],
    "name:fra_x_preferred":[
        "Kendu Bay"
    ],
    "name:nld_x_preferred":[
        "Kendu Bay"
    ],
    "name:pol_x_preferred":[
        "Kendu Bay"
    ],
    "name:por_x_preferred":[
        "Kendu Bay"
    ],
    "name:swa_x_preferred":[
        "Kendu Bay"
    ],
    "name:swe_x_preferred":[
        "Kendu Bay"
    ],
    "name:unk_x_variant":[
        "Kendu"
    ],
    "ne:ADM0CAP":0.0,
    "ne:ADM0NAME":"Kenya",
    "ne:ADM0_A3":"KEN",
    "ne:ADM1NAME":"Nyanza",
    "ne:ADMIN1_COD":0,
    "ne:CAPALT":0,
    "ne:CHANGED":0,
    "ne:CHECKME":0,
    "ne:COMPARE":0,
    "ne:DIFFASCII":0,
    "ne:ELEVATION":0.0,
    "ne:FEATURECLA":"Populated place",
    "ne:GEONAMEID":-1,
    "ne:GEONAMESNO":"No GeoNames match due to small population, not in GeoNames, or poor NEV placement.",
    "ne:GN_POP":0,
    "ne:GTOPO30":0.0,
    "ne:ISO_A2":"KE",
    "ne:LABELRANK":5,
    "ne:LATITUDE":-0.359579,
    "ne:LONGITUDE":34.639994,
    "ne:LS_MATCH":1,
    "ne:LS_NAME":"Kendu Bay",
    "ne:MAX_AREAKM":91.0,
    "ne:MAX_AREAMI":35.0,
    "ne:MAX_BBXMAX":34.825,
    "ne:MAX_BBXMIN":34.608333,
    "ne:MAX_BBYMAX":-0.35,
    "ne:MAX_BBYMIN":-0.441667,
    "ne:MAX_NATSCA":20.0,
    "ne:MAX_PERKM":120.0,
    "ne:MAX_PERMI":75.0,
    "ne:MAX_POP10":91248,
    "ne:MAX_POP20":91248,
    "ne:MAX_POP300":0,
    "ne:MAX_POP310":0,
    "ne:MAX_POP50":0,
    "ne:MEAN_BBXC":34.717017,
    "ne:MEAN_BBYC":-0.39778,
    "ne:MEGACITY":0,
    "ne:MIN_AREAKM":91.0,
    "ne:MIN_AREAMI":35.0,
    "ne:MIN_BBXMAX":34.825,
    "ne:MIN_BBXMIN":34.608333,
    "ne:MIN_BBYMAX":-0.35,
    "ne:MIN_BBYMIN":-0.441667,
    "ne:MIN_PERKM":120.0,
    "ne:MIN_PERMI":75.0,
    "ne:NAME":"Kendu Bay",
    "ne:NAMEASCII":"Kendu Bay",
    "ne:NAMEDIFF":0,
    "ne:NATSCALE":20,
    "ne:POP1950":0,
    "ne:POP1955":0,
    "ne:POP1960":0,
    "ne:POP1965":0,
    "ne:POP1970":0,
    "ne:POP1975":0,
    "ne:POP1980":0,
    "ne:POP1985":0,
    "ne:POP1990":0,
    "ne:POP1995":0,
    "ne:POP2000":0,
    "ne:POP2005":0,
    "ne:POP2010":0,
    "ne:POP2015":0,
    "ne:POP2020":0,
    "ne:POP2025":0,
    "ne:POP2050":0,
    "ne:POP_MAX":91248,
    "ne:POP_MIN":91248,
    "ne:POP_OTHER":183346,
    "ne:RANK_MAX":8,
    "ne:RANK_MIN":8,
    "ne:SCALERANK":7,
    "ne:SOV0NAME":"Kenya",
    "ne:SOV_A3":"KEN",
    "ne:UN_FID":0,
    "ne:UN_LAT":0.0,
    "ne:UN_LONG":0.0,
    "ne:WORLDCITY":0,
    "ne:min_zoom":6.7,
    "wof:name":"Kendu Bay",
    "wof:placetype":"locality",
    "wof:population":434
},
  "geometry": {"coordinates":[34.6399938545182,-0.35957883820117],"type":"Point"}
}