{
  "type": "Feature",
  "properties": {
    "gn:admin1_code":"15.0",
    "gn:asciiname":"Karingare",
    "gn:country_code":"KE",
    "gn:dem":1546,
    "gn:feature_class":"P",
    "gn:feature_code":"PPL",
    "gn:name":"Karingare",
    "gn:population":0,
    "gn:timezone":"Africa/Nairobi",
    "iso:country":"KE",
    "name:und_x_variant":[
        "Karingari",
        "Karingare"
    ],
    "wof:name":"Karingare",
    "wof:placetype":"locality"
},
  "geometry": {"coordinates":[37.50635,-0.4713],"type":"Point"}
}