{
  "type": "Feature",
  "properties": {
    "gn:admin1_code":"38",
    "gn:asciiname":"Chomo",
    "gn:country_code":"KE",
    "gn:dem":1848,
    "gn:feature_class":"P",
    "gn:feature_code":"PPL",
    "gn:name":"Chomo",
    "gn:population":0,
    "gn:timezone":"Africa/Nairobi",
    "iso:country":"KE",
    "wof:name":"Chomo",
    "wof:placetype":"locality"
},
  "geometry": {"coordinates":[36.86544,-0.88518],"type":"Point"}
}