{
  "type": "Feature",
  "properties": {
    "gn:admin1_code":"23.0",
    "gn:asciiname":"Kijiwetanga",
    "gn:country_code":"KE",
    "gn:dem":34,
    "gn:feature_class":"P",
    "gn:feature_code":"PPL",
    "gn:name":"Kijiwetanga",
    "gn:population":0,
    "gn:timezone":"Africa/Nairobi",
    "iso:country":"KE",
    "wof:name":"Kijiwetanga",
    "wof:placetype":"locality"
},
  "geometry": {"coordinates":[40.08333,-3.25],"type":"Point"}
}