{
  "type": "Feature",
  "properties": {
    "gn:admin1_code":"24.0",
    "gn:asciiname":"Ndunduini",
    "gn:country_code":"KE",
    "gn:dem":1740,
    "gn:feature_class":"P",
    "gn:feature_code":"PPL",
    "gn:name":"Ndunduini",
    "gn:population":0,
    "gn:timezone":"Africa/Nairobi",
    "iso:country":"KE",
    "name:und_x_variant":[
        "Dondueni",
        "Ndundu-ini",
        "Ndunduini"
    ],
    "wof:name":"Ndunduini",
    "wof:placetype":"locality"
},
  "geometry": {"coordinates":[37.30848,-0.43829],"type":"Point"}
}