{
  "type": "Feature",
  "properties": {
    "gn:admin1_code":"28.0",
    "gn:asciiname":"Mwaembe",
    "gn:country_code":"KE",
    "gn:dem":25,
    "gn:feature_class":"P",
    "gn:feature_code":"PPL",
    "gn:name":"Mwaembe",
    "gn:population":0,
    "gn:timezone":"Africa/Nairobi",
    "iso:country":"KE",
    "name:urd_x_preferred":[
        "\u0645\u0648\u0627\u06cc\u0645\u0628\u06d2"
    ],
    "wof:name":"Mwaembe",
    "wof:placetype":"locality"
},
  "geometry": {"coordinates":[39.46453,-4.49256],"type":"Point"}
}