{
  "type": "Feature",
  "properties": {
    "gn:admin1_code":"38.0",
    "gn:asciiname":"Wanjereri",
    "gn:country_code":"KE",
    "gn:dem":2155,
    "gn:feature_class":"P",
    "gn:feature_code":"PPL",
    "gn:name":"Wanjereri",
    "gn:population":0,
    "gn:timezone":"Africa/Nairobi",
    "iso:country":"KE",
    "wof:name":"Wanjereri",
    "wof:placetype":"locality"
},
  "geometry": {"coordinates":[36.85,-0.65],"type":"Point"}
}