{
  "type": "Feature",
  "properties": {
    "iso:country":"KE",
    "name:dut_x_preferred":[
        "Kiserian"
    ],
    "name:eng_x_preferred":[
        "Kiserian"
    ],
    "name:jpn_x_preferred":[
        "\u30ad\u30bb\u30ea\u30a2\u30f3"
    ],
    "name:unk_x_variant":[
        "Kisserian"
    ],
    "qs:gn_country":"KE",
    "qs:gn_fcode":"PPL",
    "qs:gn_pop":0,
    "qs:name":"Kiserian",
    "qs:name_adm0":"Kenya",
    "qs:name_adm1":"Rift Valley",
    "qs:photos":0,
    "qs:photos_1k":0,
    "qs:photos_9k":1,
    "qs:photos_9r":1,
    "qs:photos_all":1,
    "qs:photos_sr":0,
    "qs:placetype":"Town",
    "qs:pop_sr":"0",
    "qs:woe_adm0":23424863,
    "wd:wordcount":212,
    "wof:name":"Kiserian",
    "wof:placetype":"locality"
},
  "geometry": {"coordinates":[36.68873,-1.42122],"type":"Point"}
}