{
  "type": "Feature",
  "properties": {
    "gn:admin1_code":"28.0",
    "gn:asciiname":"Mwandoni",
    "gn:country_code":"KE",
    "gn:dem":207,
    "gn:feature_class":"P",
    "gn:feature_code":"PPL",
    "gn:name":"Mwandoni",
    "gn:population":0,
    "gn:timezone":"Africa/Nairobi",
    "iso:country":"KE",
    "name:urd_x_preferred":[
        "\u0645\u0648\u0627\u0646\u0688\u0648\u0646\u06cc"
    ],
    "wof:name":"Mwandoni",
    "wof:placetype":"locality"
},
  "geometry": {"coordinates":[39.29445,-3.86279],"type":"Point"}
}