{
  "type": "Feature",
  "properties": {
    "gn:admin1_code":"32.0",
    "gn:asciiname":"Kikumini",
    "gn:country_code":"KE",
    "gn:dem":1201,
    "gn:feature_class":"P",
    "gn:feature_code":"PPL",
    "gn:name":"Kikumini",
    "gn:population":0,
    "gn:timezone":"Africa/Nairobi",
    "iso:country":"KE",
    "wof:name":"Kikumini",
    "wof:placetype":"locality"
},
  "geometry": {"coordinates":[37.57621,-2.04617],"type":"Point"}
}