{
  "type": "Feature",
  "properties": {
    "gn:admin1_code":"43.0",
    "gn:asciiname":"Upper Gilgil",
    "gn:country_code":"KE",
    "gn:dem":2661,
    "gn:feature_class":"P",
    "gn:feature_code":"PPL",
    "gn:name":"Upper Gilgil",
    "gn:population":0,
    "gn:timezone":"Africa/Nairobi",
    "iso:country":"KE",
    "name:ceb_x_preferred":[
        "Gilgil"
    ],
    "name:ces_x_preferred":[
        "Gilgil"
    ],
    "name:nor_x_preferred":[
        "Gilgil"
    ],
    "name:pol_x_preferred":[
        "Gilgil"
    ],
    "name:rus_x_preferred":[
        "\u0413\u0438\u043b\u0433\u0438\u043b"
    ],
    "name:swa_x_preferred":[
        "Gilgil"
    ],
    "name:swe_x_preferred":[
        "Gilgil"
    ],
    "name:und_x_variant":[
        "Khirgil",
        "Gilgil"
    ],
    "wof:name":"Upper Gilgil",
    "wof:placetype":"locality"
},
  "geometry": {"coordinates":[36.27248,-0.21209],"type":"Point"}
}