{
  "type": "Feature",
  "properties": {
    "gn:admin1_code":"19.0",
    "gn:asciiname":"Lorngosua",
    "gn:country_code":"KE",
    "gn:dem":1529,
    "gn:feature_class":"P",
    "gn:feature_code":"PPL",
    "gn:name":"Lorngosua",
    "gn:population":0,
    "gn:timezone":"Africa/Nairobi",
    "iso:country":"KE",
    "name:und_x_variant":[
        "Lolnguswa"
    ],
    "wof:name":"Lorngosua",
    "wof:placetype":"locality"
},
  "geometry": {"coordinates":[36.65172000000001,-2.14492],"type":"Point"}
}