{
  "type": "Feature",
  "properties": {
    "gn:admin1_code":"28",
    "gn:asciiname":"Kichakasimba",
    "gn:country_code":"KE",
    "gn:dem":146,
    "gn:feature_class":"P",
    "gn:feature_code":"PPL",
    "gn:name":"Kichakasimba",
    "gn:population":0,
    "gn:timezone":"Africa/Nairobi",
    "iso:country":"KE",
    "wof:name":"Kichakasimba",
    "wof:placetype":"locality"
},
  "geometry": {"coordinates":[39.35914,-4.34908],"type":"Point"}
}