{
  "type": "Feature",
  "properties": {
    "gn:admin1_code":"34",
    "gn:asciiname":"Songa",
    "gn:country_code":"KE",
    "gn:dem":992,
    "gn:feature_class":"P",
    "gn:feature_code":"PPLL",
    "gn:name":"Songa",
    "gn:population":0,
    "gn:timezone":"Africa/Nairobi",
    "iso:country":"KE",
    "wof:name":"Songa",
    "wof:placetype":"locality"
},
  "geometry": {"coordinates":[38.0104,2.23937],"type":"Point"}
}