{
  "type": "Feature",
  "properties": {
    "iso:country":"KE",
    "name:cat_x_preferred":[
        "Namanga"
    ],
    "name:kat_x_preferred":[
        "\u10dc\u10d0\u10db\u10d0\u10dc\u10d2\u10d0"
    ],
    "name:pol_x_preferred":[
        "Namanga"
    ],
    "name:ron_x_preferred":[
        "Namanga"
    ],
    "name:swe_x_preferred":[
        "Namanga"
    ],
    "name:urd_x_preferred":[
        "\u0646\u0627\u0645\u0627\u0646\u06af\u0627"
    ],
    "name:zho_x_preferred":[
        "\u7d0d\u66fc\u52a0"
    ],
    "ne:ADM0CAP":0.0,
    "ne:ADM0NAME":"Kenya",
    "ne:ADM0_A3":"KEN",
    "ne:ADM1NAME":"Rift Valley",
    "ne:ADMIN1_COD":8,
    "ne:CAPALT":0,
    "ne:CHANGED":0,
    "ne:CHECKME":0,
    "ne:COMPARE":0,
    "ne:DIFFASCII":0,
    "ne:ELEVATION":0.0,
    "ne:FEATURECLA":"Populated place",
    "ne:FEATURE_CL":"P",
    "ne:FEATURE_CO":"PPL",
    "ne:GEONAMEID":184570,
    "ne:GEONAMESNO":"GeoNames match with ascii name + lat + long whole numbers.",
    "ne:GN_ASCII":"Namanga",
    "ne:GN_POP":13193,
    "ne:GTOPO30":1355.0,
    "ne:ISO_A2":"KE",
    "ne:LABELRANK":5,
    "ne:LATITUDE":-2.539601,
    "ne:LONGITUDE":36.800017,
    "ne:LS_MATCH":1,
    "ne:LS_NAME":"Namanga",
    "ne:MAX_AREAKM":2.0,
    "ne:MAX_AREAMI":1.0,
    "ne:MAX_BBXMAX":36.791667,
    "ne:MAX_BBXMIN":36.783333,
    "ne:MAX_BBYMAX":-2.541667,
    "ne:MAX_BBYMIN":-2.558333,
    "ne:MAX_NATSCA":20.0,
    "ne:MAX_PERKM":6.0,
    "ne:MAX_PERMI":3.0,
    "ne:MAX_POP10":2136,
    "ne:MAX_POP20":2136,
    "ne:MAX_POP300":0,
    "ne:MAX_POP310":0,
    "ne:MAX_POP50":0,
    "ne:MEAN_BBXC":36.7875,
    "ne:MEAN_BBYC":-2.55,
    "ne:MEGACITY":0,
    "ne:MIN_AREAKM":2.0,
    "ne:MIN_AREAMI":1.0,
    "ne:MIN_BBXMAX":36.791667,
    "ne:MIN_BBXMIN":36.783333,
    "ne:MIN_BBYMAX":-2.541667,
    "ne:MIN_BBYMIN":-2.558333,
    "ne:MIN_PERKM":6.0,
    "ne:MIN_PERMI":3.0,
    "ne:NAME":"Namanga",
    "ne:NAMEASCII":"Namanga",
    "ne:NAMEDIFF":0,
    "ne:NATSCALE":20,
    "ne:POP1950":0,
    "ne:POP1955":0,
    "ne:POP1960":0,
    "ne:POP1965":0,
    "ne:POP1970":0,
    "ne:POP1975":0,
    "ne:POP1980":0,
    "ne:POP1985":0,
    "ne:POP1990":0,
    "ne:POP1995":0,
    "ne:POP2000":0,
    "ne:POP2005":0,
    "ne:POP2010":0,
    "ne:POP2015":0,
    "ne:POP2020":0,
    "ne:POP2025":0,
    "ne:POP2050":0,
    "ne:POP_MAX":13193,
    "ne:POP_MIN":2136,
    "ne:POP_OTHER":0,
    "ne:RANK_MAX":6,
    "ne:RANK_MIN":4,
    "ne:SCALERANK":7,
    "ne:SOV0NAME":"Kenya",
    "ne:SOV_A3":"KEN",
    "ne:TIMEZONE":"Africa/Nairobi",
    "ne:UN_FID":0,
    "ne:UN_LAT":0.0,
    "ne:UN_LONG":0.0,
    "ne:WORLDCITY":0,
    "qs:gn_country":"KE",
    "qs:gn_fcode":"PPL",
    "qs:gn_pop":13193,
    "qs:name":"Namanga",
    "qs:name_adm0":"Kenya",
    "qs:name_adm1":"Rift Valley",
    "qs:photos":150,
    "qs:photos_1k":30,
    "qs:photos_9k":1,
    "qs:photos_9r":3,
    "qs:photos_all":150,
    "qs:photos_sr":3,
    "qs:placetype":"Town",
    "qs:pop_sr":"6",
    "qs:woe_adm0":23424863,
    "wd:wordcount":360,
    "wof:name":"Namanga",
    "wof:placetype":"locality",
    "wof:population":13193
},
  "geometry": {"coordinates":[36.79053,-2.54327],"type":"Point"}
}