{
  "type": "Feature",
  "properties": {
    "gn:admin1_code":"48.0",
    "gn:asciiname":"Mbalambala",
    "gn:country_code":"KE",
    "gn:dem":202,
    "gn:feature_class":"P",
    "gn:feature_code":"PPL",
    "gn:name":"Mbalambala",
    "gn:population":0,
    "gn:timezone":"Africa/Nairobi",
    "iso:country":"KE",
    "name:und_x_variant":[
        "Bahadale",
        "Mbalambala"
    ],
    "wof:name":"Mbalambala",
    "wof:placetype":"locality"
},
  "geometry": {"coordinates":[39.06082,-0.04319],"type":"Point"}
}