{
  "type": "Feature",
  "properties": {
    "gn:admin1_code":"55",
    "gn:asciiname":"Cheburua",
    "gn:country_code":"KE",
    "gn:dem":1673,
    "gn:feature_class":"P",
    "gn:feature_code":"PPL",
    "gn:name":"Cheburua",
    "gn:population":0,
    "gn:timezone":"Africa/Nairobi",
    "iso:country":"KE",
    "name:und_x_variant":[
        "Chepurwa"
    ],
    "wof:name":"Cheburua",
    "wof:placetype":"locality"
},
  "geometry": {"coordinates":[35.20995,2.03221],"type":"Point"}
}