{
  "type": "Feature",
  "properties": {
    "gn:admin1_code":"38.0",
    "gn:asciiname":"Kahuro",
    "gn:country_code":"KE",
    "gn:dem":1640,
    "gn:feature_class":"P",
    "gn:feature_code":"PPL",
    "gn:name":"Kahuro",
    "gn:population":0,
    "gn:timezone":"Africa/Nairobi",
    "iso:country":"KE",
    "wof:name":"Kahuro",
    "wof:placetype":"locality"
},
  "geometry": {"coordinates":[37.00832,-0.74816],"type":"Point"}
}