{
  "type": "Feature",
  "properties": {
    "gn:admin1_code":"27.0",
    "gn:asciiname":"Randani",
    "gn:country_code":"KE",
    "gn:dem":451,
    "gn:feature_class":"P",
    "gn:feature_code":"PPL",
    "gn:name":"Randani",
    "gn:population":0,
    "gn:timezone":"Africa/Nairobi",
    "iso:country":"KE",
    "wof:name":"Randani",
    "wof:placetype":"locality"
},
  "geometry": {"coordinates":[38.56667,-1.66667],"type":"Point"}
}