{
  "type": "Feature",
  "properties": {
    "gn:admin1_code":"21.0",
    "gn:asciiname":"Kapsamonget",
    "gn:country_code":"KE",
    "gn:dem":1998,
    "gn:feature_class":"P",
    "gn:feature_code":"PPL",
    "gn:name":"Kapsamonget",
    "gn:population":0,
    "gn:timezone":"Africa/Nairobi",
    "iso:country":"KE",
    "wof:name":"Kapsamonget",
    "wof:placetype":"locality"
},
  "geometry": {"coordinates":[35.21667,-0.31667],"type":"Point"}
}