{
  "type": "Feature",
  "properties": {
    "gn:admin1_code":"23",
    "gn:asciiname":"Dindiri",
    "gn:country_code":"KE",
    "gn:dem":90,
    "gn:feature_class":"P",
    "gn:feature_code":"PPL",
    "gn:name":"Dindiri",
    "gn:population":0,
    "gn:timezone":"Africa/Nairobi",
    "iso:country":"KE",
    "wof:name":"Dindiri",
    "wof:placetype":"locality"
},
  "geometry": {"coordinates":[39.80094,-3.72748],"type":"Point"}
}