{
  "type": "Feature",
  "properties": {
    "gn:admin1_code":"47.0",
    "gn:asciiname":"Ndome",
    "gn:country_code":"KE",
    "gn:dem":940,
    "gn:feature_class":"P",
    "gn:feature_code":"PPL",
    "gn:name":"Ndome",
    "gn:population":0,
    "gn:timezone":"Africa/Nairobi",
    "iso:country":"KE",
    "wof:name":"Ndome",
    "wof:placetype":"locality"
},
  "geometry": {"coordinates":[38.47888,-3.30299],"type":"Point"}
}