{
  "type": "Feature",
  "properties": {
    "gn:admin1_code":"49",
    "gn:asciiname":"Marimanti",
    "gn:country_code":"KE",
    "gn:dem":580,
    "gn:feature_class":"P",
    "gn:feature_code":"PPL",
    "gn:name":"Marimanti",
    "gn:population":0,
    "gn:timezone":"Africa/Nairobi",
    "iso:country":"KE",
    "wof:name":"Marimanti",
    "wof:placetype":"locality"
},
  "geometry": {"coordinates":[37.97625,-0.15457],"type":"Point"}
}