{
  "type": "Feature",
  "properties": {
    "gn:admin1_code":"47.0",
    "gn:asciiname":"Ndile",
    "gn:country_code":"KE",
    "gn:dem":851,
    "gn:feature_class":"P",
    "gn:feature_code":"PPL",
    "gn:name":"Ndile",
    "gn:population":0,
    "gn:timezone":"Africa/Nairobi",
    "iso:country":"KE",
    "wof:name":"Ndile",
    "wof:placetype":"locality"
},
  "geometry": {"coordinates":[38.48405,-3.32008],"type":"Point"}
}