{
  "type": "Feature",
  "properties": {
    "gn:admin1_code":"28.0",
    "gn:asciiname":"Ngombeni",
    "gn:country_code":"KE",
    "gn:dem":28,
    "gn:feature_class":"P",
    "gn:feature_code":"PPL",
    "gn:name":"Ngombeni",
    "gn:population":0,
    "gn:timezone":"Africa/Nairobi",
    "iso:country":"KE",
    "name:und_x_variant":[
        "Ngomheni",
        "Ngombeni"
    ],
    "wof:name":"Ngombeni",
    "wof:placetype":"locality"
},
  "geometry": {"coordinates":[39.62844000000001,-4.12934],"type":"Point"}
}