{
  "type": "Feature",
  "properties": {
    "gn:admin1_code":"24.0",
    "gn:asciiname":"Mathangauta",
    "gn:country_code":"KE",
    "gn:dem":1182,
    "gn:feature_class":"P",
    "gn:feature_code":"PPL",
    "gn:name":"Mathangauta",
    "gn:population":0,
    "gn:timezone":"Africa/Nairobi",
    "iso:country":"KE",
    "name:und_x_variant":[
        "Mathaguta",
        "Mathangauta"
    ],
    "wof:name":"Mathangauta",
    "wof:placetype":"locality"
},
  "geometry": {"coordinates":[37.36667,-0.63333],"type":"Point"}
}