{
  "type": "Feature",
  "properties": {
    "gn:admin1_code":"47.0",
    "gn:asciiname":"Wongonyi",
    "gn:country_code":"KE",
    "gn:dem":1184,
    "gn:feature_class":"P",
    "gn:feature_code":"PPL",
    "gn:name":"Wongonyi",
    "gn:population":0,
    "gn:timezone":"Africa/Nairobi",
    "iso:country":"KE",
    "wof:name":"Wongonyi",
    "wof:placetype":"locality"
},
  "geometry": {"coordinates":[38.43355,-3.31637],"type":"Point"}
}