{
  "type": "Feature",
  "properties": {
    "gn:admin1_code":"46.0",
    "gn:asciiname":"Ndori",
    "gn:country_code":"KE",
    "gn:dem":1342,
    "gn:feature_class":"P",
    "gn:feature_code":"PPL",
    "gn:name":"Ndori",
    "gn:population":0,
    "gn:timezone":"Africa/Nairobi",
    "iso:country":"KE",
    "wof:name":"Ndori",
    "wof:placetype":"locality"
},
  "geometry": {"coordinates":[34.36329,-0.07892],"type":"Point"}
}