{
  "type": "Feature",
  "properties": {
    "gn:admin1_code":"35.0",
    "gn:asciiname":"Lare",
    "gn:country_code":"KE",
    "gn:dem":1836,
    "gn:feature_class":"P",
    "gn:feature_code":"PPL",
    "gn:name":"Lare",
    "gn:population":0,
    "gn:timezone":"Africa/Nairobi",
    "iso:country":"KE",
    "wof:name":"Lare",
    "wof:placetype":"locality"
},
  "geometry": {"coordinates":[37.93749,0.33727],"type":"Point"}
}