{
  "type": "Feature",
  "properties": {
    "gn:admin1_code":"10.0",
    "gn:asciiname":"Kapchepkor",
    "gn:country_code":"KE",
    "gn:dem":2182,
    "gn:feature_class":"P",
    "gn:feature_code":"PPL",
    "gn:name":"Kapchepkor",
    "gn:population":0,
    "gn:timezone":"Africa/Nairobi",
    "iso:country":"KE",
    "name:nld_x_preferred":[
        "Kapchepkor"
    ],
    "wof:name":"Kapchepkor",
    "wof:placetype":"locality"
},
  "geometry": {"coordinates":[35.81383,0.62511],"type":"Point"}
}