{
  "type": "Feature",
  "properties": {
    "gn:admin1_code":"44.0",
    "gn:asciiname":"Kamwenja",
    "gn:country_code":"KE",
    "gn:dem":1875,
    "gn:feature_class":"P",
    "gn:feature_code":"PPL",
    "gn:name":"Kamwenja",
    "gn:population":0,
    "gn:timezone":"Africa/Nairobi",
    "iso:country":"KE",
    "wof:name":"Kamwenja",
    "wof:placetype":"locality"
},
  "geometry": {"coordinates":[36.91617,-0.39738],"type":"Point"}
}