{
  "type": "Feature",
  "properties": {
    "gn:admin1_code":"38.0",
    "gn:asciiname":"Githumu",
    "gn:country_code":"KE",
    "gn:dem":1878,
    "gn:feature_class":"P",
    "gn:feature_code":"PPL",
    "gn:name":"Githumu",
    "gn:population":0,
    "gn:timezone":"Africa/Nairobi",
    "iso:country":"KE",
    "wof:name":"Githumu",
    "wof:placetype":"locality"
},
  "geometry": {"coordinates":[36.91592,-0.83035],"type":"Point"}
}