{
  "type": "Feature",
  "properties": {
    "gn:admin1_code":"22.0",
    "gn:asciiname":"Kiambaa",
    "gn:country_code":"KE",
    "gn:dem":2139,
    "gn:feature_class":"P",
    "gn:feature_code":"PPL",
    "gn:name":"Kiambaa",
    "gn:population":0,
    "gn:timezone":"Africa/Nairobi",
    "iso:country":"KE",
    "wof:name":"Kiambaa",
    "wof:placetype":"locality"
},
  "geometry": {"coordinates":[36.65659,-1.19929],"type":"Point"}
}