{
  "type": "Feature",
  "properties": {
    "gn:admin1_code":"30",
    "gn:asciiname":"Kilweni",
    "gn:country_code":"KE",
    "gn:dem":7,
    "gn:feature_class":"P",
    "gn:feature_code":"PPL",
    "gn:name":"Kilweni",
    "gn:population":0,
    "gn:timezone":"Africa/Nairobi",
    "iso:country":"KE",
    "wof:name":"Kilweni",
    "wof:placetype":"locality"
},
  "geometry": {"coordinates":[41.02496,-2.03258],"type":"Point"}
}