{
  "type": "Feature",
  "properties": {
    "gn:admin1_code":"16",
    "gn:asciiname":"Elaa",
    "gn:country_code":"KE",
    "gn:dem":82,
    "gn:feature_class":"P",
    "gn:feature_code":"PPL",
    "gn:name":"Elaa",
    "gn:population":0,
    "gn:timezone":"Africa/Nairobi",
    "iso:country":"KE",
    "name:und_x_variant":[
        "Ela",
        "Elaa"
    ],
    "wof:name":"Elaa",
    "wof:placetype":"locality"
},
  "geometry": {"coordinates":[40.78333,-1.16667],"type":"Point"}
}