{
  "type": "Feature",
  "properties": {
    "gn:admin1_code":"20",
    "gn:asciiname":"Malava Constituency",
    "gn:country_code":"KE",
    "gn:dem":1627,
    "gn:feature_class":"P",
    "gn:feature_code":"PPL",
    "gn:name":"Malava Constituency",
    "gn:population":0,
    "gn:timezone":"Africa/Nairobi",
    "iso:country":"KE",
    "wof:name":"Malava Constituency",
    "wof:placetype":"locality"
},
  "geometry": {"coordinates":[34.85007,0.44638],"type":"Point"}
}