{
  "type": "Feature",
  "properties": {
    "gn:admin1_code":"24.0",
    "gn:asciiname":"Kameichiri",
    "gn:country_code":"KE",
    "gn:dem":1193,
    "gn:feature_class":"P",
    "gn:feature_code":"PPL",
    "gn:name":"Kameichiri",
    "gn:population":0,
    "gn:timezone":"Africa/Nairobi",
    "iso:country":"KE",
    "wof:name":"Kameichiri",
    "wof:placetype":"locality"
},
  "geometry": {"coordinates":[37.30576,-0.65186],"type":"Point"}
}