{
  "type": "Feature",
  "properties": {
    "gn:admin1_code":"10.0",
    "gn:asciiname":"Kinyach",
    "gn:country_code":"KE",
    "gn:dem":1147,
    "gn:feature_class":"P",
    "gn:feature_code":"PPL",
    "gn:name":"Kinyach",
    "gn:population":0,
    "gn:timezone":"Africa/Nairobi",
    "iso:country":"KE",
    "wof:name":"Kinyach",
    "wof:placetype":"locality"
},
  "geometry": {"coordinates":[35.68843,0.92317],"type":"Point"}
}