{
  "type": "Feature",
  "properties": {
    "gn:admin1_code":"23.0",
    "gn:asciiname":"Luswani",
    "gn:country_code":"KE",
    "gn:dem":270,
    "gn:feature_class":"P",
    "gn:feature_code":"PPL",
    "gn:name":"Luswani",
    "gn:population":0,
    "gn:timezone":"Africa/Nairobi",
    "iso:country":"KE",
    "wof:name":"Luswani",
    "wof:placetype":"locality"
},
  "geometry": {"coordinates":[39.55,-3.46667],"type":"Point"}
}