{
  "type": "Feature",
  "properties": {
    "gn:admin1_code":"8.0",
    "gn:asciiname":"Sang'alo",
    "gn:country_code":"KE",
    "gn:dem":1986,
    "gn:feature_class":"P",
    "gn:feature_code":"PPL",
    "gn:name":"Sang\u2019alo",
    "gn:population":0,
    "gn:timezone":"Africa/Nairobi",
    "iso:country":"KE",
    "wof:name":"Sang'alo",
    "wof:placetype":"locality"
},
  "geometry": {"coordinates":[35.04991,0.35113],"type":"Point"}
}