{
  "type": "Feature",
  "properties": {
    "gn:admin1_code":"21.0",
    "gn:asciiname":"Kenegut",
    "gn:country_code":"KE",
    "gn:dem":1958,
    "gn:feature_class":"P",
    "gn:feature_code":"PPL",
    "gn:name":"Kenegut",
    "gn:population":0,
    "gn:timezone":"Africa/Nairobi",
    "iso:country":"KE",
    "wof:name":"Kenegut",
    "wof:placetype":"locality"
},
  "geometry": {"coordinates":[35.22417,-0.26903],"type":"Point"}
}