{
  "type": "Feature",
  "properties": {
    "gn:admin1_code":"22.0",
    "gn:asciiname":"Kiriri",
    "gn:country_code":"KE",
    "gn:dem":1972,
    "gn:feature_class":"P",
    "gn:feature_code":"PPL",
    "gn:name":"Kiriri",
    "gn:population":0,
    "gn:timezone":"Africa/Nairobi",
    "iso:country":"KE",
    "wof:name":"Kiriri",
    "wof:placetype":"locality"
},
  "geometry": {"coordinates":[36.57034,-1.20825],"type":"Point"}
}