{
  "type": "Feature",
  "properties": {
    "gn:admin1_code":"28",
    "gn:asciiname":"Diani Beach",
    "gn:country_code":"KE",
    "gn:dem":12,
    "gn:feature_class":"P",
    "gn:feature_code":"PPL",
    "gn:name":"Diani Beach",
    "gn:population":0,
    "gn:timezone":"Africa/Nairobi",
    "iso:country":"KE",
    "wof:name":"Diani Beach",
    "wof:placetype":"locality"
},
  "geometry": {"coordinates":[39.59413,-4.27774],"type":"Point"}
}