{
  "type": "Feature",
  "properties": {
    "gn:admin1_code":"05",
    "gn:asciiname":"Bomas of Kenya",
    "gn:country_code":"KE",
    "gn:dem":1785,
    "gn:feature_class":"P",
    "gn:feature_code":"PPL",
    "gn:name":"Bomas of Kenya",
    "gn:population":0,
    "gn:timezone":"Africa/Nairobi",
    "iso:country":"KE",
    "name:deu_x_preferred":[
        "Bomas of Kenya"
    ],
    "name:fra_x_preferred":[
        "Bomas of Kenya"
    ],
    "name:rus_x_preferred":[
        "\u0411\u043e\u043c\u0430\u0441"
    ],
    "name:swa_x_preferred":[
        "Bomas of Kenya"
    ],
    "name:ukr_x_preferred":[
        "\u0411\u043e\u043c\u0430\u0441"
    ],
    "wof:name":"Bomas of Kenya",
    "wof:placetype":"locality"
},
  "geometry": {"coordinates":[36.76998,-1.33675],"type":"Point"}
}