{
  "type": "Feature",
  "properties": {
    "gn:admin1_code":"38.0",
    "gn:asciiname":"Gatitu",
    "gn:country_code":"KE",
    "gn:dem":1552,
    "gn:feature_class":"P",
    "gn:feature_code":"PPL",
    "gn:name":"Gatitu",
    "gn:population":0,
    "gn:timezone":"Africa/Nairobi",
    "iso:country":"KE",
    "wof:name":"Gatitu",
    "wof:placetype":"locality"
},
  "geometry": {"coordinates":[37.04366,-0.90685],"type":"Point"}
}