{
  "type": "Feature",
  "properties": {
    "gn:admin1_code":"18.0",
    "gn:asciiname":"Sericho",
    "gn:country_code":"KE",
    "gn:dem":236,
    "gn:feature_class":"P",
    "gn:feature_code":"PPL",
    "gn:name":"Sericho",
    "gn:population":0,
    "gn:timezone":"Africa/Nairobi",
    "iso:country":"KE",
    "name:und_x_variant":[
        "Saricho",
        "Sericho"
    ],
    "wof:name":"Sericho",
    "wof:placetype":"locality"
},
  "geometry": {"coordinates":[39.08681,1.14495],"type":"Point"}
}