{
  "type": "Feature",
  "properties": {
    "iso:country":"KE",
    "name:eng_x_preferred":[
        "Makowe"
    ],
    "name:nld_x_preferred":[
        "Makowe"
    ],
    "qs:gn_country":"KE",
    "qs:gn_fcode":"PPL",
    "qs:gn_pop":0,
    "qs:name":"Mokowe",
    "qs:name_adm0":"Kenya",
    "qs:name_adm1":"Coast",
    "qs:photos":23,
    "qs:photos_1k":5,
    "qs:photos_9k":1,
    "qs:photos_9r":1,
    "qs:photos_all":23,
    "qs:photos_sr":1,
    "qs:placetype":"Town",
    "qs:pop_sr":"0",
    "qs:woe_adm0":23424863,
    "wd:wordcount":200,
    "wof:name":"Mokowe",
    "wof:placetype":"locality"
},
  "geometry": {"coordinates":[40.84656,-2.23428],"type":"Point"}
}