{
  "type": "Feature",
  "properties": {
    "gn:admin1_code":"38.0",
    "gn:asciiname":"Kariua",
    "gn:country_code":"KE",
    "gn:dem":1765,
    "gn:feature_class":"P",
    "gn:feature_code":"PPL",
    "gn:name":"Kariua",
    "gn:population":0,
    "gn:timezone":"Africa/Nairobi",
    "iso:country":"KE",
    "name:und_x_variant":[
        "Kariura",
        "Kariuwa",
        "Kariua"
    ],
    "wof:name":"Kariua",
    "wof:placetype":"locality"
},
  "geometry": {"coordinates":[36.96907,-0.84467],"type":"Point"}
}