{
  "type": "Feature",
  "properties": {
    "gn:admin1_code":"28",
    "gn:asciiname":"Kachini",
    "gn:country_code":"KE",
    "gn:dem":133,
    "gn:feature_class":"P",
    "gn:feature_code":"PPL",
    "gn:name":"Kachini",
    "gn:population":0,
    "gn:timezone":"Africa/Nairobi",
    "iso:country":"KE",
    "wof:name":"Kachini",
    "wof:placetype":"locality"
},
  "geometry": {"coordinates":[39.13395,-4.43448],"type":"Point"}
}