{
  "type": "Feature",
  "properties": {
    "gn:admin1_code":"23.0",
    "gn:asciiname":"Kabiboni",
    "gn:country_code":"KE",
    "gn:dem":113,
    "gn:feature_class":"P",
    "gn:feature_code":"PPL",
    "gn:name":"Kabiboni",
    "gn:population":0,
    "gn:timezone":"Africa/Nairobi",
    "iso:country":"KE",
    "wof:name":"Kabiboni",
    "wof:placetype":"locality"
},
  "geometry": {"coordinates":[40.00701,-3.00526],"type":"Point"}
}