{
  "type": "Feature",
  "properties": {
    "gn:admin1_code":"44.0",
    "gn:asciiname":"Kiangararu",
    "gn:country_code":"KE",
    "gn:dem":1752,
    "gn:feature_class":"P",
    "gn:feature_code":"PPL",
    "gn:name":"Kiangararu",
    "gn:population":0,
    "gn:timezone":"Africa/Nairobi",
    "iso:country":"KE",
    "wof:name":"Kiangararu",
    "wof:placetype":"locality"
},
  "geometry": {"coordinates":[37.13333,-0.48333],"type":"Point"}
}