{
  "type": "Feature",
  "properties": {
    "gn:admin1_code":"47.0",
    "gn:asciiname":"Ikanga",
    "gn:country_code":"KE",
    "gn:dem":775,
    "gn:feature_class":"P",
    "gn:feature_code":"PPL",
    "gn:name":"Ikanga",
    "gn:population":0,
    "gn:timezone":"Africa/Nairobi",
    "iso:country":"KE",
    "wof:name":"Ikanga",
    "wof:placetype":"locality"
},
  "geometry": {"coordinates":[38.51167,-3.36768],"type":"Point"}
}