{
  "type": "Feature",
  "properties": {
    "gn:admin1_code":"11",
    "gn:asciiname":"Chemaner",
    "gn:country_code":"KE",
    "gn:dem":2166,
    "gn:feature_class":"P",
    "gn:feature_code":"PPL",
    "gn:name":"Chemaner",
    "gn:population":0,
    "gn:timezone":"Africa/Nairobi",
    "iso:country":"KE",
    "wof:name":"Chemaner",
    "wof:placetype":"locality"
},
  "geometry": {"coordinates":[35.48598,-0.80375],"type":"Point"}
}