{
  "type": "Feature",
  "properties": {
    "gn:admin1_code":"44.0",
    "gn:asciiname":"Njege",
    "gn:country_code":"KE",
    "gn:dem":1662,
    "gn:feature_class":"P",
    "gn:feature_code":"PPL",
    "gn:name":"Njege",
    "gn:population":0,
    "gn:timezone":"Africa/Nairobi",
    "iso:country":"KE",
    "wof:name":"Njege",
    "wof:placetype":"locality"
},
  "geometry": {"coordinates":[37.06667,-0.56667],"type":"Point"}
}