{
  "type": "Feature",
  "properties": {
    "gn:admin1_code":"28.0",
    "gn:asciiname":"Kikoneni",
    "gn:country_code":"KE",
    "gn:dem":121,
    "gn:feature_class":"P",
    "gn:feature_code":"PPL",
    "gn:name":"Kikoneni",
    "gn:population":0,
    "gn:timezone":"Africa/Nairobi",
    "iso:country":"KE",
    "wof:name":"Kikoneni",
    "wof:placetype":"locality"
},
  "geometry": {"coordinates":[39.30998,-4.44766],"type":"Point"}
}