{
  "type": "Feature",
  "properties": {
    "gn:admin1_code":"22.0",
    "gn:asciiname":"Gikure",
    "gn:country_code":"KE",
    "gn:dem":1856,
    "gn:feature_class":"P",
    "gn:feature_code":"PPL",
    "gn:name":"Gikure",
    "gn:population":0,
    "gn:timezone":"Africa/Nairobi",
    "iso:country":"KE",
    "wof:name":"Gikure",
    "wof:placetype":"locality"
},
  "geometry": {"coordinates":[36.84419000000001,-0.96975],"type":"Point"}
}