{
  "type": "Feature",
  "properties": {
    "gn:admin1_code":"49.0",
    "gn:asciiname":"Weru",
    "gn:country_code":"KE",
    "gn:dem":1196,
    "gn:feature_class":"P",
    "gn:feature_code":"PPL",
    "gn:name":"Weru",
    "gn:population":0,
    "gn:timezone":"Africa/Nairobi",
    "iso:country":"KE",
    "wof:name":"Weru",
    "wof:placetype":"locality"
},
  "geometry": {"coordinates":[37.71942,-0.36718],"type":"Point"}
}