{
  "type": "Feature",
  "properties": {
    "gn:admin1_code":"47.0",
    "gn:asciiname":"Figini",
    "gn:country_code":"KE",
    "gn:dem":1114,
    "gn:feature_class":"P",
    "gn:feature_code":"PPL",
    "gn:name":"Figini",
    "gn:population":0,
    "gn:timezone":"Africa/Nairobi",
    "iso:country":"KE",
    "wof:name":"Figini",
    "wof:placetype":"locality"
},
  "geometry": {"coordinates":[38.38847,-3.37459],"type":"Point"}
}