{
  "type": "Feature",
  "properties": {
    "gn:admin1_code":"23.0",
    "gn:asciiname":"Kidutani",
    "gn:country_code":"KE",
    "gn:dem":21,
    "gn:feature_class":"P",
    "gn:feature_code":"PPL",
    "gn:name":"Kidutani",
    "gn:population":0,
    "gn:timezone":"Africa/Nairobi",
    "iso:country":"KE",
    "wof:name":"Kidutani",
    "wof:placetype":"locality"
},
  "geometry": {"coordinates":[39.71667,-3.88333],"type":"Point"}
}