{
  "type": "Feature",
  "properties": {
    "gn:admin1_code":"51",
    "gn:asciiname":"Lokiriama",
    "gn:country_code":"KE",
    "gn:dem":927,
    "gn:feature_class":"P",
    "gn:feature_code":"PPL",
    "gn:name":"Lokiriama",
    "gn:population":0,
    "gn:timezone":"Africa/Nairobi",
    "iso:country":"KE",
    "wof:name":"Lokiriama",
    "wof:placetype":"locality"
},
  "geometry": {"coordinates":[34.85042,2.725],"type":"Point"}
}