{
  "type": "Feature",
  "properties": {
    "gn:admin1_code":"28.0",
    "gn:asciiname":"Shambini",
    "gn:country_code":"KE",
    "gn:dem":235,
    "gn:feature_class":"P",
    "gn:feature_code":"PPL",
    "gn:name":"Shambini",
    "gn:population":0,
    "gn:timezone":"Africa/Nairobi",
    "iso:country":"KE",
    "wof:name":"Shambini",
    "wof:placetype":"locality"
},
  "geometry": {"coordinates":[39.17526,-4.04961],"type":"Point"}
}