{
  "type": "Feature",
  "properties": {
    "gn:admin1_code":"22.0",
    "gn:asciiname":"Uthiru",
    "gn:country_code":"KE",
    "gn:dem":1858,
    "gn:feature_class":"P",
    "gn:feature_code":"PPL",
    "gn:name":"Uthiru",
    "gn:population":0,
    "gn:timezone":"Africa/Nairobi",
    "iso:country":"KE",
    "wof:name":"Uthiru",
    "wof:placetype":"locality"
},
  "geometry": {"coordinates":[36.71233,-1.25392],"type":"Point"}
}