{
  "type": "Feature",
  "properties": {
    "iso:country":"KE",
    "name:ceb_x_preferred":[
        "Kapsabet"
    ],
    "name:dan_x_preferred":[
        "Kapsabet"
    ],
    "name:deu_x_preferred":[
        "Kapsabet"
    ],
    "name:eng_x_preferred":[
        "Kapsabet"
    ],
    "name:fas_x_preferred":[
        "\u06a9\u0627\u067e\u0633\u0627\u0628\u062a"
    ],
    "name:fra_x_preferred":[
        "Kapsabet"
    ],
    "name:heb_x_preferred":[
        "\u05e7\u05e4\u05e1\u05d0\u05d1\u05d8"
    ],
    "name:ita_x_preferred":[
        "Kapsabet"
    ],
    "name:jpn_x_preferred":[
        "\u30ab\u30d7\u30b5\u30d9\u30c3\u30c8"
    ],
    "name:nld_x_preferred":[
        "Kapsabet"
    ],
    "name:nob_x_preferred":[
        "Kapsabet"
    ],
    "name:nor_x_preferred":[
        "Kapsabet"
    ],
    "name:pol_x_preferred":[
        "Kapsabet"
    ],
    "name:rus_x_preferred":[
        "\u041a\u0430\u043f\u0441\u0430\u0431\u0435\u0442"
    ],
    "name:spa_x_preferred":[
        "Kapsabet"
    ],
    "name:swa_x_preferred":[
        "Kapsabet"
    ],
    "name:swe_x_preferred":[
        "Kapsabet"
    ],
    "name:szl_x_preferred":[
        "Kapsabet"
    ],
    "name:und_x_variant":[
        "Nandi"
    ],
    "name:urd_x_preferred":[
        "\u06a9\u0627\u067e\u0633\u0627\u0628\u062a"
    ],
    "name:zho_x_preferred":[
        "\u5361\u666e\u85a9\u8c9d\u7279"
    ],
    "qs:gn_country":"KE",
    "qs:gn_fcode":"PPL",
    "qs:gn_pop":3758,
    "qs:name":"Kapsabet",
    "qs:name_adm0":"Kenya",
    "qs:name_adm1":"Rift Valley",
    "qs:photos":0,
    "qs:photos_1k":0,
    "qs:photos_9k":1,
    "qs:photos_9r":1,
    "qs:photos_all":1,
    "qs:photos_sr":0,
    "qs:placetype":"Town",
    "qs:pop_sr":"4",
    "qs:woe_adm0":23424863,
    "wd:wordcount":1056,
    "wof:name":"Kapsabet",
    "wof:placetype":"locality",
    "wof:population":3758
},
  "geometry": {"coordinates":[35.105,0.20387],"type":"Point"}
}