{
  "type": "Feature",
  "properties": {
    "iso:country":"KE",
    "name:dut_x_preferred":[
        "Cheberia"
    ],
    "name:eng_x_preferred":[
        "Cheberia"
    ],
    "name:swe_x_preferred":[
        "Chepareria"
    ],
    "name:unk_x_variant":[
        "Cheberia"
    ],
    "qs:gn_country":"KE",
    "qs:gn_fcode":"PPL",
    "qs:gn_pop":1073,
    "qs:name":"Chepareria",
    "qs:name_adm0":"Kenya",
    "qs:name_adm1":"Rift Valley",
    "qs:photos":0,
    "qs:photos_1k":0,
    "qs:photos_9k":0,
    "qs:photos_9r":0,
    "qs:photos_all":0,
    "qs:photos_sr":0,
    "qs:placetype":"Town",
    "qs:pop_sr":"3",
    "qs:woe_adm0":23424863,
    "wd:wordcount":139,
    "wof:name":"Chepareria",
    "wof:placetype":"locality",
    "wof:population":1073
},
  "geometry": {"coordinates":[35.2039,1.30774],"type":"Point"}
}