{
  "type": "Feature",
  "properties": {
    "gn:admin1_code":"48.0",
    "gn:asciiname":"Mwanathamba",
    "gn:country_code":"KE",
    "gn:dem":8,
    "gn:feature_class":"P",
    "gn:feature_code":"PPL",
    "gn:name":"Mwanathamba",
    "gn:population":0,
    "gn:timezone":"Africa/Nairobi",
    "iso:country":"KE",
    "name:und_x_variant":[
        "Mwanathumba",
        "Mwanathamba"
    ],
    "name:urd_x_preferred":[
        "\u0645\u0648\u0627\u0646\u0627\u062a\u06be\u0645\u0628\u0627"
    ],
    "wof:name":"Mwanathamba",
    "wof:placetype":"locality"
},
  "geometry": {"coordinates":[40.1974,-2.43333],"type":"Point"}
}