{
  "type": "Feature",
  "properties": {
    "gn:admin1_code":"48.0",
    "gn:asciiname":"Fanjua",
    "gn:country_code":"KE",
    "gn:dem":49,
    "gn:feature_class":"P",
    "gn:feature_code":"PPL",
    "gn:name":"Fanjua",
    "gn:population":0,
    "gn:timezone":"Africa/Nairobi",
    "iso:country":"KE",
    "wof:name":"Fanjua",
    "wof:placetype":"locality"
},
  "geometry": {"coordinates":[40.12245,-1.66066],"type":"Point"}
}