{
  "type": "Feature",
  "properties": {
    "gn:admin1_code":"33",
    "gn:asciiname":"Finno",
    "gn:country_code":"KE",
    "gn:dem":434,
    "gn:feature_class":"P",
    "gn:feature_code":"PPL",
    "gn:name":"Finno",
    "gn:population":0,
    "gn:timezone":"Africa/Nairobi",
    "iso:country":"KE",
    "name:und_x_variant":[
        "Berti Finno",
        "Burti Fino",
        "Finno"
    ],
    "wof:name":"Finno",
    "wof:placetype":"locality"
},
  "geometry": {"coordinates":[41.41588,3.38219],"type":"Point"}
}