{
  "type": "Feature",
  "properties": {
    "gn:admin1_code":"38.0",
    "gn:asciiname":"Githunguri",
    "gn:country_code":"KE",
    "gn:dem":1567,
    "gn:feature_class":"P",
    "gn:feature_code":"PPL",
    "gn:name":"Githunguri",
    "gn:population":0,
    "gn:timezone":"Africa/Nairobi",
    "iso:country":"KE",
    "wof:name":"Githunguri",
    "wof:placetype":"locality"
},
  "geometry": {"coordinates":[37.05,-0.73333],"type":"Point"}
}