{
  "type": "Feature",
  "properties": {
    "gn:admin1_code":"33",
    "gn:asciiname":"Waragalla",
    "gn:country_code":"KE",
    "gn:dem":581,
    "gn:feature_class":"P",
    "gn:feature_code":"PPL",
    "gn:name":"Waragalla",
    "gn:population":0,
    "gn:timezone":"Africa/Nairobi",
    "iso:country":"KE",
    "wof:name":"Waragalla",
    "wof:placetype":"locality"
},
  "geometry": {"coordinates":[41.00899,3.40951],"type":"Point"}
}