{
  "type": "Feature",
  "properties": {
    "gn:admin1_code":"38.0",
    "gn:asciiname":"Karuri",
    "gn:country_code":"KE",
    "gn:dem":1626,
    "gn:feature_class":"P",
    "gn:feature_code":"PPL",
    "gn:name":"Karuri",
    "gn:population":0,
    "gn:timezone":"Africa/Nairobi",
    "iso:country":"KE",
    "name:azb_x_preferred":[
        "\u06a9\u0627\u0631\u0648\u0631\u06cc"
    ],
    "name:ceb_x_preferred":[
        "Karuri"
    ],
    "name:fas_x_preferred":[
        "\u06a9\u0627\u0631\u0648\u0631\u06cc"
    ],
    "name:nor_x_preferred":[
        "Karuri"
    ],
    "name:pol_x_preferred":[
        "Karuri"
    ],
    "name:spa_x_preferred":[
        "Karuri"
    ],
    "name:swa_x_preferred":[
        "Karuri"
    ],
    "name:swe_x_preferred":[
        "Karuri"
    ],
    "name:urd_x_preferred":[
        "\u06a9\u0627\u0631\u0648\u0631\u06cc"
    ],
    "wof:name":"Karuri",
    "wof:placetype":"locality"
},
  "geometry": {"coordinates":[37.03333,-0.71667],"type":"Point"}
}