{
  "type": "Feature",
  "properties": {
    "gn:admin1_code":"30.0",
    "gn:asciiname":"Mangai",
    "gn:country_code":"KE",
    "gn:dem":10,
    "gn:feature_class":"P",
    "gn:feature_code":"PPL",
    "gn:name":"Mangai",
    "gn:population":0,
    "gn:timezone":"Africa/Nairobi",
    "iso:country":"KE",
    "wof:name":"Mangai",
    "wof:placetype":"locality"
},
  "geometry": {"coordinates":[41.17648,-1.74804],"type":"Point"}
}