{
  "type": "Feature",
  "properties": {
    "gn:admin1_code":"30.0",
    "gn:asciiname":"Mangai",
    "gn:country_code":"KE",
    "gn:dem":10,
    "gn:feature_class":"P",
    "gn:feature_code":"PPL",
    "gn:name":"Mangai",
    "gn:population":0,
    "gn:timezone":"Africa/Nairobi",
    "iso:country":"KE",
    "name:ben_x_preferred":[
        "\u09ae\u09be\u0982\u0997\u09be\u0987"
    ],
    "name:ceb_x_preferred":[
        "Mangai"
    ],
    "name:deu_x_preferred":[
        "Mangai"
    ],
    "name:ell_x_preferred":[
        "\u039c\u03b1\u03bd\u03b3\u03ba\u03ac\u03b9"
    ],
    "name:fas_x_preferred":[
        "\u0645\u0627\u0646\u06af\u0627\u06cc\u06cc"
    ],
    "name:fra_x_preferred":[
        "Mangai"
    ],
    "name:heb_x_preferred":[
        "\u05de\u05e0\u05d2\u05d0\u05d9"
    ],
    "name:hin_x_preferred":[
        "\u092e\u0902\u0917\u093e\u0908"
    ],
    "name:hun_x_preferred":[
        "Mangai"
    ],
    "name:ind_x_preferred":[
        "Mangai"
    ],
    "name:ita_x_preferred":[
        "Mangai"
    ],
    "name:kor_x_preferred":[
        "\ub9dd\uac00\uc774"
    ],
    "name:ron_x_preferred":[
        "Mangai"
    ],
    "name:rus_x_preferred":[
        "\u041c\u0430\u043d\u0433\u0435"
    ],
    "name:spa_x_preferred":[
        "Mangai"
    ],
    "name:swe_x_preferred":[
        "Mangai"
    ],
    "name:tur_x_preferred":[
        "Mangai"
    ],
    "name:ukr_x_preferred":[
        "\u041c\u0430\u043d\u0433\u0430\u0457"
    ],
    "name:urd_x_preferred":[
        "\u0645\u0627\u0646\u06af\u0627\u0626\u06cc"
    ],
    "name:vie_x_preferred":[
        "Mangai"
    ],
    "wof:name":"Mangai",
    "wof:placetype":"locality"
},
  "geometry": {"coordinates":[41.17648,-1.74804],"type":"Point"}
}