{
  "type": "Feature",
  "properties": {
    "gn:admin1_code":"32.0",
    "gn:asciiname":"Ngandani",
    "gn:country_code":"KE",
    "gn:dem":803,
    "gn:feature_class":"P",
    "gn:feature_code":"PPL",
    "gn:name":"Ngandani",
    "gn:population":0,
    "gn:timezone":"Africa/Nairobi",
    "iso:country":"KE",
    "wof:name":"Ngandani",
    "wof:placetype":"locality"
},
  "geometry": {"coordinates":[38.01667,-2.36667],"type":"Point"}
}