{
  "type": "Feature",
  "properties": {
    "gn:admin1_code":"38.0",
    "gn:asciiname":"Muthithi",
    "gn:country_code":"KE",
    "gn:dem":1512,
    "gn:feature_class":"P",
    "gn:feature_code":"PPL",
    "gn:name":"Muthithi",
    "gn:population":0,
    "gn:timezone":"Africa/Nairobi",
    "iso:country":"KE",
    "name:und_x_variant":[
        "Ndunyu",
        "Muthithi"
    ],
    "wof:name":"Muthithi",
    "wof:placetype":"locality"
},
  "geometry": {"coordinates":[37.07155,-0.81662],"type":"Point"}
}