{
  "type": "Feature",
  "properties": {
    "gn:admin1_code":"47.0",
    "gn:asciiname":"Maranu",
    "gn:country_code":"KE",
    "gn:dem":909,
    "gn:feature_class":"P",
    "gn:feature_code":"PPL",
    "gn:name":"Maranu",
    "gn:population":0,
    "gn:timezone":"Africa/Nairobi",
    "iso:country":"KE",
    "wof:name":"Maranu",
    "wof:placetype":"locality"
},
  "geometry": {"coordinates":[37.69229,-3.39096],"type":"Point"}
}