{
  "type": "Feature",
  "properties": {
    "gn:admin1_code":"51.0",
    "gn:asciiname":"Lokichar",
    "gn:country_code":"KE",
    "gn:dem":763,
    "gn:feature_class":"P",
    "gn:feature_code":"PPL",
    "gn:name":"Lokichar",
    "gn:population":0,
    "gn:timezone":"Africa/Nairobi",
    "iso:country":"KE",
    "name:azb_x_preferred":[
        "\u0644\u0648\u06a9\u06cc\u0686\u0627\u0631"
    ],
    "name:fas_x_preferred":[
        "\u0644\u0648\u06a9\u06cc\u0686\u0627\u0631"
    ],
    "wof:name":"Lokichar",
    "wof:placetype":"locality"
},
  "geometry": {"coordinates":[35.65123,2.38116],"type":"Point"}
}