{
  "type": "Feature",
  "properties": {
    "gn:admin1_code":"27.0",
    "gn:asciiname":"Kilawa",
    "gn:country_code":"KE",
    "gn:dem":898,
    "gn:feature_class":"P",
    "gn:feature_code":"PPL",
    "gn:name":"Kilawa",
    "gn:population":0,
    "gn:timezone":"Africa/Nairobi",
    "iso:country":"KE",
    "wof:name":"Kilawa",
    "wof:placetype":"locality"
},
  "geometry": {"coordinates":[38.08113,-2.14073],"type":"Point"}
}