{
  "type": "Feature",
  "properties": {
    "gn:admin1_code":"41.0",
    "gn:asciiname":"Lemek",
    "gn:country_code":"KE",
    "gn:dem":1895,
    "gn:feature_class":"P",
    "gn:feature_code":"PPL",
    "gn:name":"Lemek",
    "gn:population":0,
    "gn:timezone":"Africa/Nairobi",
    "iso:country":"KE",
    "wof:name":"Lemek",
    "wof:placetype":"locality"
},
  "geometry": {"coordinates":[35.38243,-1.10723],"type":"Point"}
}