{
  "type": "Feature",
  "properties": {
    "gn:admin1_code":"10.0",
    "gn:asciiname":"Kapkalelwa",
    "gn:country_code":"KE",
    "gn:dem":1371,
    "gn:feature_class":"P",
    "gn:feature_code":"PPL",
    "gn:name":"Kapkalelwa",
    "gn:population":0,
    "gn:timezone":"Africa/Nairobi",
    "iso:country":"KE",
    "wof:name":"Kapkalelwa",
    "wof:placetype":"locality"
},
  "geometry": {"coordinates":[35.71973,0.37195],"type":"Point"}
}