{
  "type": "Feature",
  "properties": {
    "gn:admin1_code":"22.0",
    "gn:asciiname":"Miguta",
    "gn:country_code":"KE",
    "gn:dem":1777,
    "gn:feature_class":"P",
    "gn:feature_code":"PPL",
    "gn:name":"Miguta",
    "gn:population":0,
    "gn:timezone":"Africa/Nairobi",
    "iso:country":"KE",
    "wof:name":"Miguta",
    "wof:placetype":"locality"
},
  "geometry": {"coordinates":[36.83376,-1.06821],"type":"Point"}
}