{
  "type": "Feature",
  "properties": {
    "gn:admin1_code":"38.0",
    "gn:asciiname":"Nyati",
    "gn:country_code":"KE",
    "gn:dem":1332,
    "gn:feature_class":"P",
    "gn:feature_code":"PPL",
    "gn:name":"Nyati",
    "gn:population":0,
    "gn:timezone":"Africa/Nairobi",
    "iso:country":"KE",
    "name:und_x_variant":[
        "Nyali",
        "Nyati"
    ],
    "wof:name":"Nyati",
    "wof:placetype":"locality"
},
  "geometry": {"coordinates":[37.18333,-0.85],"type":"Point"}
}