{
  "type": "Feature",
  "properties": {
    "gn:admin1_code":"19",
    "gn:asciiname":"Elangata Wuas",
    "gn:country_code":"KE",
    "gn:dem":1425,
    "gn:feature_class":"P",
    "gn:feature_code":"PPL",
    "gn:name":"Elangata Wuas",
    "gn:population":0,
    "gn:timezone":"Africa/Nairobi",
    "iso:country":"KE",
    "name:und_x_variant":[
        "Mile 46",
        "Elangata Wuas"
    ],
    "wof:name":"Elangata Wuas",
    "wof:placetype":"locality"
},
  "geometry": {"coordinates":[36.58825,-1.89098],"type":"Point"}
}