{
  "type": "Feature",
  "properties": {
    "gn:admin1_code":"24.0",
    "gn:asciiname":"Kiamutugu",
    "gn:country_code":"KE",
    "gn:dem":1570,
    "gn:feature_class":"P",
    "gn:feature_code":"PPL",
    "gn:name":"Kiamutugu",
    "gn:population":0,
    "gn:timezone":"Africa/Nairobi",
    "iso:country":"KE",
    "name:und_x_variant":[
        "Kiamatogo",
        "Kiamatugu",
        "Kiamutugu"
    ],
    "wof:name":"Kiamutugu",
    "wof:placetype":"locality"
},
  "geometry": {"coordinates":[37.39053,-0.46718],"type":"Point"}
}