{
  "type": "Feature",
  "properties": {
    "gn:admin1_code":"32.0",
    "gn:asciiname":"Kyeni Kya Kai",
    "gn:country_code":"KE",
    "gn:dem":958,
    "gn:feature_class":"P",
    "gn:feature_code":"PPL",
    "gn:name":"Kyeni Kya Kai",
    "gn:population":0,
    "gn:timezone":"Africa/Nairobi",
    "iso:country":"KE",
    "wof:name":"Kyeni Kya Kai",
    "wof:placetype":"locality"
},
  "geometry": {"coordinates":[37.87215,-2.25989],"type":"Point"}
}