{
  "type": "Feature",
  "properties": {
    "gn:admin1_code":"28.0",
    "gn:asciiname":"Kibaya",
    "gn:country_code":"KE",
    "gn:dem":92,
    "gn:feature_class":"P",
    "gn:feature_code":"PPL",
    "gn:name":"Kibaya",
    "gn:population":0,
    "gn:timezone":"Africa/Nairobi",
    "iso:country":"KE",
    "name:ron_x_preferred":[
        "Kibaya"
    ],
    "wof:name":"Kibaya",
    "wof:placetype":"locality"
},
  "geometry": {"coordinates":[39.12313,-4.47344],"type":"Point"}
}