{
  "type": "Feature",
  "properties": {
    "gn:admin1_code":"44.0",
    "gn:asciiname":"Kariara",
    "gn:country_code":"KE",
    "gn:dem":1380,
    "gn:feature_class":"P",
    "gn:feature_code":"PPL",
    "gn:name":"Kariara",
    "gn:population":0,
    "gn:timezone":"Africa/Nairobi",
    "iso:country":"KE",
    "name:und_x_variant":[
        "Karuiro",
        "Kariara"
    ],
    "wof:name":"Kariara",
    "wof:placetype":"locality"
},
  "geometry": {"coordinates":[37.14277,-0.61017],"type":"Point"}
}