{
  "type": "Feature",
  "properties": {
    "gn:admin1_code":"31.0",
    "gn:asciiname":"Kalasa",
    "gn:country_code":"KE",
    "gn:dem":1150,
    "gn:feature_class":"P",
    "gn:feature_code":"PPL",
    "gn:name":"Kalasa",
    "gn:population":0,
    "gn:timezone":"Africa/Nairobi",
    "iso:country":"KE",
    "name:cat_x_preferred":[
        "Kalasa"
    ],
    "name:kan_x_preferred":[
        "\u0c95\u0cb3\u0cb8"
    ],
    "name:san_x_preferred":[
        "\u0915\u0933\u0938"
    ],
    "wof:name":"Kalasa",
    "wof:placetype":"locality"
},
  "geometry": {"coordinates":[37.66667,-1.53333],"type":"Point"}
}