{
  "type": "Feature",
  "properties": {
    "gn:admin1_code":"22.0",
    "gn:asciiname":"Wabuga",
    "gn:country_code":"KE",
    "gn:dem":1881,
    "gn:feature_class":"P",
    "gn:feature_code":"PPL",
    "gn:name":"Wabuga",
    "gn:population":0,
    "gn:timezone":"Africa/Nairobi",
    "iso:country":"KE",
    "wof:name":"Wabuga",
    "wof:placetype":"locality"
},
  "geometry": {"coordinates":[36.71667,-1.23333],"type":"Point"}
}