{
  "type": "Feature",
  "properties": {
    "gn:admin1_code":"48.0",
    "gn:asciiname":"Yedi",
    "gn:country_code":"KE",
    "gn:dem":93,
    "gn:feature_class":"P",
    "gn:feature_code":"PPL",
    "gn:name":"Yedi",
    "gn:population":0,
    "gn:timezone":"Africa/Nairobi",
    "iso:country":"KE",
    "wof:name":"Yedi",
    "wof:placetype":"locality"
},
  "geometry": {"coordinates":[39.88333,-1.03333],"type":"Point"}
}